Workbook

Sheet 2017 
A1: 项目经营管理台账（2017年）（电子）
A2: 序号 | B2: 项目信息 | E2: 经营信息 | J2: 概算信息（估算） | M2: 审计信息 | P2: 甲方支付信息 | W2: 公司收支信息 | AF2: 备注
B3: 项目名称 | C3: 项目概况 | D3: 项目编号 | E3: 甲方单位 | F3: 联系人 | G3: 联系方式 | H3: 经营 负责人 | I3: 经营 参与人 | J3: 设计费（元） | K3: 勘察费（元） | L3: 可研费（元） | M3: 设计费（元） | N3: 勘察费（元） | O3: 可研费（元） | P3: 合同/补充协议额（元） | T3: 应支额（元） | W3: 应收额（元） | X3: 收款信息 | Z3: 支付信息 | AE3: 公司结余 （元）
P4: 设计费（元） | Q4: 勘察费（元） | R4: 可研费（元） | S4: 补充协议额（元） | U4: 支付金额（元） | V4: 未收金额（元） | X4: 实收金额（元） | Y4: 未收金额（元） | Z4: 单位 （个人） | AA4: 内容 | AB4: 金额（元） | AC4: 经营奖金（元） | AD4: 生产奖金（元）
A5: 1 | B5: 房山区108国道大修工程（峡峪口桥-十霞路）K73+900-K104+330 | C5: 二级路、30km | D5: HNJH2017-001 | E5: 房山公路局 | F5: 白秀龙 | G5: 13811745176 | H5: 杨建东 | I5: 王新星 | J5: 744841 | K5: 304570 | L5: 0 | M5: =INT(J5*0.99) -> 737392 | N5: =INT(K5*0.99) -> 301524 | O5: =INT(L5*0.99) -> 0 | P5: =M5 -> 737392 | Q5: =N5 -> 301524 | R5: =O5 -> 0 | S5: =P5+Q5+R5 -> 1038916 | T5: =S5 -> 1038916 | U5: 311674 | V5: =T5-U5-U6-U7 -> 0 | W5: =S5*0.8 -> 831132.8 | X5: =U5*0.8 -> 249339.2 | Y5: =W5-X5-X6-X7 -> 0 | Z5: 刘素良 | AA5: 测量 | AB5: 76075 | AC5: =77918.7+22841.87+28018.79+16668.8 -> 145448.16 | AD5: =44243.52+13273.06+15902.12+9464.82 -> 82883.52 | AE5: =W5-AB5-AB6-AB7-AC5-AD5 -> 481874.12 | AG5: =AC5/T5 -> 0.13999992 | AH5: =AD5/W5 -> 0.099723558
U6: 415566 | X6: =U6*0.8 -> 332452.8 | AA6: 取芯 | AB6: =15*150 -> 2250
U7: 311676 | X7: =U7*0.8 -> 249340.8 | Z7: 瑞通十九处 | AA7: 路况 | AB7: 42602
A8: 2 | B8: 房山区108国道大修工程（涞宝路-市界）K120+850-139+450 | C8: 二级路、15km | D8: HNJH2017-002 | E8: 房山公路局 | F8: 白秀龙 | G8: 13811745176 | H8: 杨建东 | I8: 王新星 | J8: 632486 | K8: 187280 | L8: 0 | M8: 624894 | N8: 185407 | O8: =INT(L8*0.99) -> 0 | P8: =M8 -> 624894 | Q8: =N8 -> 185407 | R8: =O8 -> 0 | S8: =P8+Q8+R8 -> 810301 | T8: =S8 -> 810301 | U8: 243470 | V8: =S8-U8-U9-U10 -> 0 | W8: =S8*0.8 -> 648240.8 | X8: =U8*0.8 -> 194776 | Y8: =W8-X8-X9-X10 -> 0 | Z8: 刘素梁 | AA8: 测绘 | AB8: 46500 | AC8: =60867.6+3233.13+49518.75 -> 113619.48 | AD8: =37569.66+2003.72+30567.13 -> 70140.51 | AE8: =W8-AB8-AB9-AB10-AC8-AD8 -> 385820.81 | AG8: =AC8/T8 -> 0.14021886 | AH8: =AD8/W8 -> 0.10820132
U9: 324627 | X9: =U9*0.8 -> 259701.6 | Z9: 刘素梁 | AA9: 取芯 | AB9: =16*150 -> 2400
U10: 242204 | X10: =U10*0.8 -> 193763.2 | Z10: 瑞通十九处 | AA10: 路况 | AB10: 29760
A11: 4 | B11: 房山区良三路大修工程（K4+500-K8+500) | C11: 一级路、3.956km | D11: HNJH2017-004 | E11: 房山公路局 | F11: 白秀龙 | G11: 13811745176 | H11: 王新星 | I11: 王新星 | J11: 552573.9 | K11: 59340 | L11: 0 | M11: 552573.9 | N11: 59340 | O11: =INT(L11*0.99) -> 0 | P11: =M11 -> 552573.9 | Q11: =N11 -> 59340 | R11: =O11 -> 0 | S11: =P11+Q11+R11 -> 611913.9 | T11: =S11 -> 611913.9 | U11: 183573.9 | V11: =S11-U11-U12-U13 -> 0 | W11: =S11*0.8 -> 489531.12 | X11: =U11*0.8 -> 146859.12 | Y11: =W11-X11-X12-X13 -> 0 | Z11: 刘素良 | AA11: 测量 | AB11: =50000-AB12 -> 47300 | AC11: =45893.48+39774.31 -> 85667.79 | AD11: =33154.38+28733.76 -> 61888.14 | AE11: =W11-AB11-AB12-AB13-AC11-AD11 -> 277655.19 | AG11: =AC11/T11 -> 0.13999975 | AH11: =AD11/W11 -> 0.1264233
U12: 244765 | X12: =U12*0.8 -> 195812 | Z12: 刘素良 | AA12: 取芯 | AB12: =18*150 -> 2700
U13: 183575 | X13: =U13*0.8 -> 146860 | Z13: 瑞通十九处 | AA13: 路况 | AB13: 14320
A14: 6 | B14: 延庆区滦赤路大修工程（K108+890-K129+000) | C14: 三级路、20.11km | D14: HNJH2017-006 | E14: 延庆公路局 | F14: 吴颖 | G14: 13488805779 | H14: 杨建东 | I14: 王新星 | J14: 449664 | K14: 213100 | L14: 0 | M14: 445167 | N14: 210969 | O14: 0 | P14: =M14 -> 445167 | Q14: =N14 -> 210969 | R14: =O14 -> 0 | S14: =P14+Q14+R14 -> 656136 | T14: =S14 -> 656136 | U14: 411294 | V14: =S14-U14-U15-U16 -> 0 | W14: =S14*0.8 -> 524908.8 | X14: =U14*0.8 -> 329035.2 | Y14: =W14-X14-X15-X16 -> 0 | Z14: 刘素良 | AA14: 测量 | AB14: =20.11*2500 -> 50275 | AC14: =12465.8+49210.2+42488.05+18159.75+10450 -> 132773.8 | AD14: =6980.85+27557.71+23113.5+9793.67+2840.18 -> 70285.91 | AE14: =W14-AB14-AB15-AB16-AC14-AD14 -> 253086.09 | AG14: =AC14/T14 -> 0.20235713 | AH14: =AD14/W14 -> 0.13390118
U15: 200325 | X15: =U15*0.8 -> 160260 | AA15: 取芯 | AB15: =16*150 -> 2400
U16: 44517 | X16: =U16*0.8 -> 35613.6 | Z16: 瑞通十九处 | AA16: 路况 | AB16: =20.11*800 -> 16088
A17: 7 | B17: 2018年通州区普通公路养护工程勘察设计-2标，通州区漷马路大修工程（K9+480-K21+000)，转中修漷马路（K10+000-K16+000）中修工程 | C17: 二、三级路、11.52km(方案） | D17: HNJH2017-007 | E17: 通州公路局 | F17: 张伟 | G17: 13439987630 | H17: 王新星 | I17: 王新星 | J17: 623024 | K17: 94960 | L17: 0 | M17: 199017 | N17: 48000 | O17: 0 | P17: =M17 -> 199017 | Q17: =N17 -> 48000 | R17: =O17 -> 0 | S17: =P17+Q17+R17 -> 247017 | T17: =S17 -> 247017 | U17: 247017 | V17: =T17-U17 -> 0 | W17: =S17*0.8 -> 197613.6 | X17: =U17*0.8 -> 197613.6 | Y17: =W17-X17 -> 0 | Z17: 刘素良 | AA17: 测量 | AB17: =6*2500 -> 15000 | AC17: =61754.25 -> 61754.25 | AD17: =31842.72 -> 31842.72 | AE17: =W17-AB17-AB18-AB19-AC17-AD17 -> 78000.63 | AG17: =AC17/T17 -> 0.25 | AH17: =AD17/W17 -> 0.16113628
AA18: 取芯 | AB18: =12*150 -> 1800
Z19: 瑞通十九处 | AA19: 路况 | AB19: =5.52*800+6*800 -> 9216
A20: 8 | B20: 2018年通州区普通公路养护工程勘察设计-2标，通州区觅西路大修工程（K0+000-K10+000) | C20: 二级路、10.54km | D20: HNJH2017-008 | E20: 通州公路局 | F20: 张伟 | G20: 13439987630 | H20: 王新星 | I20: 王新星 | J20: 783827 | K20: 105400 | L20: 0 | M20: 775989 | N20: 104346 | O20: 0 | P20: =M20 -> 775989 | Q20: =N20 -> 104346 | R20: =O20 -> 0 | S20: =P20+Q20+R20 -> 880335 | T20: =S20 -> 880335 | U20: 792301.5 | V20: =S20-U20-U21 -> 0 | W20: =S20*0.8 -> 704268 | X20: =U20*0.8 -> 633841.2 | Y20: =W20-X20-X21 -> 0 | Z20: 刘素良 | AA20: 测量 | AB20: 26350 | AC20: =66025.13+66125+4699.39+5272.94+16337.85 -> 158460.31 | AD20: =46559.34+46552+3103.96+3103.96+11521.06+15419.61 -> 126259.93 | AE20: =W20-AB20-AB21-AB22-AC20-AD20 -> 373369.76 | AG20: =AC20/T20 -> 0.18000001 | AH20: =AD20/W20 -> 0.17927824
U21: 88033.5 | X21: =U21*0.8 -> 70426.8 | AA21: 取芯 | AB21: 1950
Z22: 十九处 | AA22: 弯沉 | AB22: =10500+7378 -> 17878
A23: 9 | B23: 石桥片区、果园片区区域环境提升工程 | C23: 果园片区 | D23: HBJH2017-009 | E23: 密云园林绿化服务中心 | F23: 王辉 | G23: 13681368593 | H23: 杨建东 | I23: 杨建东 | M23: 61686.63 | N23: 0 | O23: 0 | P23: 61686.63 | Q23: 0 | R23: 0 | S23: =Q23 -> 0 | T23: =P23+Q23+R23 -> 61686.63 | U23: 61686.63 | V23: =T23-U23 -> 0 | W23: =T23*0.6 -> 37011.978 | X23: =37011.98 -> 37011.98 | Y23: =W23-X23 -> -0.002 | AC23: 17484.25 | AD23: =7063.64+12588.66-12588.66-7063.64+3738.21+6662.16 -> 10400.37 | AE23: =W23-AC23-AD23-AB23-AB24-AB25 -> 9127.358 | AG23: =AC23/T23 -> 0.28343662 | AH23: =AD23/W23 -> 0.28100011
C24: 石桥片区一
C25: 石桥片区二
C26: 石桥片区-微森公园 | M26: 275821.71 | N26: 0 | O26: 0 | P26: 275821.71 | Q26: 0 | R26: 0 | S26: =P26+Q26+R26 -> 275821.71 | T26: =S26 -> 275821.71 | U26: =T26 -> 275821.71 | V26: =T26-U26-U27 -> 0 | W26: =INT(S26*0.6) -> 165493 | X26: =W26 -> 165493 | Y26: =W26-X26 -> 0 | AD26: =41373.26 -> 41373.26 | AE26: =W26-AB26-AB27-AC26-AD26 -> 124119.74 | AG26: =AC26/T26 -> 0 | AH26: =AD26/W26 -> 0.25000006
B28: 水源路环境提升工程（二标段） | C28: 水源路4l | J28: 1424700 | K28: 108300 | L28: 0 | M28: 797775.73 | N28: 0 | O28: 0 | P28: 797775.73 | Q28: 0 | R28: 0 | S28: =P28+Q28+R28 -> 797775.73 | T28: =S28 -> 797775.73 | U28: =389093.86 -> 389093.86 | V28: =T28-U28-U29-U30 -> 0 | W28: =T28*0.75 -> 598331.8 | X28: 300000 | Y28: =W28-X28-X29-X30 -> -0.0025 | AC28: =90000+93300+29304.56 -> 212604.56 | AD28: =27500+60000+20256.34+45014.08+19536.37 -> 172306.79 | AE28: =W28-AB28-AB29-AB30-AC28-AD28 -> 213420.45 | AG28: =AC28/T28 -> 0.26649665 | AH28: =AD28/W28 -> 0.28797866
U29: 311000 | X29: 225070.4
U30: 97681.87 | X30: 73261.4
A31: 10 | B31: 物华科技综合楼项目道路开口设计工程 | C31: 开口 | D31: HXJH2017-010 | E31: 北京万华置业有限公司 | H31: 马旭 | I31: 马旭 | J31: 160000 | K31: 0 | L31: 0 | M31: 160000 | N31: 0 | O31: 0 | P31: 160000 | Q31: 0 | R31: 0 | S31: =P31+Q31+R31 -> 160000 | T31: =S31 -> 160000 | U31: =J31 -> 160000 | V31: =T31-U31 -> 0 | W31: =U31*0.81 -> 129600 | X31: 129600 | Y31: =W31-X31 -> 0 | Z31: 马旭 | AA31: 设计咨询 | AB31: =U31*0.75 -> 120000 | AE31: =W31-AB31 -> 9600 | AF31: 帮忙马旭
A32: 11 | B32: 2017年通州区年乡村公路安全生命防护工程 | C32: 9个乡镇，202条道路 | D32: HXJH2017-011 | E32: 通州公路局 | F32: 潘宝龙 | G32: 13810052975 | H32: 王新星 | I32: 王新星 | J32: 336092 | K32: 0 | L32: 0 | M32: 213641 | N32: 0 | O32: 0 | P32: 213641 | Q32: 0 | R32: 0 | S32: =P32+Q32+R32 -> 213641 | T32: =S32 -> 213641 | U32: =T32 -> 213641 | V32: =T32-U32 -> 0 | W32: =U32*0.81 -> 173049.21 | X32: 173049.21 | Y32: =W32-X32 -> 0 | AC32: 53410 | AD32: 34609.84 | AE32: =W32-AC32-AD32-AB32 -> 85029.37 | AG32: =AC32/T32 -> 0.24999883 | AH32: =AD32/W32 -> 0.19999999
A33: 12 | B33: 通州区2018年公路桥梁改建工程（张家湾镇北凉运桥） | C33: 桥长12.5米，宽10米，现浇实心板梁 | D33: HXJH2017-012 | E33: 通州公路局 | F33: 潘宝龙 | G33: 13810052975 | H33: 王新星 | I33: 王新星 | J33: 147562 | M33: 60348 | P33: =M33 -> 60348 | S33: =P33 -> 60348 | T33: =S33 -> 60348 | U33: 0 | V33: =T33-U33 -> 60348 | W33: =T33*0.8 -> 48278.4 | X33: =W33 -> 48278.4 | Y33: =W33-X33 -> 0
A34: 14 | B34: 通州区燃气管线回填道路恢复工程 | C34: 胡郎路（变更后）三级公路4.41km | D34: HXJH2017-014 | E34: 燃气基建公司 | H34: 王新星 | I34: 王新星 | J34: 199344 | K34: 35280 | L34: 0 | M34: 199344 | N34: 35280 | O34: 0 | P34: 199344 | Q34: 35280 | R34: 0 | S34: =P34+Q34 -> 234624 | T34: =S34 -> 234624 | U34: =T34 -> 234624 | V34: =T34-U34 -> 0 | W34: =U34*0.81 -> 190045.44 | X34: =W34 -> 190045.44 | Y34: =W34-X34 -> 0 | AC34: =64100.5+7839.5+69391.75+33638.75 -> 174970.5 | AD34: =5471.6+39860.4+45317.4+23567 -> 114216.4 | AE34: =W34+W35+W36+W37+W38-AC34-AD34 -> 277717.52
C35: 潞城中路（定向钻）二级公路1.57km | D35: HXJH2017-014 | E35: 燃气基建公司 | H35: 王新星 | I35: 王新星 | J35: 27243 | K35: 15700 | L35: 0 | M35: 27243 | N35: 15700 | O35: 0 | P35: 27243 | Q35: 15700 | R35: 0 | S35: =P35+Q35 -> 42943 | T35: =S35 -> 42943 | U35: =T35 -> 42943 | V35: =T35-U35 -> 0 | W35: =U35*0.81 -> 34783.83 | X35: =W35 -> 34783.83 | Y35: =W35-X35 -> 0
C36: 潞西路三级公路2.09km | D36: HXJH2017-014 | E36: 燃气基建公司 | H36: 王新星 | I36: 王新星 | J36: 117835 | K36: 16720 | L36: 0 | M36: 117835 | N36: 16720 | O36: 0 | P36: 117835 | Q36: 16720 | R36: 0 | S36: =P36+Q36 -> 134555 | T36: =S36 -> 134555 | U36: =T36 -> 134555 | V36: =T36-U36 -> 0 | W36: =U36*0.81 -> 108989.55 | X36: =W36 -> 108989.55 | Y36: =W36-X36 -> 0
C37: 张凤路（明开）二级公路3.72km，（定向钻）二级公路2.65km | D37: HXJH2017-014 | E37: 燃气基建公司 | H37: 王新星 | I37: 王新星 | J37: 199302 | K37: 57100 | L37: 0 | M37: 199302 | N37: 57100 | O37: 0 | P37: 199302 | Q37: 57100 | R37: 0 | S37: =P37+Q37 -> 256402 | T37: =S37 -> 256402 | U37: =T37 -> 256402 | V37: =T37-U37 -> 0 | W37: =U37*0.81 -> 207685.62 | X37: =W37 -> 207685.62 | Y37: =W37-X37 -> 0
C38: 漷马路三级公路0.50km | D38: HXJH2017-014 | E38: 燃气基建公司 | H38: 王新星 | I38: 王新星 | J38: 27358 | K38: 4000 | L38: 0 | M38: 27358 | N38: 4000 | O38: 0 | P38: 27358 | Q38: 4000 | R38: 0 | S38: =P38+Q38 -> 31358 | T38: =S38 -> 31358 | U38: =T38 -> 31358 | V38: =T38-U38 -> 0 | W38: =U38*0.81 -> 25399.98 | X38: =W38 -> 25399.98 | Y38: =W38-X38 -> 0
A39: 15 | B39: 2018年张家湾镇乡村公路（16条道路） | C39: 大小北关路，2.794km | D39: HNJH2017-015L01S | E39: 张湾公路站 | F39: 卢世茹 | G39: 13520175981 | H39: 王新星 | I39: 王新星 | J39: 305803.4 | K39: 35508 | L39: 0 | M39: 104954.52 | N39: 0 | O39: 0 | P39: 104954.52 | Q39: 0 | R39: 0 | S39: =P39+Q39 -> 104954.52 | T39: =S39 -> 104954.52 | U39: =T39 -> 104954.52 | V39: =T39-U39 -> 0 | W39: =U39*0.81 -> 85013.161 | X39: =W39 -> 85013.161 | Y39: =W39-X39 -> 0 | Z39: 刘素良 | AA39: 测量 | AB39: =18.864*1500 -> 28296 | AC39: =3462.8+45565.96+34434.04+100702.65 -> 184165.45 | AD39: =27702.4+27702.4+35467.25+26522.85+40648.52 -> 158043.42 | AE39: =W39+W40+W41+W42+W43+W44+W45+W46+W47+W48+W49+W50+W51+W52+W53-AB40-AB39-AC39-AD39 -> 369515.18 | AG39: =SUM(T39:T53) -> 920827.22 | AH39: =SUM(W39:W53) -> 745870.05
C40: 小北关东路，0.833km | D40: HNJH2017-015L02S | J40: 87694.56 | K40: 11867 | L40: 0 | M40: 28070.73 | N40: 0 | O40: 0 | P40: 28070.73 | Q40: 0 | R40: 0 | S40: =P40+Q40 -> 28070.73 | T40: =S40 -> 28070.73 | U40: =T40 -> 28070.73 | V40: =T40-U40 -> 0 | W40: =U40*0.81 -> 22737.291 | X40: =W40 -> 22737.291 | Y40: =W40-X40 -> 0 | AA40: 取芯 | AB40: =39*150 -> 5850
C41: 小北关北路，1.117km | D41: HNJH2017-015L03S | J41: 111553.36 | K41: 12176.26 | L41: 0 | M41: 39492.33 | N41: 0 | O41: 0 | P41: 39492.33 | Q41: 0 | R41: 0 | S41: =P41+Q41 -> 39492.33 | T41: =S41 -> 39492.33 | U41: =T41 -> 39492.33 | V41: =T41-U41 -> 0 | W41: =U41*0.81 -> 31988.787 | X41: =W41 -> 31988.787 | Y41: =W41-X41 -> 0 | AG41: =AC39/AG39 -> 0.20000001 | AH41: =AD39/AH39 -> 0.21189136
C42: 瓜厂路，1.38km | D42: HNJH2017-015L04S | J42: 298926.55 | K42: 16614.86 | L42: 0 | M42: 101491.48 | N42: 0 | O42: 0 | P42: 101491.48 | Q42: 0 | R42: 0 | S42: =P42+Q42 -> 101491.48 | T42: =S42 -> 101491.48 | U42: =T42 -> 101491.48 | V42: =T42-U42 -> 0 | W42: =U42*0.81 -> 82208.099 | X42: =W42 -> 82208.099 | Y42: =W42-X42 -> 0
C43: 样田东路，1.39km | D43: HNJH2017-015L05S | J43: 182141.5 | K43: 19382.37 | L43: 0 | M43: 133530.08 | N43: 0 | O43: 0 | P43: 133530.08 | Q43: 0 | R43: 0 | S43: =P43+Q43 -> 133530.08 | T43: =S43 -> 133530.08 | U43: =T43 -> 133530.08 | V43: =T43-U43 -> 0 | W43: =U43*0.81 -> 108159.36 | X43: =W43 -> 108159.36 | Y43: =W43-X43 -> 0
C44: 沿上路，0.449km | D44: HNJH2017-015L06S | J44: 108911.88 | K44: 5953.25 | L44: 0 | M44: 38443.53 | N44: 0 | O44: 0 | P44: 38443.53 | Q44: 0 | R44: 0 | S44: =P44+Q44 -> 38443.53 | T44: =S44 -> 38443.53 | U44: =T44 -> 38443.53 | V44: =T44-U44 -> 0 | W44: =U44*0.81 -> 31139.259 | X44: =W44 -> 31139.259 | Y44: =W44-X44 -> 0
C45: 中街南路，1.412km | D45: HNJH2017-015L07S | J45: 123254.78 | K45: 15760.72 | L45: 0 | M45: 45475.57 | N45: 0 | O45: 0 | P45: 45475.57 | Q45: 0 | R45: 0 | S45: =P45+Q45 -> 45475.57 | T45: =S45 -> 45475.57 | U45: =T45 -> 45475.57 | V45: =T45-U45 -> 0 | W45: =U45*0.81 -> 36835.212 | X45: =W45 -> 36835.212 | Y45: =W45-X45 -> 0
C46: 中街西路，1.543km | D46: HNJH2017-015L08S | J46: 138893.74 | K46: 16745.87 | L46: 0 | M46: 50209.37 | N46: 0 | O46: 0 | P46: 50209.37 | Q46: 0 | R46: 0 | S46: =P46+Q46 -> 50209.37 | T46: =S46 -> 50209.37 | U46: =T46 -> 50209.37 | V46: =T46-U46 -> 0 | W46: =U46*0.81 -> 40669.59 | X46: =W46 -> 40669.59 | Y46: =W46-X46 -> 0
C47: 三间房路，1.114km | D47: HNJH2017-015L09S | J47: 139380.98 | K47: 11596.05 | L47: 0 | M47: 48763.31 | N47: 0 | O47: 0 | P47: 48763.31 | Q47: 0 | R47: 0 | S47: =P47+Q47 -> 48763.31 | T47: =S47 -> 48763.31 | U47: =T47 -> 48763.31 | V47: =T47-U47 -> 0 | W47: =U47*0.81 -> 39498.281 | X47: =W47 -> 39498.281 | Y47: =W47-X47 -> 0
C48: 高营路，0.424km | D48: HNJH2017-015L10S | J48: 92871.044 | K48: 8845.85 | L48: 0 | M48: 26104.11 | N48: 0 | O48: 0 | P48: 26104.11 | Q48: 0 | R48: 0 | S48: =P48+Q48 -> 26104.11 | T48: =S48 -> 26104.11 | U48: =T48 -> 26104.11 | V48: =T48-U48 -> 0 | W48: =U48*0.81 -> 21144.329 | X48: =W48 -> 21144.329 | Y48: =W48-X48 -> 0
C49: 垡头南街，1.944km | D49: HNJH2017-015L11S | J49: 296367.16 | K49: 21264.47 | L49: 0 | M49: 96869.06 | N49: 0 | O49: 0 | P49: 96869.06 | Q49: 0 | R49: 0 | S49: =P49+Q49 -> 96869.06 | T49: =S49 -> 96869.06 | U49: =T49 -> 96869.06 | V49: =T49-U49 -> 0 | W49: =U49*0.81 -> 78463.939 | X49: =W49 -> 78463.939 | Y49: =W49-X49 -> 0
C50: 中街东路，0.44km | D50: HNJH2017-015L12S | J50: 34237.464 | K50: 6993.96 | L50: 0 | M50: 12446.46 | N50: 0 | O50: 0 | P50: 12446.46 | Q50: 0 | R50: 0 | S50: =P50+Q50 -> 12446.46 | T50: =S50 -> 12446.46 | U50: =T50 -> 12446.46 | V50: =T50-U50 -> 0 | W50: =U50*0.81 -> 10081.633 | X50: =W50 -> 10081.633 | Y50: =W50-X50 -> 0
C51: 枣林庄外围路，0.862km | D51: HNJH2017-015L13S | J51: 200526.91 | K51: 9625.07 | L51: 0 | M51: 65388.77 | N51: 0 | O51: 0 | P51: 65388.77 | Q51: 0 | R51: 0 | S51: =P51+Q51 -> 65388.77 | T51: =S51 -> 65388.77 | U51: =T51 -> 65388.77 | V51: =T51-U51 -> 0 | W51: =U51*0.81 -> 52964.904 | X51: =W51 -> 52964.904 | Y51: =W51-X51 -> 0
C52: 坨堤西路，1.878km | D52: HNJH2017-015L14S | J52: 321939.65 | K52: 21601.66 | L52: 0 | M52: 108131.44 | N52: 0 | O52: 0 | P52: 108131.44 | Q52: 0 | R52: 0 | S52: =P52+Q52 -> 108131.44 | T52: =S52 -> 108131.44 | U52: =T52 -> 108131.44 | V52: =T52-U52 -> 0 | W52: =U52*0.81 -> 87586.466 | X52: =W52 -> 87586.466 | Y52: =W52-X52 -> 0
C53: 牌楼营路，0.629km | D53: HNJH2017-015L15S | J53: 67459.059 | K53: 6996.19 | L53: 0 | M53: 21456.46 | N53: 0 | O53: 0 | P53: 21456.46 | Q53: 0 | R53: 0 | S53: =P53+Q53 -> 21456.46 | T53: =S53 -> 21456.46 | U53: =T53 -> 21456.46 | V53: =T53-U53 -> 0 | W53: =U53*0.81 -> 17379.733 | X53: =W53 -> 17379.733 | Y53: =W53-X53 -> 0
A54: 16 | B54: 2018年台湖镇乡村公路（11条道路，作废1条） | C54: 唐大庄北路，0.516km | D54: HNJH2017-016L01S | E54: 台湖公路站 | F54: 姜永刚 | G54: 13716336185 | H54: 王新星 | I54: 王新星 | J54: 20914.997 | K54: 6657.79 | L54: 0 | M54: 10465.02 | N54: 6657.79 | O54: 0 | P54: 10465.02 | Q54: 6657.79 | R54: 0 | S54: =P54+Q54 -> 17122.81 | T54: =S54 -> 17122.81 | U54: 81160 | V54: =T54+T55+T56+T57+T58+T59+T60+T61+T62-U54-U55 -> 123483.79 | W54: =T54*0.8 -> 13698.248 | X54: =U54*0.8 -> 64928 | Y54: =W54+W55+W56+W57+W58+W59+W60+W61+W62-X54-X55 -> 98787.034 | Z54: 刘素良 | AA54: 测量 | AB54: =(0.516+0.647+0.801+0.836+0.79+0.493+0.387+1.93+1.716)*1500 -> 12174 | AE54: =W54-AC54-AD54-AB54-AB55 -> -275.75194
C55: 兴武林路，0.647km | D55: HNJH2017-016L02S | J55: 26513.258 | K55: 7418.08 | L55: 0 | M55: 13266.164 | N55: 7418.08 | O55: 0 | P55: 13266.164 | Q55: 7418.08 | R55: 0 | S55: =P55+Q55 -> 20684.244 | T55: =S55 -> 20684.244 | U55: 412775 | W55: =T55*0.8 -> 16547.395 | X55: =U55*0.8 -> 330220 | AA55: 取芯 | AB55: =12*150 -> 1800
C56: 东减路，0.801km | D56: HNJH2017-016L03S | J56: 80332.752 | K56: 8524.37 | L56: 0 | M56: 40195.269 | N56: 8524.37 | O56: 0 | P56: 40195.269 | Q56: 8524.37 | R56: 0 | S56: =P56+Q56 -> 48719.639 | T56: =S56 -> 48719.639 | W56: =T56*0.8 -> 38975.712
C57: 铺九路，0.836km | D57: HNJH2017-016L04S | J57: 94834.252 | K57: 8433.88 | L57: 0 | M57: 47451.23 | N57: 8433.88 | O57: 0 | P57: 47451.23 | Q57: 8433.88 | R57: 0 | S57: =P57+Q57 -> 55885.11 | T57: =S57 -> 55885.11 | W57: =T57*0.8 -> 44708.088
C58: 农贸市场路，0.79km | D58: HNJH2017-016L05S | J58: 125121.5 | K58: 46249.61 | L58: 0 | M58: 62605.749 | N58: 46249.61 | O58: 0 | P58: 62605.749 | Q58: 46249.61 | R58: 0 | S58: =P58+Q58 -> 108855.36 | T58: =S58 -> 108855.36 | W58: =T58*0.8 -> 87084.288
C59: 铺外四路，0.493km | D59: HNJH2017-016L06S | J59: 98343.86 | K59: 6686.33 | L59: 0 | M59: 49207.3 | N59: 6686.33 | O59: 0 | P59: 49207.3 | Q59: 6686.33 | R59: 0 | S59: =P59+Q59 -> 55893.63 | T59: =S59 -> 55893.63 | W59: =T59*0.8 -> 44714.904
C60: 张九路，0.387km | D60: HNJH2017-016L07S | J60: 45121.963 | K60: 5790.34 | L60: 0 | M60: 22577.21 | N60: 5790.34 | O60: 0 | P60: 22577.21 | Q60: 5790.34 | R60: 0 | S60: =P60+Q60 -> 28367.55 | T60: =S60 -> 28367.55 | W60: =T60*0.8 -> 22694.04
C61: 西下营路，1.93km | D61: HNJH2017-016L08S | J61: 231141.41 | K61: 22974.78 | L61: 0 | M61: 114709.43 | N61: 22974.78 | O61: 0 | P61: 114709.43 | Q61: 22974.78 | R61: 0 | S61: =P61+Q61 -> 137684.21 | T61: =S61 -> 137684.21 | W61: =T61*0.8 -> 110147.37
C62: 蒋辛庄北路，1.716km | D62: HNJH2017-016L09S | J62: 248581.45 | K62: 19857.3 | L62: 0 | M62: 124348.94 | N62: 19857.3 | O62: 0 | P62: 124348.94 | Q62: 19857.3 | R62: 0 | S62: =P62+Q62 -> 144206.24 | T62: =S62 -> 144206.24 | W62: =T62*0.8 -> 115364.99
A63: 19 | B63: 通州区2018年公路桥梁改建工程(7座桥） | C63: 和合站东桥 | D63: HNJH2017-019 | E63: 通州公路局 | F63: 潘宝龙 | G63: 13810052975 | H63: 王新星 | I63: 王新星 | J63: 216424.24 | K63: 0 | L63: 0 | M63: 136396 | N63: 0 | O63: 0 | P63: 136396 | Q63: 0 | R63: 0 | S63: =P63+Q63 -> 136396 | T63: =S63 -> 136396 | U63: 136396 | V63: =T63-U63 -> 0 | W63: =U63*0.8 -> 109116.8 | X63: =U63*0.8 -> 109116.8 | Y63: =W63-X63 -> 0 | AC63: =10229.7+15033.9+23869.3 -> 49132.9 | AD63: =8183.76+13639.6 -> 21823.36 | AE63: =W63-AC63-AD63 -> 38160.54 | AG63: =AC63/T63 -> 0.36022244 | AH63: =AD63/P63/0.8 -> 0.2
C64: 杜店东桥 | J64: 131911.52 | K64: 0 | L64: 0 | M64: 85908 | N64: 0 | O64: 0 | P64: 85908 | Q64: 0 | R64: 0 | S64: =P64+Q64 -> 85908 | T64: =S64 -> 85908 | U64: 85908 | V64: =T64-U64 -> 0 | W64: =U64*0.8 -> 68726.4 | X64: =U64*0.8 -> 68726.4 | Y64: =W64-X64 -> 0 | AC64: =6443.1 -> 6443.1 | AD64: =5154.48+8590.8 -> 13745.28 | AE64: =W64-AC64-AD64 -> 48538.02 | AG64: =AC64/T64 -> 0.075 | AH64: =AD64/P64/0.8 -> 0.2
C65: 武协路板函
C66: 大灰店北路1号板函
C67: 蒋辛庄北路桥 | J67: 201849.62 | K67: 0 | L67: 0 | M67: 106442 | N67: 0 | O67: 0 | P67: 106442 | Q67: 0 | R67: 0 | S67: =P67+Q67 -> 106442 | T67: =S67 -> 106442 | U67: 106442 | V67: =T67-U67 -> 0 | W67: =U67*0.8 -> 85153.6 | X67: =U67*0.8 -> 85153.6 | Y67: =W67-X67 -> 0 | AC67: =7983.15+18627.35 -> 26610.5 | AD67: =6386.52+10644.2 -> 17030.72 | AE67: =W67-AC67-AD67 -> 41512.38 | AG67: =AC67/T67 -> 0.25 | AH67: =AD67/P67/0.8 -> 0.2
C68: 大北关桥 | J68: 159798.84 | K68: 0 | L68: 0 | M68: 87500 | N68: 0 | O68: 0 | P68: 87500 | Q68: 0 | R68: 0 | S68: =P68+Q68 -> 87500 | T68: =S68 -> 87500 | U68: 87500 | V68: =T68-U68 -> 0 | W68: =U68*0.8 -> 70000 | X68: =U68*0.8 -> 70000 | Y68: =W68-X68 -> 0 | AC68: =6562.5+15312.5 -> 21875 | AD68: =5250+8750 -> 14000 | AE68: =W68-AC68-AD68 -> 34125 | AG68: =AC68/T68 -> 0.25 | AH68: =AD68/P68/0.8 -> 0.2
C69: 靛庄村西桥
C70: 后堰上北2桥 | J70: 29949.08 | K70: 0 | L70: 0 | M70: 12266 | N70: 0 | O70: 0 | P70: =M70 -> 12266 | Q70: =N70 -> 0 | R70: =O70 -> 0 | S70: =P70+Q70 -> 12266 | T70: =S70 -> 12266 | U70: 0 | V70: =T70-U70 -> 12266 | W70: =T70*0.8 -> 9812.8 | X70: =U70*0.8 -> 0 | Y70: =W70-X70 -> 9812.8 | AE70: =W70-AC70-AD70 -> 9812.8
C71: 南小营东桥 | J71: 33656.65 | K71: 0 | L71: 0 | M71: 14815 | N71: 0 | O71: 0 | P71: =M71 -> 14815 | Q71: =N71 -> 0 | R71: =O71 -> 0 | S71: =P71+Q71 -> 14815 | T71: =S71 -> 14815 | U71: 0 | V71: =T71-U71 -> 14815 | W71: =T71*0.8 -> 11852 | X71: =U71*0.8 -> 0 | Y71: =W71-X71 -> 11852 | AE71: =W71-AC71-AD71 -> 11852
A72: 21 | B72: 2019年张家湾镇乡村公路储备项目第一批 | C72: 小耕垡路，0.655km | D72: HNJH2017-016L11S | E72: 张湾公路站 | F72: 卢世茹 | G72: 13520175981 | H72: 王新星 | I72: 王新星 | J72: 60151 | K72: 21264 | L72: 0 | M72: 25453.22 | N72: 0 | O72: 0 | P72: =M72 -> 25453.22 | Q72: =N72 -> 0 | R72: =O72 -> 0 | S72: =P72+P73+P74+P75+Q72+Q73+Q74+Q75+R75+R74+R73+R72 -> 162898.49 | T72: =S72 -> 162898.49 | U72: 37590 | V72: =T72-U72-U73 -> 0 | W72: =T72*0.8 -> 130318.79 | X72: =U72*0.8 -> 30072 | Y72: =W72-X72-X73 -> 0 | Z72: 刘素良 | AA72: 测量 | AB72: =(0.655+0.543+1.451+1.521)*1500 -> 6255 | AC72: =7518+31327.12 -> 38845.12 | AD72: =6014.4+18928.56 -> 24942.96 | AE72: =W72-AC72-AD72-AB72-AB73 -> 59525.712 | AG72: =AC72/T72 -> 0.23846212 | AH72: =AD72/W72 -> 0.19139956
C73: 南火垡路，0.543km | D73: HNJH2017-021L01S | J73: 53707 | K73: 8296 | L73: 0 | M73: 22789.48 | N73: 0 | O73: 0 | P73: =M73 -> 22789.48 | Q73: =N73 -> 0 | R73: =O73 -> 0 | U73: 125308.49 | X73: =U73*0.8 -> 100246.79 | Z73: 刘素良 | AA73: 取芯 | AB73: =(1+2+2)*150 -> 750
C74: 高营路，1.451km | D74: HNJH2017-021L02S | J74: 134292 | K74: 22677 | L74: 0 | M74: 48870.03 | N74: 0 | O74: 0 | P74: =M74 -> 48870.03 | Q74: =N74 -> 0 | R74: =O74 -> 0
C75: 北大化路，1.521km | D75: HNJH2017-021L03S | J75: 170133 | K75: 22641 | L75: 0 | M75: 65785.76 | N75: 0 | O75: 0 | P75: =M75 -> 65785.76 | Q75: =N75 -> 0 | R75: =O75 -> 0
B76: 2019年张家湾镇乡村公路储备项目第二批 | C76: 北仪阁西路（新增） | D76: HNJH2017-021L04S | J76: 65059 | K76: 9499 | L76: 0 | M76: 26407.66 | N76: 0 | O76: 0 | P76: =M76 -> 26407.66 | Q76: =N76 -> 0 | R76: =O76 -> 0 | S76: =P76+P77+P78+Q78+Q77+Q76+R76+R77+R78 -> 147086.22 | T76: =S76 -> 147086.22 | U76: 147086.22 | V76: =T76-U76 -> 0 | W76: =T76*0.8 -> 117668.98 | X76: =U76*0.8 -> 117668.98 | Y76: =W76-X76-X77 -> 0 | Z76: 刘素良 | AA76: 测量 | AB76: =(0.71+1.22+1.085)*1500 -> 4522.5 | AC76: =36771.56 -> 36771.56 | AD76: =22809.48 -> 22809.48 | AE76: =W76-AC76-AD76-AB76 -> 53565.436 | AG76: =AC76/T76 -> 0.25000003 | AH76: =AD76/W76 -> 0.19384447
C77: 三采路（西段）（新增） | D77: HNJH2017-021L05S | J77: 261021 | K77: 17514 | L77: 0 | M77: 87912.65 | N77: 0 | O77: 0 | P77: =M77 -> 87912.65 | Q77: =N77 -> 0 | R77: =O77 -> 0
C78: 高营东路（新增） | D78: HNJH2017-021L06S | J78: 83067 | K78: 15529 | L78: 0 | M78: 32765.91 | N78: 0 | O78: 0 | P78: =M78 -> 32765.91 | Q78: =N78 -> 0 | R78: =O78 -> 0
A79: 22 | B79: 2018下半年台湖镇乡村公路储备项目 项目5条道路（3出图2新增） | C79: 铺外二路西段，0.717km | D79: HNJH2017-022L01S | E79: 台湖公路站 | F79: 姜永刚 | G79: 13716336185 | H79: 王新星 | I79: 王新星 | J79: 63833.162 | K79: 9017 | L79: 0 | M79: 31939.54 | N79: 9017 | O79: 0 | P79: =M79 -> 31939.54 | Q79: =N79 -> 9017 | R79: 0 | S79: =P79+P80+P81+P82+P83+P84+Q79+Q80+Q81+Q82+Q83+Q84 -> 245141.42 | T79: =S79 -> 245141.42 | U79: 38940 | V79: =T79-U79-U80 -> 49028.42 | W79: =T79*0.8 -> 196113.14 | X79: =U79*0.8 -> 31152 | Y79: =W79-X79-X80 -> 39222.736 | Z79: 刘素良 | AA79: 测量 | AB79: =3.389*1500 -> 5083.5 | AE79: =W79-AB79-AB80-AC79-AD79 -> 190429.64
C80: 北凉路，0.672km | D80: HNJH2017-022L02S | J80: 54374.964 | K80: 9212 | L80: 0 | M80: 27207.04 | N80: 9212 | O80: 0 | P80: =M80 -> 27207.04 | Q80: =N80 -> 9212 | R80: 0 | U80: 157173 | X80: =U80*0.8 -> 125738.4 | AA80: 取芯 | AB80: =4*150 -> 600
C81: 尖垡路，0.335km | D81: HNJH2017-022L03S | J81: 30982.969 | K81: 6326 | L81: 0 | M81: 15502.63 | N81: 6326 | O81: 0 | P81: =M81 -> 15502.63 | Q81: =N81 -> 6326 | R81: 0
C82: 北火垡西路（新增）0.76km | D82: HNJH2017-022L04S | J82: 78210.213 | K82: 15138 | L82: 0 | M82: 39133.23 | N82: 15138 | O82: 0 | P82: =M82 -> 39133.23 | Q82: =N82 -> 15138 | R82: 0
C83: 外高路（新增），0.509km | D83: HNJH2017-022L05S | J83: 32199.071 | K83: 13710 | L83: 0 | M83: 16111.04 | N83: 13710 | O83: 0 | P83: =M83 -> 16111.04 | Q83: =N83 -> 13710 | R83: 0
C84: 前田路东段，0.9005km | D84: HNJH2017-022L05S | J84: 101915.9 | K84: 10850.34 | L84: 0 | M84: 50994.6 | N84: 10850.34 | O84: 0 | P84: =M84 -> 50994.6 | Q84: =N84 -> 10850.34 | R84: 0
A85: 23 | B85: 2019年漷县镇乡村公路储备项目 6条道路（2出图3方案1作废） | C85: 三马路，0.582km | D85: HNJH2017-023L01S | E85: 漷县公路站 | F85: 李超同 | G85: 13522038867 | H85: 王新星 | I85: 王新星 | J85: 69293.63 | K85: 0 | L85: 0 | M85: 41807.97 | N85: 0 | O85: 0 | P85: 0 | Q85: =N85 -> 0 | R85: 0 | S85: =Q85+Q86+Q87 -> 0 | T85: =S85 -> 0 | U85: 0 | V85: =T85-U85 -> 0 | Y85: =W85-X85 -> 0 | Z85: 刘素良 | AA85: 取芯 | AB85: =1*150 -> 150 | AF85: 测绘漷县镇自行委托测绘，三马路没上
C86: 郭庄路，1.313km | D86: HNJH2017-023L02S | J86: 85178.21 | K86: 0 | L86: 0 | M86: 57443.98 | N86: 0 | O86: 0 | P86: 0 | Q86: =N86 -> 0 | R86: 0 | S86: =Q86+Q87+Q88 -> 0 | T86: =S86 -> 0 | U86: 0 | V86: =T86-U86 -> 0 | Y86: =W86-X86 -> 0 | Z86: 刘素良 | AA86: 取芯 | AB86: =3*150 -> 450
C87: 小靛路 | D87: HNJH2017-023L03S | J87: 691297 | K87: 0 | L87: 0 | M87: 183039.85 | N87: 0 | O87: 0 | P87: =M87 -> 183039.85 | Q87: =N87 -> 0 | R87: =K87 -> 0 | S87: =P87+Q87+R87 -> 183039.85 | T87: =S87 -> 183039.85 | U87: 28150 | V87: =T87-U87-U88 -> 154889.85 | W87: =T87*0.8 -> 146431.88 | X87: =U87*0.8 -> 22520 | Y87: =W87-X87 -> 123911.88 | Z87: 刘素良 | AA87: 取芯 | AB87: =5*150 -> 750 | AE87: =W87-AB87-AC87-AD87 -> 145681.88
U88: 0
A89: 24 | B89: 昌平沙河生态公园 | C89: 4万平米 | D89: HBJH2017-024 | E89: 沙河镇政府 | F89: 宋岩 | G89: 13426361410 | H89: 杨建东 | I89: 王新星 | J89: 898150
A90: 25 | B90: 延庆区外石路（K0+395-K8+035）还建修复工程 | C90: 三级路、7.55km | D90: HNJH2017-025 | E90: 北京市延庆区八达岭镇人民政府 | F90: 吴颖 | G90: 13488805779 | H90: 杨建东 | I90: 杨建东 | J90: 869499.99 | K90: 69653.83 | L90: 0 | M90: 344547 | N90: 60400 | O90: 0 | P90: =M90 -> 344547 | Q90: =N90 -> 60400 | R90: 0 | S90: =P90+Q90+R90 -> 404947 | T90: =S90 -> 404947 | U90: 300000 | V90: =T90-U90-U91 -> 0 | W90: =T90*0.8 -> 323957.6 | X90: =U90*0.8 -> 240000 | Y90: =W90-X90-X91 -> 0 | Z90: 刘素梁 | AA90: 取芯 | AB90: =7*150 -> 1050 | AE90: =W90-AB90-AB91-AC90-AD90 -> 310855.1
U91: 104947 | X91: =U91*0.8 -> 83957.6 | Z91: 刘素梁 | AA91: 测量 | AB91: =8.035*1500 -> 12052.5
A92: 26 | B92: 密云白河两岸绿化提升项目 | C92: 4km，89812m2 | D92: JNJH2017-026 | E92: 园林中心 | F92: 王辉 | G92: 13681368593 | H92: 杨建东 | I92: 杨建东 | J92: 807700 | K92: 0 | L92: 0 | M92: 741049.65 | N92: 0 | O92: 0 | P92: =M92 -> 741049.65 | Q92: =N92 -> 0 | R92: =K92 -> 0 | S92: =P92+Q92+R92 -> 741049.65 | T92: =S92 -> 741049.65 | U92: 403800 | V92: =T92-U92-U93 -> 0 | W92: =T92*0.77 -> 570608.23 | X92: =U92*0.77 -> 310926 | Y92: =W92-X92-X93 -> 0 | AC92: =44125.87+94999.9 -> 139125.77 | AD92: =80760+50666.61 -> 131426.61 | AE92: =W92-AB92-AB93-AC92-AD92 -> 300055.85 | AG92: =AC92/T92 -> 0.1877415 | AH92: =AD92/(P92*0.77) -> 0.23032722
U93: =337250-0.35 -> 337249.65 | X93: =U93*0.77 -> 259682.23
A94: 总计： | J94: =SUM(J5:J93) -> 15290374 | K94: =SUM(K5:K93) -> 1806601.2 | L94: =SUM(L5:L93) -> 0 | M94: =SUM(M5:M93) -> 9183129.7 | N94: =SUM(N5:N93) -> 1295631.8 | O94: =SUM(O5:O93) -> 0 | P94: =SUM(P5:P93) -> 9083877.8 | Q94: =SUM(Q5:Q93) -> 1295631.8 | ... Y94: =SUM(Y5:Y93) -> 283586.45 | AB94: =SUM(AB5:AB93) -> 604647.5 | AC94: =SUM(AC5:AC92) -> 1659162.5 | AD94: =SUM(AD5:AD92) -> 1220029.2 | AE94: =SUM(AE5:AE93) -> 4182174.8

Sheet 2018
A1: 项目经营管理台账（2018年）（电子）
A2: 序号 | B2: 项目信息 | F2: 经营信息 | K2: 概算信息（估算） | N2: 审计信息 | Q2: 甲方支付信息 | X2: 公司收支信息 | AG2: 备注
B3: 项目名称 | C3: 承接日期 | D3: 项目概况 | E3: 项目编号 | F3: 单位 | G3: 联系人 | H3: 联系方式 | I3: 经营 负责人 | J3: 经营 参与人 | K3: 设计费（元） | L3: 勘察费（元） | M3: 可研费（元） | N3: 设计费（元） | O3: 勘察费（元） | P3: 可研费（元） | Q3: 合同/补充协议额（元） | U3: 应支额（元） | X3: 应收额（元） | Y3: 收款信息 | AA3: 支付信息 | AF3: 公司结余 （元）
Q4: 设计费（元） | R4: 勘察费（元） | S4: 可研费（元） | T4: 补充协议额（元） | V4: 支付金额（元） | W4: 未收金额（元） | Y4: 实收金额（元） | Z4: 未收金额（元） | AA4: 单位 （个人） | AB4: 内容 | AC4: 金额（元） | AD4: 经营奖金（元） | AE4: 生产奖金（元）
A5: 1 | B5: 密云望潮亭、云启、时光公园提升工程设计 | D5: 面积5.75万㎡ | E5: JNJH2018-001 | F5: 园林中心 | G5: 王辉 | H5: 13681368593 | I5: 杨建东 | J5: 杨建东 | K5: 1169900 | L5: 0 | M5: 0 | N5: 884899.04 | O5: 0 | P5: 0 | Q5: =N5 -> 884899.04 | R5: =O5 -> 0 | S5: =P5 -> 0 | T5: =Q5+R5+S5 -> 884899.04 | U5: =T5 -> 884899.04 | V5: 442400 | W5: =U5-V5-V6 -> 0 | X5: =U5*0.77 -> 681372.26 | Y5: =V5*0.77 -> 340648 | Z5: =X5-Y5-Y6 -> 0 | AA5: 刘素良 | AB5: 测绘 | AC5: =1.05*2500 -> 2625 | AD5: =132720+124647.62 -> 257367.62 | AE5: =31158.32+74942.56+70384.35 -> 176485.23 | AF5: =X5-AC5-AC6-AD5-AE5 -> 244894.41 | AH5: =AD5/U5 -> 0.29084405 | AI5: =AE5/(Q5*0.77) -> 0.2590144
V6: 442499.04 | Y6: =V6*0.77 -> 340724.26
A7: 2 | B7: 通州区通武线大修工程 | D7: 大修，K1106+773-K1111+175 | E7: HNJH2018-002 | F7: 通州公路局 | G7: 张伟 | H7: 13439987630 | I7: 王新星 | J7: 王新星 | K7: 202382 | L7: 45135 | M7: 0 | N7: 202382 | O7: 45135 | P7: 0 | Q7: =N7 -> 202382 | R7: =O7 -> 45135 | S7: =P7 -> 0 | T7: =Q7+R7+S7 -> 247517 | U7: =T7 -> 247517 | V7: 222765.3 | W7: =U7-V7-V8-V9 -> 1.0913936e-11 | X7: =U7*0.8 -> 198013.6 | Y7: =V7*0.8 -> 178212.24 | Z7: =X7-Y7-Y8-Y9 -> 1.4551915e-11 | AA7: 韩国峰 | AB7: 测绘 | AC7: =4.4*2500 -> 11000 | AE7: =20942 -> 20942 | AF7: =X7-AC7-AC8-AC9-AD7-AE7 -> 146837.6 | AH7: =AD7/U7 -> 0 | AI7: =AE7/(Q7*0.8) -> 0.12934698
V8: 24751.7 | Y8: =V8*0.8 -> 19801.36 | AA8: 刘素良 | AB8: 取芯 | AC8: =6*150 -> 900
Y9: =V9*0.8 -> 0 | AA9: 瑞通十九处 | AB9: 路检+弯沉 | AC9: =17.48*800+87*50 -> 18334
D10: 大修，K1111+175-K1115+400 | E10: HNJH2018-002 | F10: 通州公路局 | G10: 张伟 | H10: 13439987630 | I10: 王新星 | J10: 王新星 | K10: 301366.44 | L10: 53182.31 | M10: 0 | N10: =K10*0.99 -> 298352.78 | O10: =L10*0.99 -> 52650.487 | P10: 0 | Q10: 294960.52 | R10: 52051.85 | S10: =P10 -> 0 | T10: =Q10+R10+S10 -> 347012.37 | U10: =T10 -> 347012.37 | V10: 312311.14 | W10: =U10-V10-V11-V12 -> -0.01 | X10: =U10*0.8 -> 277609.9 | Y10: =V10*0.8 -> 249848.91 | Z10: =X10-Y10-Y11-Y12 -> -0.008 | AF10: =X10-AC10-AC11-AC12-AD10-AE10 -> 277609.9 | AH10: =AD10/U10 -> 0 | AI10: =AE10/(Q10*0.8) -> 0
V11: 34701.24 | Y11: =V11*0.8 -> 27760.992
Y12: =V12*0.8 -> 0
A13: 7 | B13: 延庆区京银线、G234、滦赤路、四宝路、北西路大修工程-第四合同段（四宝路）勘察设计---延庆区四宝路（K0+000-K19+300)大修工程 | D13: 大修，19.3km，调整为预养 | E13: HXJH2018-007 | F13: 延庆公路局 | G13: 吴颖 | H13: 13488805779 | I13: 杨建东 | J13: 王新星 | K13: 541919 | L13: 193330 | M13: 0 | N13: =INT(541919*0.99)+1 -> 536500 | O13: =INT(193330*0.99) -> 191396 | P13: 0 | Q13: =N13 -> 536500 | R13: =O13 -> 191396 | S13: =P13 -> 0 | T13: =Q13+R13+S13 -> 727896 | U13: =T13 -> 727896 | W13: =U13-V13-V14-V15 -> 727896 | X13: =U13*0.8 -> 582316.8 | Y13: =V13*0.8 -> 0 | Z13: =X13-Y13-Y14-Y15 -> 582316.8 | AA13: 刘素良 | AB13: 测绘 | AC13: =19.3*2500 -> 48250 | AF13: =X13-AC13-AC14-AC15-AD13-AE13 -> 499202.8 | AH13: =AD13/U13 -> 0 | AI13: =AE13/(Q13*0.8) -> 0
Y14: =V14*0.8 -> 0 | AA14: 刘素良 | AB14: 取芯 | AC14: =16*150 -> 2400
Y15: =V15*0.8 -> 0 | AA15: 十九处 | AB15: 路检 | AC15: =(38.6*800+194*50)*0.8 -> 32464
A16: 13 | B16: 新机场高速公路地下综合管廊（南四环~新机场）工程一期土建施工交通导行工程 | D16: 帮忙刘军达 | E16: HNJH2018-013 | F16: 中铁一局 | G16: 刘军达 | H16: 18518335628 | K16: 31359 | L16: 0 | M16: 0 | N16: 12887.7 | O16: 0 | P16: 0 | Q16: =N16 -> 12887.7 | R16: =O16 -> 0 | S16: =P16 -> 0 | T16: =Q16+R16+S16 -> 12887.7 | U16: =T16 -> 12887.7 | V16: 12887.7 | W16: =U16-V16-V17-V18 -> 0 | X16: =U16*0.8 -> 10310.16 | Y16: =V16*0.8 -> 10310.16 | Z16: =X16-Y16-Y17-Y18 -> 0 | AA16: 刘君达 | AB16: 设计 | AC16: 10310.16 | AF16: =X16-AC16-AC17-AC18-AD16-AE16 -> 1.8189894e-12
Y17: =V17*0.8 -> 0
Y18: =V18*0.8 -> 0
A19: 14 | B19: 2019年通州区台湖镇乡村公路（7条路） | D19: 窑兴路，0.854km | E19: HNJH2018-014L01S | F19: 台湖公路站 | G19: 吕工 | H19: 15801247391 | I19: 王新星 | J19: 王新星 | K19: 145303 | L19: 6807 | M19: 0 | N19: 145303 | O19: 6807 | P19: 0 | Q19: 0 | R19: 0 | S19: =P19 -> 0 | T19: =Q20 -> 139675.75 | U19: =T19 -> 139675.75 | V19: 0 | W19: =U19-V19-V24-V25 -> 139675.75 | X19: =U19*0.8 -> 111740.6 | Y19: =V19*0.8 -> 0 | Z19: =X19-Y19-Y24-Y25 -> 111740.6 | AA19: 刘素良 | AB19: 测绘+取芯 | AC19: =0.854*2000+2*150 -> 2008 | AF19: =X19-AC19-AC20-AC21-AC22-AC23-AC24-AC25-AD19-AE19 -> 92176.6 | AG19: 未施工
D20: 农贸市场路(张台路-铺外四路）K0-K0+920 | E20: HNJH2018-014L07S | K20: 327015 | L20: 27961 | M20: 0 | N20: 327015 | O20: 27961 | P20: 0 | Q20: 139675.75 | R20: 0 | S20: 0 | AA20: 刘素良 | AB20: 测绘 | AC20: =0.92*2000 -> 1840
D21: 政府大街西段 | E21: HNJH2018-014L03S | K21: 314738 | L21: 9439 | M21: 0 | N21: 314738 | O21: 9439 | P21: 0 | Q21: 0 | R21: 0 | S21: 0 | AA21: 刘素良 | AB21: 测绘+取芯 | AC21: =0.62*2000+5*150 -> 1990 | AG21: 未施工
D22: 胡家垡村环路（未出图） | E22: HNJH2018-014L04S | AA22: 刘素良 | AB22: 测绘+取芯 | AC22: =2.24*2000+8*150 -> 5680
D23: 碱厂环路（未出图） | E23: HNJH2018-014L05S | AA23: 刘素良 | AB23: 测绘+取芯 | AC23: =1.149*2000+6*150 -> 3198
D24: 江场村环路（未出图） | E24: HNJH2018-014L06S | AA24: 刘素良 | AB24: 测绘+取芯 | AC24: =0.48*2000+6*150 -> 1860
D25: 北九路（未出图） | E25: HNJH2018-014L02S | AA25: 刘素良 | AB25: 测绘+取芯 | AC25: =1.194*2000+4*150 -> 2988
A26: 15 | B26: 2019年通州区张家湾镇(第三批）乡村公路（6条路） | D26: 枣凤沟路（新建） | E26: HNJH2018-015L01S | F26: 张湾公路站 | G26: 卢世茹 | H26: 13520175981 | I26: 王新星 | J26: 王新星 | K26: 240008.58 | L26: 27871.1 | M26: 0 | N26: 87614.72 | O26: 0 | P26: 0 | Q26: 87614.72 | R26: 0 | S26: =P26 -> 0 | T26: =Q26+Q27+Q28+Q29+Q30+Q31+R26+R27+R28+R29+R30+R31 -> 419201.59 | U26: =T26 -> 419201.59 | V26: 90420 | W26: =U26-V26-V27-V28-V29-V30-V31 -> 0 | X26: =U26*0.8 -> 335361.27 | Y26: =V26*0.8 -> 72336 | Z26: =X26-Y26-Y27-Y28-Y29-Y30-Y31 -> 0 | AA26: 刘素良 | AB26: 测绘+取芯 | AC26: =1.966*2000+6*150 -> 4832 | AD26: =18084+82195.4 -> 100279.4 | AE26: =13953.39+50742.27 -> 64695.66 | AF26: =X26-AC26-AC30-AC31-AD26-AE26 -> 163210.21 | AH26: =AD26/U26 -> 0.23921522 | AI26: =AE26/X26 -> 0.19291333
D27: 何牌路支线（新建） | E27: HNJH2018-015L02S | K27: 146488.99 | L27: 12196 | M27: 0 | N27: 51559.94 | O27: 0 | P27: 0 | Q27: 51559.94 | R27: 0 | S27: =P27 -> 0 | V27: 328781.59 | Y27: =V27*0.8 -> 263025.27 | AA27: 刘素良 | AB27: 测绘+取芯 | AC27: =0.798*2000+0*150 -> 1596
D28: 南姚园生态园路（路网改造） | E28: HNJH2018-015L03S | K28: 137583.32 | L28: 20311.7 | M28: 0 | N28: 45530.91 | O28: 0 | P28: 0 | Q28: 45530.91 | R28: 0 | S28: =P28 -> 0 | AA28: 刘素良 | AB28: 测绘+取芯 | AC28: =1.368*2000+4*150 -> 3336
D29: 东翟路（大修） | E29: HNJH2018-015L04S | K29: 172942.09 | L29: 14513.8 | M29: 0 | N29: 66834.33 | O29: 0 | P29: 0 | Q29: 66834.33 | R29: 0 | S29: =P29 -> 0 | AA29: 刘素良 | AB29: 测绘+取芯 | AC29: =1.071*2000+4*150 -> 2742
D30: 三间房北环路延长线（新建） | E30: HNJH2018-015L05S | K30: 194756.81 | L30: 37680.5 | M30: 0 | N30: 85760.81 | O30: 0 | P30: 0 | Q30: 85760.81 | R30: 0 | S30: =P30 -> 0 | AA30: 刘素良 | AB30: 测绘+取芯 | AC30: =0.824*2000+0*150 -> 1648
D31: 卫生院南路（综合治理） | E31: HNJH2018-015L06S | K31: 242302.45 | L31: 13737.4 | M31: 0 | N31: 81900.88 | O31: 0 | P31: 0 | Q31: 81900.88 | R31: 0 | S31: =P31 -> 0 | AA31: 刘素良 | AB31: 测绘+取芯 | AC31: =0.198*2000+2*150 -> 696
A32: 16 | B32: 房山区河北镇项目-房东路 | D32: 城市次干路2.5km | E32: HNJH2018-016 | F32: 北京圣泉投资有限公司 | G32: 肖建营 | H32: 13911835251 | I32: 杨建东 | J32: 杨建东/王新星 | K32: =3022700+831700 -> 3854400 | L32: 0 | M32: 0 | N32: 3861000 | O32: 0 | P32: 0 | Q32: 3861000 | R32: =O32 -> 0 | S32: =P32 -> 0 | T32: =Q32+R32+S32 -> 3861000 | U32: =T32 -> 3861000 | V32: 1875450 | W32: =U32-V32-V33-V34 -> 1985550 | X32: =U32*0.82 -> 3166020 | Y32: =V32*0.82 -> 1537869 | Z32: =X32-Y32-Y33-Y34 -> 1628151 | AF32: =X32-AC32-AC33-AC34-AD32-AE32 -> 3166020
D33: 桥梁 | Y33: =V33*0.8 -> 0
D34: 给排水 | Y34: =V34*0.8 -> 0
A35: 17 | B35: 通州区2019年公路桥梁改建工程—十仓桥设计 | D35: 位于张家湾镇，8m钢筋混凝土现浇板 | E35: HNJH2018-017 | F35: 通州公路局 | G35: 潘宝龙 | H35: 13439987630 | I35: 王新星 | J35: 王新星 | K35: 121316.91 | L35: 0 | M35: 0 | N35: 59288 | O35: 0 | P35: 0 | Q35: =N35 -> 59288 | R35: =O35 -> 0 | S35: =P35 -> 0 | T35: =Q35+R35+S35 -> 59288 | U35: =T35 -> 59288 | V35: 0 | W35: =U35-V35-V36-V37 -> 59288 | X35: =U35*0.8 -> 47430.4 | Y35: =V35*0.8 -> 0 | Z35: =X35-Y35-Y36-Y37 -> 47430.4 | AF35: =X35-AC35-AC36-AC37-AD35-AE35 -> 47430.4 | AH35: =AD35/U35 -> 0 | AI35: =AE35/(Q35*0.8) -> 0
Y36: =V36*0.8 -> 0
Y37: =V37*0.8 -> 0
A38: 18 | B38: 前苇沟组团棚户区改造土地开发项目平衡资金地块道路工程 | D38: 7条支路,4.87km | E38: ZYJH2018-018 | F38: 北京昆泰嘉恒房地产开发有限公司 | G38: 常工 | H38: 18701639618 | I38: 王新星 | J38: 王新星 | K38: 3526664 | L38: 0 | M38: 0 | N38: 2804700 | O38: 0 | P38: 0 | Q38: =N38 -> 2804700 | R38: =O38 -> 0 | S38: =P38 -> 0 | T38: =Q38+R38+S38 -> 2804700 | U38: =T38 -> 2804700 | V38: 560940 | W38: =U38-V38-V39-V40 -> 841410 | X38: =U38*0.7 -> 1963290 | Y38: =V38*0.7 -> 392658 | Z38: =X38-Y38-Y39-Y40 -> 588987 | AD38: =158011.27 -> 158011.27 | AE38: 55303.94 | AF38: =X38-AC38-AC39-AC40-AD38-AE38 -> 1749974.8 | AH38: =AD38/U38 -> 0.056338029 | AI38: =AE38/X38 -> 0.028169012
V39: 1402350 | Y39: =V39*0.7 -> 981645
Y40: =V40*0.8 -> 0
A41: 19 | B41: 房山区佛子庄乡山川村帮扶项目工程 | D41: 滚水河、水库、凤凰山基地 | E41: CJJH2018-019 | F41: 北京市政路桥管理养护集团有限公司 | G41: 赵忠鑫 | H41: 13581861007 | I41: 王新星 | J41: 王新星 | K41: 40000 | L41: 20000 | M41: 0 | N41: 40000 | O41: 20000 | P41: 0 | Q41: =N41 -> 40000 | R41: =O41 -> 20000 | S41: =P41 -> 0 | T41: =Q41+R41+S41 -> 60000 | U41: =T41 -> 60000 | V41: 60000 | W41: =U41-V41-V42-V43 -> 0 | X41: =U41*0.8 -> 48000 | Y41: 27000 | Z41: =X41-Y41-Y42-Y43 -> 21000 | AA41: 刘素良 | AB41: 测绘 | AC41: 20000 | AD41: =6750 -> 6750 | AE41: =3600 -> 3600 | AF41: =X41-AC41-AC42-AC43-AD41-AE41 -> 17650 | AH41: =AD41/U41 -> 0.1125 | AI41: =AE41/(Q41*0.8) -> 0.1125
Y42: =V42*0.8 -> 0
A44: 20 | B44: 通州区体育局建设球类场地项目 | D44: 篮球场30块，笼式多功能球场17块，门球球场3块；共计31384.26㎡ | E44: CJJH2018-020 | F44: 通州体育局 | G44: 吕海龙 | H44: 13910628276 | I44: 王新星 | J44: 王新星 | K44: 70700 | L44: 0 | M44: 48000 | N44: 37565.78 | O44: 0 | P44: 48000 | Q44: =N44 -> 37565.78 | R44: =O44 -> 0 | S44: =P44 -> 48000 | T44: =Q44+R44+S44 -> 85565.78 | U44: =T44 -> 85565.78 | V44: 85565.78 | W44: =U44-V44-V45-V46 -> 0 | X44: =U44*0.8 -> 68452.624 | Y44: 30052.62 | Z44: =X44-Y44-Y45 -> 0.004 | AD44: =12000+9391.45 -> 21391.45 | AE44: =4608+3125.4+2709.04+2884.51 -> 13326.95 | AF44: =X44-AC44-AC45-AC46-AD44-AE44 -> 33734.224 | AH44: =AD44/U44 -> 0.25000006 | AI44: =AE44/X44 -> 0.19468867
Y45: 38400
A47: 21 | B47: 清水湾小区南侧代征绿地建设工程 | D47: 3440㎡ | E47: JNJH2018-021 | F47: 园林中心 | G47: 王辉 | H47: 13681368593 | I47: 杨建东 | J47: 杨建东 | K47: 82900 | L47: 0 | M47: 0 | N47: 70090 | O47: 0 | P47: 0 | Q47: =N47 -> 70090 | R47: =O47 -> 0 | S47: =P47 -> 0 | T47: =Q47+R47+S47 -> 70090 | U47: =T47 -> 70090 | V47: 41400 | W47: =U47-V47-V48-V49 -> 0 | X47: =U47*0.77 -> 53969.3 | Y47: =V47*0.77 -> 31878 | Z47: =X47-Y47-Y48 -> 0 | AA47: 刘素良 | AB47: 测绘 | AC47: 787.5 | AD47: =12420+8083.66 -> 20503.66 | AE47: =9108+4563.46 -> 13671.46 | AF47: =X47-AC47-AC48-AC49-AD47-AE47 -> 19006.68 | AH47: =AD47/U47 -> 0.29253331 | AI47: =AE47/(Q47*0.8) -> 0.24381973
V48: 28690 | Y48: =V48*0.77 -> 22091.3
A50: 22 | B50: 密云第七小学外代征绿地建设工程 | D50: 4745㎡ | E50: JNJH2018-022 | F50: 园林中心 | G50: 王辉 | H50: 13681368593 | I50: 杨建东 | J50: 杨建东 | K50: 88700 | L50: 0 | M50: 0 | N50: 75103 | O50: 0 | P50: 0 | Q50: =N50 -> 75103 | R50: =O50 -> 0 | S50: =P50 -> 0 | T50: =Q50+R50+S50 -> 75103 | U50: =T50 -> 75103 | V50: 44200 | W50: =U50-V50-V51 -> 0 | X50: =U50*0.77 -> 57829.31 | Y50: =V50*0.77 -> 34034 | Z50: =X50-Y50-Y51 -> 0 | AA50: 刘素良 | AB50: 测绘 | AC50: 500 | AD50: =13260+8705.07 -> 21965.07 | AE50: =9724+4915.46 -> 14639.46 | AF50: =X50-AC50-AC51-AC52-AD50-AE50 -> 20724.78 | AH50: =AD50/U50 -> 0.29246595 | AI50: =AE50/(Q50*0.8) -> 0.24365638
V51: 30903 | Y51: =V51*0.77 -> 23795.31
A53: 总计 | K53: =SUM(K5:K52) -> 11952746 | L53: =SUM(L5:L52) -> 482164.81 | M53: =SUM(M5:M52) -> 48000 | N53: =SUM(N5:N52) -> 10089026 | O53: =SUM(O5:O52) -> 353388.49 | P53: =SUM(P5:P52) -> 48000 | Q53: =SUM(Q5:Q52) -> 9438253.4 | R53: =SUM(R5:R52) -> 308582.85 | ... Z53: =SUM(Z5:Z52) -> 2979625.8 | AC53: =SUM(AC5:AC52) -> 181984.66 | AD53: =SUM(AD5:AD52) -> 586268.47 | AE53: =SUM(AE5:AE52) -> 362664.7 | AF53: =SUM(AF5:AF52) -> 6478472.4

Sheet 2019
A1: 项目经营管理台账（2019年）（电子）
A2: 序号 | B2: 项目信息 | G2: 经营信息 | L2: 概算信息（估算） | O2: 审计信息 | R2: 甲方信息 | Z2: 公司信息 | AJ2: 备注
B3: 项目名称 | C3: 承接 日期 | D3: 项目概况 | E3: 资质 | F3: 项目编号 | G3: 单位 | H3: 联系人 | I3: 联系方式 | J3: 经营 负责人 | K3: 经营 参与人 | L3: 设计费（元） | M3: 勘察费（元） | N3: 可研费（元） | O3: 设计费（元） | P3: 勘察费（元） | Q3: 可研费（元） | R3: 合同/补充协议额（元） | V3: 应支额（元） | W3: 甲方支付信息 | Z3: 应收额（元） | AD3: 公司支付信息 | AI3: 公司结余 （元）
R4: 设计费（元） | S4: 勘察费（元） | T4: 可研费（元） | U4: 补充协议额（元） | W4: 开票金额（元） | X4: 支付金额（元） | Y4: 未收金额（元） | AA4: 开票金额（元） | AB4: 实收金额（元） | AC4: 未收金额（元） | AD4: 单位 （个人） | AE4: 内容 | AF4: 金额（元） | AG4: 经营奖金（元） | AH4: 生产奖金（元）
A5: 1 | B5: 2020年房山区普通公路大修、预防性养护工程勘察设计 | C5: 2019.1.3 | D5: (第1标段西环路）大修+综治（公路，二级，2.831km） | E5: 河南交规院 | F5: HNJH2019-001 | G5: 房山公路局 | H5: 白秀龙 | I5: 13811745176 | J5: 杨建东 | K5: 王新星 | L5: 133940 | M5: 28026 | O5: 193940 | P5: 28026 | R5: =O5 -> 193940 | S5: =P5 -> 28026 | U5: =R5+S5 -> 221966 | V5: =R5+S5 -> 221966 | W5: 133179.6 | X5: 133179.6 | Y5: =V5-X5-X6 -> 0 | Z5: =V5*0.8 -> 177572.8 | AA5: =W5*0.8 -> 106543.68 | AB5: =X5*0.8 -> 106543.68 | AC5: =Z5-AB5-AB6 -> 0 | AD5: 任永超 | AE5: 测绘 | AF5: =3.01*2500 -> 7525 | AG5: 21258.72 | AH5: =15797.72 -> 15797.72 | AI5: =Z5-AG5-AH5 -> 140516.36 | AJ5: 测绘及取芯费用燕山管委会支付，本单位不再另行支付。 | AK5: =AG5/V5 -> 0.095774668 | AL5: =AH5/R5/0.8 -> 0.10182092
W6: 88786.4 | X6: =W6 -> 88786.4 | AA6: =W6*0.8 -> 71029.12 | AB6: =X6*0.8 -> 71029.12 | AD6: 任永超 | AE6: 取芯 | AF6: =13*150 -> 1950
D7: 108国道K42-K67+900 | F7: HNJH2019-001 | L7: 134848 | M7: 259000 | O7: 131768 | P7: 256410 | R7: =O7 -> 131768 | S7: =P7 -> 256410 | U7: =R7+S7 -> 388178 | V7: =U7 -> 388178 | W7: 310542.4 | X7: =W7 -> 310542.4 | Y7: =V7-X7-X8 -> 0 | Z7: =V7*0.8 -> 310542.4 | AA7: =W7*0.8 -> 248433.92 | AB7: 248433.92 | AC7: =Z7-AB7-AB8 -> 0 | AD7: 解远飞 | AE7: 测绘 | AF7: =(67.9-42)*2500 -> 64750 | AG7: =72897.28 -> 72897.28 | AI7: =Z7-AF7-AF8-AG7-AH7 -> 169745.12 | AK7: =AG7/V7 -> 0.18779343 | AL7: =AH7/R7/0.8 -> 0
W8: 77635.6 | X8: 77635.6 | AA8: =W8*0.8 -> 62108.48 | AB8: =AA8 -> 62108.48 | AD8: 刘素良 | AE8: 取芯 | AF8: =21*150 -> 3150
A9: 4 | B9: 通州区2019年健身步道工程 | C9: 2019.1.4 | D9: 儒林小公园位于运河大堤路西侧，健步道全长0.839km | E9: 天津城建院 | F9: CJJH2019-004 | G9: 通州体育局 | H9: 吕海龙 | I9: 13910628276 | J9: 王新星 | K9: 王新星 | L9: 387100 | M9: 101800 | N9: 50000 | O9: 198537.16 | P9: 101800 | Q9: 50000 | R9: =O9 -> 198537.16 | S9: =P9 -> 101800 | T9: 0 | U9: =R9+S9+T9 -> 300337.16 | V9: =U9+U10+U13 -> 350337.16 | W9: =R9+S9+T9 -> 300337.16 | X9: =W9 -> 300337.16 | Y9: =V9-X9-X10-X13 -> 0 | Z9: =V9*0.8-0.01 -> 280269.72 | AA9: 105118 | AB9: =AA9 -> 105118 | AC9: =Z9-AB9-AB10-AB11-AB12 -> -0.0019999999 | AD9: 刘素梁 | AE9: 测绘 | AF9: =0.839*2000 -> 1678 | AG9: =82587.29 -> 82587.29 | AH9: =31765.95+4800+3004.69+12500 -> 52070.64 | AI9: =Z9-AF9-AF11-AG9-AH9 -> 138517.79 | AK9: =AG9/V9 -> 0.2357366 | AL9: =AH9/Z9 -> 0.18578761
R10: =O10 -> 0 | S10: =P10 -> 0 | T10: =Q9 -> 50000 | U10: =R10+S10+T10 -> 50000 | W10: =R10+S10+T10 -> 50000 | X10: =W10 -> 50000 | AA10: 135151.72 | AB10: =AA10 -> 135151.72
D11: 环湖路健步道位于环湖小镇东侧，健步道全长2.708km | AA11: 24000 | AB11: 24000 | AD11: 刘素梁 | AE11: 测绘 | AF11: =2.708*2000 -> 5416
AA12: 16000 | AB12: =AA12 -> 16000
C13: 2019.10.31 | L13: 85200 | M13: 16355.66 | O13: 50946.6 | P13: =M13 -> 16355.66
A14: 6 | B14: 2019年延庆区昌赤路（K53+000-K60+300)中修工程 | C14: 2019.1.14 | D14: 中修（公路二级，7.3km） | E14: 长安大学 | F14: LS2019-31-01 | G14: 延庆公路局 | H14: 刑工 | I14: 13810992745 | J14: 杨建东 | K14: 王新星 | L14: 144356 | M14: 73000 | O14: =L14 -> 144356 | P14: =M14 -> 73000 | R14: =O14 -> 144356 | S14: =P14 -> 73000 | T14: =Q14 -> 0 | U14: =R14+S14+T14 -> 217356 | V14: =U14 -> 217356 | W14: =V14 -> 217356 | X14: =W14 -> 217356 | Y14: =V14-X14 -> 0 | Z14: =V14*0.75-7300 -> 155717 | AA14: 60000 | AB14: 60000 | AC14: =Z14-AB14-AB15 -> 12.25 | AD14: 韩国峰 | AE14: 取芯 | AF14: 2000 | AG14: =U14*0.25 -> 54339 | AH14: =R14*0.75*0.2 -> 21653.4 | AI14: =Z14-AG14-AH14-AF14-AF15 -> 70424.6 | AJ14: 长安，管理费25%，6万元开票，95717元报销。公司收入扣除测量交桩费7300元，差12.25元未给。结清。 | AK14: =AG14/V14 -> 0.25 | AL14: =AH14/R14/0.8 -> 0.1875
AA15: 95704.75 | AB15: =AA15 -> 95704.75 | AD15: 戴工 | AE15: 交桩 | AF15: =7.3*1000 -> 7300
A16: 8 | B16: 2019年延庆区G234（K220+300-K223+650)中修工程 | C16: 2019.1.14 | D16: 中修，公路二级4km | E16: 河北华越 | F16: HNHY2019-008 | G16: 延庆公路局 | H16: 刑工 | I16: 13810992745 | J16: 杨建东 | K16: 王新星 | L16: 180939 | M16: 50250 | O16: =L16 -> 180939 | P16: =M16 -> 50250 | R16: =O16 -> 180939 | S16: =P16 -> 50250 | T16: =Q16 -> 0 | U16: =R16+S16+T16 -> 231189 | V16: =U16 -> 231189 | W16: =V16 -> 231189 | X16: =W16 -> 231189 | Y16: =V16-X16 -> 0 | Z16: =V16*0.82 -> 189574.98 | AA16: 189574.98 | AB16: =AA16 -> 189574.98 | AC16: =Z16-AB16 -> 0 | AD16: 韩国峰 | AE16: 取芯 | AF16: =7*200 -> 1400 | AG16: =U16*0.25 -> 57797.25 | AH16: =29674 -> 29674 | AI16: =Z16-AG16-AH16-AF16-AF17 -> 92328.73 | AJ16: 华越，合同中49544.02.元计入编号18。 | AK16: =AG16/V16 -> 0.25 | AL16: =AH16/R16/0.8 -> 0.20500003
AD17: 韩国峰 | AE17: 测绘 | AF17: =3.35*2500 -> 8375
A18: 12 | B18: 延庆区世园会周边道路标志改造工程 | D18: 公路册一期 | F18: HNHY2019-012 | L18: =30496 -> 30496 | O18: 27814 | R18: =O18 -> 27814 | U18: =R18+S18+T18 -> 27814 | V18: =U18 -> 27814 | W18: =V18 -> 27814 | X18: =W18 -> 27814 | Y18: =V18-X18 -> 0 | Z18: =V18*0.8 -> 22251.2 | AA18: =W18*0.8 -> 22251.2 | AB18: =X18*0.8 -> 22251.2 | AC18: =Z18-AB18 -> 0 | AG18: =6953.5 -> 6953.5 | AH18: =4450.24 -> 4450.24 | AI18: =Z18-AG18-AH18-AF18-AF19 -> 10847.46 | AK18: =AG18/V18 -> 0.25 | AL18: =AH18/R18/0.8 -> 0.2
D19: 公路册二期 | L19: 7747
A20: 13 | B20: 延庆区外石路（K0+395-K5+000)加宽工程 | C20: 2019.3.15 | D20: 外石路两侧加宽，公路三级4.604km | E20: 河南交规院 | F20: HNJH2019-013 | G20: 北京市延庆区八达岭镇人民政府 | H20: 吴颖 | I20: 13488805779 | J20: 杨建东 | K20: 杨建东 | L20: 174890 | O20: 74692.23 | R20: =O20 -> 74692.23 | U20: =R20+S20+T20 -> 74692.23 | V20: =U20 -> 74692.23 | W20: =V20 -> 74692.23 | X20: =W20 -> 74692.23 | Y20: =V20-X20 -> 0 | Z20: =V20*0.8 -> 59753.784 | AA20: 59753.78 | AB20: =Z20 -> 59753.784 | AC20: =Z20-AB20 -> 0 | AG20: =11922.7 -> 11922.7 | AH20: =11221.37 -> 11221.37 | AI20: =Z20-AF20-AG20-AH20 -> 36609.714 | AK20: =AG20/V20 -> 0.15962437 | AL20: =AH20/R20/0.8 -> 0.18779346
A21: 14 | B21: 燕山地区燕东路(北庄路口至丁东路路口)改造提升工程 | C21: 2019.3.22 | D21: 大修，（城市次干路1.957km） | E21: 河南交规院 | F21: HNJH2019-014 | G21: 燕山区办事处 | H21: 穆科长 | I21: 13910416067 | J21: 王新星 | K21: 王新星 | L21: 2379151 | R21: 1673310 | U21: =R21 -> 1673310 | V21: =U21 -> 1673310 | W21: 200000 | X21: =W21 -> 200000 | Y21: =V21-X21-X24-X22-X23 -> 1323310 | Z21: =V21*0.8 -> 1338648 | AA21: =X21*0.8 -> 160000 | AB21: =AA21 -> 160000 | AC21: =Z21-AB21-AB24-AB22-AB23 -> 1058648 | AD21: 张华 | AE21: 效果图 | AF21: =5*160 -> 800 | AI21: =Z21-AF21-AF22-AF23-AG21-AH21-AF24 -> 1337848 | AK21: =AG21/V21 -> 0 | AL21: =AH21/R21/0.8 -> 0
W22: 150000 | X22: 150000 | AA22: 120000 | AB22: 120000
A25: 15 | B25: 2019年通州区台湖镇乡村公路（4条路） | C25: 2019.5.5 | D25: 东水路（乡村路四级2.973km） | E25: 河南交规院 | F25: HNJH2019-015L01S | G25: 台湖公路站 | H25: 吕工 | I25: 15801247391 | J25: 王新星 | K25: 王新星 | L25: 435386.1 | M25: 46849 | O25: 127692.05 | P25: 72490.25 | R25: =O25 -> 127692.05 | S25: =P25 -> 72490.25 | U25: =R25+S25+T25 -> 200182.3 | V25: =U25+U26+U27+U28 -> 408368.96 | W25: 198059 | X25: =W25 -> 198059 | Y25: =V25+V26+V27+V28-X25-X26-X27 -> 81674.96 | Z25: =(V25+V26+V27+V28)*0.8 -> 326695.17 | AA25: =W25*0.8 -> 158447.2 | AB25: =X25*0.8 -> 158447.2 | AC25: =Z25-AB25-AB26 -> 65339.968 | AD25: 任永超 | AE25: 测绘+取芯 | AF25: =2.97*1500+4*150 -> 5055 | AI25: =Z25-AF25-AG25-AH25-AF26-AF27-AF28 -> 319000.17 | AJ25: 西碱路即2017年西下营延长线。已有测图。 | AK25: =AG25/V25 -> 0 | AL25: =AH25/R25/0.8 -> 0
D26: 西碱路（乡村路四级1.282km） | F26: HNJH2019-015L02S | L26: 199589.22 | M26: 15265.51 | O26: 80467.15 | P26: 42466.92 | R26: =O26 -> 80467.15 | S26: =P26 -> 42466.92 | U26: =R26+S26+T26 -> 122934.07 | W26: 128635 | X26: =W26 -> 128635 | AA26: =W26*0.8 -> 102908 | AB26: =X26*0.8 -> 102908 | AD26: 任永超 | AE26: 测绘+取芯 | AF26: 0 | AK26: =AG26/V26 -> #DIV/0! | AL26: =AH26/R26/0.8 -> 0
D27: 台东路（乡村路四级0.81km） | F27: HNJH2019-015L03S | L27: 128666.11 | M27: 21482 | O27: 35765.68 | P27: 21482 | R27: =O27 -> 35765.68 | S27: =P27 -> 21482 | U27: =R27+S27+T27 -> 57247.68 | AD27: 任永超 | AE27: 测绘+取芯 | AF27: =0.814*1500+3*150 -> 1671 | AK27: =AG27/V27 -> #DIV/0! | AL27: =AH27/R27/0.8 -> 0
D28: 台湖西路（乡村路四级0.446km） | F28: HNJH2019-015L05S | L28: 70487.2 | M28: 14482 | O28: 18594.74 | P28: 9410.17 | R28: =O28 -> 18594.74 | S28: =P28 -> 9410.17 | U28: =R28+S28+T28 -> 28004.91 | AD28: 任永超 | AE28: 测绘+取芯 | AF28: =0.446*1500+2*150 -> 969 | AK28: =AG28/V28 -> #DIV/0! | AL28: =AH28/R28/0.8 -> 0
B29: 2019年通州区台湖镇乡村公路（2条路） | D29: 朱家垡西路（乡村路四级0.506km） | F29: HNJH2019-015L04S | L29: 92174.37 | M29: 14475 | O29: 22497.21 | P29: 14475 | R29: =O29 -> 22497.21 | S29: =P29 -> 14475 | U29: =R29+S29+T29 -> 36972.21 | V29: =U29+U30 -> 128712.94 | Y29: =V29-X29-X30 -> 128712.94 | Z29: =V29*0.8 -> 102970.35
D30: 垛子路（乡村路四级1.045km） | F30: HNJH2019-015L06S | L30: 201261.75 | M30: 22698 | O30: 69042.73 | P30: 22698 | R30: =O30 -> 69042.73 | S30: =P30 -> 22698 | U30: =R30+S30+T30 -> 91740.73
A31: 16 | B31: 河北镇棚户区改造临时污水管线工程 | C31: 2019.3.27 | D31: 河北镇污水管线及雨水管线工程 | E31: 天津城建院 | F31: CJJH2019-016 | G31: 河北镇人民政府 | H31: 肖建营 | I31: 13911835251 | J31: 杨建东 | K31: 杨建东 | L31: =28180+171915 -> 200095 | O31: 370681.47 | R31: =O31 -> 370681.47 | U31: =R31+T31+S31 -> 370681.47 | V31: =U31 -> 370681.47 | W31: 146035 | X31: 146035 | Y31: =V31-X31-X32 -> 0 | Z31: =V31*0.8 -> 296545.18 | AA31: 73000 | AB31: 73000 | AC31: =Z31-AB31-AB32 -> 223545.18 | AG31: =18250 -> 18250 | AH31: =14600 -> 14600 | AI31: =Z31-AG31-AH31-AF31-AF32 -> 263695.18 | AJ31: 甲方超支8.25元 | AK31: =AG31/V31 -> 0.049233645 | AL31: =AH31/R31/0.8 -> 0.049233645
W32: =V31-W31 -> 224646.47 | X32: =W32 -> 224646.47
A33: 16‘ | B33: 河北镇棚户区改造临时污水、雨水管线工程竣工图编制 | C33: 2019.3.27 | D33: 河北镇污水管线及雨水管线工程 | E33: 河南交规院 | F33: HNJH2019-016 | G33: 河北镇人民政府 | H33: 肖建营 | I33: 13911835251 | J33: 杨建东 | K33: 杨建东 | L33: 29654.51 | O33: =L33 -> 29654.51 | R33: =O33 -> 29654.51 | U33: =R33+T33+S33 -> 29654.51 | V33: =U33 -> 29654.51 | W33: =U33 -> 29654.51 | X33: =W33 -> 29654.51 | Y33: =V33-X33-X34 -> 0 | Z33: =V33*0.8 -> 23723.608 | AA33: =Z33 -> 23723.608 | AB33: =AA33 -> 23723.608 | AC33: =Z33-AB33-AB34 -> 0 | AG33: =18250 -> 18250 | AH33: =14600 -> 14600 | AI33: =Z33-AG33-AH33-AF33-AF34 -> -9126.392 | AJ33: 甲方超支8.25元 | AK33: =AG33/V33 -> 0.61542072 | AL33: =AH33/R33/0.8 -> 0.61542072
W34: =V33-W33 -> 0 | X34: =W34 -> 0
A35: 17 | B35: 2020年延庆区普通公路大修及桥梁改造工程勘察设计1标段---2020年延庆区G234大修工程(K187+244-K209+113） | C35: 2019.5.15 | D35: 大修，公路一二三级长度29.669km。2020年延庆区G234大修工程(K187+244-K209+113） | E35: 河南交规院 | F35: HNJH2019-017 | G35: 延庆公路局 | H35: 吴颖 | I35: 13488805779 | J35: 杨建东 | K35: 杨建东 | L35: 950607 | M35: 209200 | O35: 949556 | P35: 209200 | R35: 940061 | S35: 175281 | U35: =R35+T35+S35 -> 1115342 | V35: =U35 -> 1115342 | W35: 598308 | X35: =W35 -> 598308 | Y35: =V35-X35-X36-X38-X39-X37 -> 0 | Z35: =V35*0.8 -> 892273.6 | AA35: 478646.4 | AB35: =AA35 -> 478646.4 | AC35: =Z35-AB35-AB36-AB37 -> 413627.2 | AD35: 任永超 | AE35: 测绘 | AF35: =21.869*2500 -> 54672.5 | AG35: =140447.89 -> 140447.89 | AH35: =63553.35 -> 63553.35 | AI35: =Z35-AG35-AH35-AF35-AF36-AF38-AF39-AF37 -> 579554.66 | AK35: =AG35/V35 -> 0.12592361 | AL35: =AH35/R35/0.8 -> 0.08450695
W36: 517034 | X36: =W36 -> 517034 | AD36: 任永超 | AE36: 取芯 | AF36: =11*150 -> 1650
X37: 0 | AD37: 质监站 | AE37: 弯沉盆检测 | AF37: 24000
X38: =W38 -> 0 | AD38: 瑞通十九处 | AE38: 路检 | AF38: =21.869*800 -> 17495.2
X39: =W39 -> 0 | AD39: 瑞通十九处 | AE39: 弯沉 | AF39: =218*50 -> 10900
A40: 18 | B40: 2020年延庆区G234中修工程(209+113-212+400） | C40: 2019.5.24 | D40: 中修，公路二级长度3.287km | E40: 河北华跃 | F40: HNHY2019-018 | G40: 延庆公路局 | H40: 刑工 | I40: 13810992745 | J40: 杨建东 | K40: 杨建东 | L40: 217831 | M40: 51000 | O40: =L40 -> 217831 | P40: =M40 -> 51000 | R40: =O40 -> 217831 | S40: =P40 -> 51000 | T40: =Q40 -> 0 | U40: =R40+T40+S40 -> 268831 | V40: =U40 -> 268831 | W40: 247048 | X40: =W40 -> 247048 | Y40: =V40-X40-X41-X42 -> 0 | Z40: =V40*0.82 -> 220441.42 | AA40: 49544.02 | AB40: =AA40 -> 49544.02 | AC40: =Z40-AB40-AB41-AB42 -> 0.4 | AD40: 任永超 | AE40: 测绘+取芯 | AF40: =3.4*2500+6*150 -> 9400 | AG40: =61762 -> 61762 | AH40: =33462.21 -> 33462.21 | AI40: =Z40-AF40-AF41-AF42-AG40-AH40 -> 115817.21 | AJ40: 华越 | AK40: =AG40/V40 -> 0.22974285 | AL40: =AH40/Z40 -> 0.15179638
W41: 21783 | X41: 21783 | AA41: 156939 | AB41: =AA41 -> 156939
AA42: 13958 | AB42: =AA42 -> 13958
A43: 21 | B43: 2020年房山区普通公路大修、预防性养护工程勘察设计，同编号1，一个招标项目 | C43: 2019.6.3 | D43: G234国道(K372+486-K372+915、K373+750-K376+540)大修工程大修公路二级长度3.219km | E43: 河南交规院 | F43: HNJH2019-021 | G43: 房山公路局 | H43: 白秀龙 | I43: 13811745176 | J43: 杨建东 | K43: 王新星 | L43: 174957 | M43: 32190 | O43: 173207 | P43: =31868 -> 31868 | R43: =O43 -> 173207 | S43: =P43 -> 31868 | U43: =R43+S43 -> 205075 | V43: =U43 -> 205075 | W43: 164060 | X43: 164060 | Y43: =V43-X43-X44 -> 0 | Z43: =V43*0.8 -> 164060 | AB43: 131248 | AC43: =Z43-AB43-AB44 -> 0 | AD43: 任永超 | AE43: 取芯 | AF43: =150*12 -> 1800 | AI43: =Z43-AF43-AF44-AG43-AH43 -> 142520 | AK43: =AG43/V43 -> 0 | AL43: =AH43/R43/0.8 -> 0
W44: 41015 | X44: 41015 | AB44: =X44*0.8 -> 32812 | AD44: 解飞 | AE44: 测绘 | AF44: =3.29*6000 -> 19740
A45: 22 | B45: 2020年房山区普通公路大修、预防性养护工程勘察设计，同编号1，一个招标项目 | C45: 2019.6.3 | D45: G234国道(K357+226-K364+555)大修工程大修公路二级长度7.329km | E45: 河南交规院 | F45: HNJH2019-022 | G45: 房山公路局 | H45: 白秀龙 | I45: 13811745176 | J45: 杨建东 | K45: 王新星 | L45: 204137 | M45: 73290 | O45: 202095 | P45: 72557 | R45: =O45 -> 202095 | S45: =P45 -> 72557 | U45: =R45+S45 -> 274652 | V45: =U45 -> 274652 | W45: 219721.6 | X45: 219721.6 | Y45: =V45-X45-X46 -> 0 | Z45: =V45*0.8 -> 219721.6 | AB45: 175777.28 | AC45: =Z45-AB45-AB46 -> 0 | AD45: 任永超 | AE45: 取芯 | AF45: =150*13 -> 1950 | AI45: =Z45-AF45-AF46-AG45-AH45 -> 173797.6 | AK45: =AG45/V45 -> 0 | AL45: =AH45/R45/0.8 -> 0
W46: 54930.4 | X46: =W46 -> 54930.4 | AB46: =X46*0.8 -> 43944.32 | AD46: 解飞 | AE46: 测绘 | AF46: =7.329*6000 -> 43974
A47: 25 | B47: 延庆区2019年乡村公路安全防护工程 | C47: 2019.6.30 | D47: 延庆区各乡镇生命安全防护工程，标志新建等设计内容 | E47: 国道通 | F47: HNJH2019-025 | G47: 延庆公路局 | H47: 吴颖 | I47: 13488805779 | J47: 杨建东 | K47: 杨建东 | L47: 262124 | O47: 142328 | R47: =O47 -> 142328 | S47: 0 | T47: 0 | U47: =R47+S47+T47 -> 142328 | V47: =U47 -> 142328 | W47: 142328 | X47: 142328 | Y47: =V47-X47 -> 0 | Z47: =X47*0.75 -> 106746 | AA47: 106746 | AB47: 0 | AC47: =Z47-AB47 -> 106746 | AG47: =V47*0.25 -> 35582 | AH47: =Z47*0.2 -> 21349.2 | AI47: =Z47-AF47-AG47-AH47 -> 49814.8 | AJ47: 因2019年未入围，用国道通资质，管理费25%。 | AK47: =AG47/V47 -> 0.25 | AL47: =AH47/R47/0.8 -> 0.1875
A48: 26 | B48: 2019年度张家湾镇乡村公路工程勘察设计采购项目（二标段） | C48: 2019.7.1 | D48: 牛高路，乡村路三级3.598km | E48: 河南交规院 | F48: HNJH2019-026L01S | G48: 张湾公路站 | H48: 卢世茹 | I48: 13520175981 | J48: 王新星 | K48: 王新星 | L48: 1107311.5 | M48: 46104 | O48: 796538.75 | P48: 33797.72 | R48: =O48 -> 796538.75 | S48: =P48 -> 33797.72 | U48: =R48+S48+T50 -> 830336.47 | V48: =U48 -> 830336.47 | W48: 179934 | X48: =W48 -> 179934 | Y48: =V48-X50-X48-X49 -> 530418.85 | Z48: =V48*0.8 -> 664269.18 | AA48: =X48*0.8 -> 143947.2 | AB48: =AA48 -> 143947.2 | AC48: =Z48-AB48-AB49-AB50 -> 424335.08 | AK48: =AG48/V48 -> 0 | AL48: =AH48/R48/0.8 -> 0
W49: 119983.62 | X49: =W49 -> 119983.62 | AA49: =X49*0.8 -> 95986.896 | AB49: =AA49 -> 95986.896
AD50: 刘素良 | AE50: 测绘+取芯 | AF50: =3.598*1500+3*150 -> 5847
D51: 三支路，2.387km | F51: HNJH2019-026L02S | L51: 584057 | M51: 34890 | O51: 353641.4 | P51: 26190.59 | R51: =O51 -> 353641.4 | S51: =P51 -> 26190.59 | U51: =O51+P51+Q51 -> 379831.99 | V51: =U51 -> 379831.99 | W51: 167280 | X51: =W51 -> 167280 | Y51: =V51-X51-X52 -> 141551.99 | Z51: =V51*0.8 -> 303865.59 | AA51: 133824 | AB51: 133824 | AC51: =Z51-AB51-AB52 -> 113241.59 | AD51: 刘素良 | AE51: 测绘+取芯 | AF51: =2.387*1500+2*150 -> 3880.5 | AK51: =AG51/V51 -> 0 | AL51: =AH51/R51/0.8 -> 0
W52: 71000 | X52: 71000 | AA52: 56800 | AB52: 56800
D53: 后坨路，长0.43km，宽7m | F53: HNJH2019-026L03S | L53: 268028.5 | M53: 17875 | O53: =77575.52*0.87 -> 67490.702 | P53: =77575.52*0.13 -> 10084.818 | R53: =O53 -> 67490.702 | S53: =P53 -> 10084.818 | U53: =R53+S53+T53 -> 77575.52 | V53: =U53 -> 77575.52 | W53: 76621.41 | X53: =W53 -> 76621.41 | Y53: =V53-X53 -> 954.11 | Z53: =V53*0.8 -> 62060.416 | AC53: =Z53-AB53 -> 62060.416 | AD53: 任永超 | AE53: 测绘+取芯 | AF53: =0.45*1500+2*150 -> 975 | AI53: =Z53-AF53-AG53-AH53 -> 61085.416 | AJ53: 走发改委资金，单独签订合同 | AK53: =AG53/V53 -> 0 | AL53: =AH53/R53/0.8 -> 0
C55: 2019.8.31 | D55: 前街村南路，长2.486km，宽5-7.5m | F55: HNJH2019-026L04S | L55: 411503.2 | M55: 38486 | O55: =138528.09*0.85 -> 117748.88 | P55: =138528.09*0.15 -> 20779.213 | R55: =O55 -> 117748.88 | S55: =P55 -> 20779.213 | U55: =R55+S55+T55 -> 138528.09 | V55: =U55 -> 138528.09 | W55: 50748 | X55: =W55 -> 50748 | Y55: =V55-X55-X56 -> 59787.25 | Z55: =V55*0.8 -> 110822.47 | AA55: =X55*0.8 -> 40598.4 | AB55: =AA55 -> 40598.4 | AC55: =Z55-AB55-AB56-AB57 -> 47829.8 | AD55: 任永超 | AE55: 测绘+取芯 | AF55: =1.9*1500+4*150 -> 3450 | AG55: =11912.68+7624.11 -> 19536.79 | AH55: =7624.11 -> 7624.11 | AI55: =Z55-AF55-AG55-AH55 -> 80211.572 | AK55: =AG55/V55 -> 0.14103125 | AL55: =AH55/R55/0.8 -> 0.080936123
W56: =32646.01-4653.17 -> 27992.84 | X56: =W56 -> 27992.84 | AA56: =X56*0.8 -> 22394.272 | AB56: =AA56 -> 22394.272
D58: 五支路，长4.086km，宽4-6m | F58: HNJH2019-026L05S | L58: 597242.5 | M58: 65079 | O58: =178887*0.81 -> 144898.47 | P58: =178887*0.19 -> 33988.53 | R58: =O58 -> 144898.47 | S58: =P58 -> 33988.53 | U58: =R58+S58+T59 -> 178887 | V58: =U58 -> 178887 | W58: 78720 | X58: =W58 -> 78720 | Y58: =V58-X59-X58 -> 100167 | Z58: =V58*0.8 -> 143109.6 | AC58: =Z58-AB59 -> 143109.6 | AK58: =AG58/V58 -> 0 | AL58: =AH58/R58/0.8 -> 0
AD59: 任永超 | AE59: 测绘+取芯 | AF59: =4.1*1500+4*150 -> 6750 | AI59: =Z58-AF59-AG59-AH59 -> 136359.6
C60: 2019.10.22 | D60: 庙东侧路（陆辛庄北路），长0.795km，宽4-5m | F60: HNJH2019-026L06S | L60: 129866.8 | M60: 21235 | P60: 0 | R60: 61970.38 | S60: =P60 -> 0 | U60: =R60+S60+T60 -> 61970.38 | V60: =U60 -> 61970.38 | Y60: =V60-X60 -> 61970.38 | Z60: =V60*0.8 -> 49576.304 | AC60: =Z60-AB60 -> 49576.304 | AD60: 任永超 | AE60: 测绘+取芯 | AF60: =0.8*1500+2*150 -> 1500 | AI60: =Z60-AF60-AG60-AH60 -> 48076.304
D61: 大集周边路，长1.155km，宽4-5m | F61: HNJH2019-026L07S | L61: 149223.4 | M61: 21894 | O61: =42714.01*0.78 -> 33316.928 | P61: =42714.01*0.22 -> 9397.0822 | R61: =O61 -> 33316.928 | S61: =P61 -> 9397.0822 | U61: =R61+S61+T61 -> 42714.01 | V61: =U61 -> 42714.01 | W61: 38060.84 | X61: =W61 -> 38060.84 | Y61: =V61-X61-X62 -> 1.2732926e-11 | Z61: =V61*0.8 -> 34171.208 | AA61: =W61*0.8 -> 30448.672 | AB61: =X61*0.8 -> 30448.672 | AC61: =Z61-AB61-AB62 -> 7.2759576e-12 | AD61: 任永超 | AE61: 测绘+取芯 | AF61: =1.15*1500+0*150 -> 1725 | AG61: =9515.21 -> 9515.21 | AH61: =6089.73 -> 6089.73 | AI61: =Z61-AF61-AG61-AH61 -> 16841.268 | AK61: =AG61/V61 -> 0.22276555 | AL61: =AH61/R61/0.8 -> 0.22847732
W62: 4653.17 | X62: =W62 -> 4653.17 | AA62: =W62*0.8 -> 3722.536 | AB62: =X62*0.8 -> 3722.536
C63: 2020.5 | D63: 齐善庄南路 | F63: HNJH2019-026L08S | L63: 102906.3 | M63: 18838 | P63: 0 | R63: =O63 -> 0 | S63: =P63 -> 0 | Z63: =V63*0.8 -> 0 | AD63: 任永超 | AE63: 测绘+取芯 | AF63: =0.8*1500+0*150 -> 1200 | AK63: =AG63/V63 -> #DIV/0! | AL63: =AH63/R63/0.8 -> #DIV/0!
C64: 2020.5 | D64: 南姚园南路 | F64: HNJH2019-026L09S | L64: 66270.17 | M64: 16579 | P64: 0 | R64: =O64 -> 0 | S64: =P64 -> 0 | Z64: =V64*0.8 -> 0 | AD64: 任永超 | AE64: 测绘+取芯 | AF64: =0.2*1500+0*150 -> 300 | AK64: =AG64/V64 -> #DIV/0! | AL64: =AH64/R64/0.8 -> #DIV/0!
A65: 29 | B65: 2020年延庆区乡村公路建养工程勘察设计---2标 | C65: 2019.8.5 | D65: 旧北路长度2.53km | E65: 河南交规院 | F65: HNJH2019-029L01S | G65: 延庆公路局 | H65: 吴颖 | I65: 13488805779 | J65: 杨建东 | K65: 杨建东 | L65: 135959 | M65: 20224 | O65: 108094 | P65: 20022 | R65: =O65 -> 108094 | S65: =P65 -> 20022 | U65: =R65+S65+T65 -> 128116 | V65: =U65 -> 128116 | W65: 128116 | X65: =W65 -> 128116 | Y65: =V65-X65 -> 0 | Z65: =V65*0.8 -> 102492.8 | AD65: 任永超 | AE65: 测绘+取芯 | AF65: =2.8*1500+4*150 -> 4800 | AI65: =Z65-AF65-AG65-AH65 -> 97692.8 | AJ65: 由于设计重大失误，不发生产奖金 | AK65: =AG65/V65 -> 0 | AL65: =AH65/R65/0.8 -> 0
D66: 胡家营路长度1km | F66: HNJH2019-029L02S | L66: 25331 | M66: 7968 | O66: 21274 | P66: 7888 | R66: =O66 -> 21274 | S66: =P66 -> 7888 | U66: =R66+S66+T66 -> 29162 | V66: =U66 -> 29162 | W66: =V66 -> 29162 | X66: =W66 -> 29162 | Y66: =V66-X66 -> 0 | Z66: =V66*0.8 -> 23329.6 | AD66: 任永超 | AE66: 测绘+取芯 | AF66: =0.996*1500+2*150 -> 1794 | AI66: =Z66-AF66-AG66-AH66 -> 21535.6 | AJ66: 前期费包含勘察设计两项费用。 | AK66: =AG66/V66 -> 0 | AL66: =AH66/R66/0.8 -> 0
D67: 胡家营东路长度0.54km | F67: HNJH2019-029L03S | L67: 16329 | M67: 4312 | O67: 13401 | P67: 4269 | R67: =O67 -> 13401 | S67: =P67 -> 4269 | U67: =R67+S67+T67 -> 17670 | V67: =U67 -> 17670 | W67: =V67 -> 17670 | X67: =W67 -> 17670 | Y67: =V67-X67 -> 0 | Z67: =V67*0.8 -> 14136 | AD67: 任永超 | AE67: 测绘+取芯 | AF67: =0.539*1500+4*150 -> 1408.5 | AI67: =Z67-AF67-AG67-AH67 -> 12727.5 | AK67: =AG67/V67 -> 0 | AL67: =AH67/R67/0.8 -> 0
C68: 2020.4 | D68: 延庆区大榆树镇小泥河路道路工程四级公路 主路2.2km,支路0.4km | E68: 长安大学 | F68: HNJH2019-029L10S | AD68: 任永超 | AE68: 测绘+取芯 | AF68: =2.6*1500+0*150 -> 3900 | AK68: =AG68/V68 -> #DIV/0! | AL68: =AH68/R68/0.8 -> #DIV/0!
A69: 30 | B69: 通州区漷马路（K10+000-K16+000）中修工程 | C69: 2017.4 | D69: 中修，公路二级长度6km | E69: 河南交规院 | F69: HNJH2017-007 | G69: 通州公路局 | H69: 张伟 | I69: 13439987630 | J69: 王新星 | K69: 王新星 | L69: 199017 | M69: 48000 | O69: =L69 -> 199017 | P69: =M69 -> 48000 | R69: =O69 -> 199017 | S69: =P69 -> 48000 | U69: =R69+S69+T69 -> 247017 | V69: =U69 -> 247017 | W69: =V69 -> 247017 | X69: =W69 -> 247017 | Y69: =V69-X69 -> 0 | Z69: =V69*0.8 -> 197613.6 | AA69: 197613.6 | AB69: =AA69 -> 197613.6 | AC69: =Z69-AB69 -> 0 | AD69: 刘素良 | AE69: 测绘 | AF69: =6*2500 -> 15000 | AI69: =Z69-AF69-AF70-AF71-AF72-AG69-AH69 -> 172497.6 | AJ69: 2017年大修改为中修，不重新招标，合同按照大修的合同。京宏-河南JH2019-011 补充协议签订金额295899.5，实际支付197613.60元 | AK69: =AG69/V69 -> 0 | AL69: =AH69/R69/0.8 -> 0
AD70: 刘素良 | AE70: 取芯 | AF70: =6*150 -> 900
AD71: 十九处 | AE71: 路检 | AF71: 4416
AD72: 十九处 | AE72: 路检 | AF72: =6*800 -> 4800
A73: 31 | B73: 通州区台湖镇西下营路(K0+000-K0+170)小修工程----17年转入 | C73: 2017.6 | D73: 小修，乡村路四级0.17m | E73: 河南交规院 | F73: HNJH2017-016L08S | G73: 台湖公路站 | H73: 吕工 | I73: 15801247391 | J73: 王新星 | K73: 王新星 | L73: 16834.52 | M73: 12572 | AJ73: 2017年项目已出图，但未施工，本次针对西下营路破损严重路段进行小修
A74: 32 | B74: 延庆区永元街大修工程 | C74: 2019.8.2 | D74: 长度2.258km | E74: 长安大学 | F74: HNJH2019-030 | G74: 延庆公路局 | H74: 张旭学 | I74: 13811589649 | J74: 杨建东 | K74: 杨建东 | L74: 120330 | M74: 18072 | O74: =125727/(L74+M74)*L74 -> 109310.05 | P74: =125727/(L74+M74)*M74 -> 16416.947 | R74: =O74 -> 109310.05 | S74: =P74 -> 16416.947 | T74: 0 | U74: =R74+S74+T74 -> 125727 | V74: =U74 -> 125727 | W74: =V74 -> 125727 | X74: =W74 -> 125727 | Y74: =V74-X74 -> 0 | Z74: =X74*0.75 -> 94295.25 | AA74: 94295.25 | AB74: 80000 | AC74: =Z74-AB74-AB75 -> 0 | AD74: 任永超 | AE74: 测绘 | AF74: =2.715*1500 -> 4072.5 | AI74: =Z74-AF74-AF75-AG74-AH74 -> 89472.75 | AJ74: 因2019年未入围，用长安资质，管理费25%。以报销的方式回款。 | AK74: =AG74/V74 -> 0 | AL74: =AH74/R74/0.8 -> 0
AB75: =6891+8109-704.75 -> 14295.25 | AD75: 任永超 | AE75: 取芯 | AF75: =5*150 -> 750
A76: 33 | B76: 2020年延庆区乡村公路建养工程勘察设计---2标 | C76: 2019.8 | D76: 延庆区滨河北路延长线道路新建工程，新建，长度0.4km | E76: 长安大学 | F76: HNJH2019-031 | G76: 延庆公路局 | H76: 张旭学 | I76: 13811589649 | J76: 杨建东 | K76: 杨建东 | L76: 68109 | O76: =52255-P76 -> 51505 | P76: =AF76/0.8 -> 750 | R76: =O76 -> 51505 | S76: =P76 -> 750 | U76: =R76+S76+T76 -> 52255 | V76: =U76 -> 52255 | W76: =V76 -> 52255 | X76: =W76 -> 52255 | Y76: =V76-X76 -> 0 | Z76: =X76*0.8 -> 41804 | AA76: 41804 | AB76: =AA76 -> 41804 | AC76: =Z76-AB76 -> 0 | AD76: 任永超 | AE76: 测绘+取芯 | AF76: =0.4*1500+0*150 -> 600 | AG76: =12266.43 -> 12266.43 | AH76: =7556 -> 7556 | AI76: =Z76-AF76-AG76-AH76 -> 21381.57 | AJ76: 互相抵扣，比例调整为0.8 | AK76: =AG76/V76 -> 0.23474175 | AL76: =AH76/R76/0.8 -> 0.18338025
A77: 37 | B77: 通州区体育局2020年建设多功能球场工程设计 | C77: 2019.10.22 | D77: 篮球场地场地尺寸34m×18m;笼式多功能球场场地尺寸为36.6m×18.3m | E77: 天津城建院 | F77: CJJH2019-035 | G77: 通州体育局 | H77: 吕海龙 | I77: 13910628276 | J77: 王新星 | K77: 王新星 | L77: 331100 | O77: 109703.21 | R77: =O77 -> 109703.21 | U77: =R77+S77+T77 -> 109703.21 | V77: =U77 -> 109703.21 | W77: =V77 -> 109703.21 | X77: =W77 -> 109703.21 | Y77: =V77-X77 -> 0 | Z77: =V77*0.8 -> 87762.568 | AA77: 87762.568 | AB77: =AA77 -> 87762.568 | AC77: =Z77-AB77 -> 0 | AG77: =17511.31 -> 17511.31 | AH77: =16481.23 -> 16481.23 | AK77: =AG77/V77 -> 0.15962441 | AL77: =AH77/R77/0.8 -> 0.18779339
A78: 41 | B78: 2020年延庆区普通公路生命安全防护工程勘察设计 | C78: 国道自己做通遗留项目 | D78: 兴阳线 | E78: 河南交规院 | F78: HNJH2019-039J01S | G78: 延庆公路局 | H78: 吴颖 | I78: 13488805779 | J78: 杨建东 | K78: 杨建东 | L78: 60757 | O78: 28857 | R78: =O78 -> 28857 | U78: =R78 -> 28857 | V78: =U78 -> 28857 | W78: 25971 | X78: =W78 -> 25971 | Y78: =V78-X78-X79 -> 0 | Z78: =V78*0.8 -> 23085.6 | AA78: 20776.8 | AB78: =AA78 -> 20776.8 | AC78: =Z78-AB78-AB79 -> 0 | AD78: 国道通 | AE78: 设计 | AF78: =AB78*0.75 -> 15582.6 | AI78: =Z78-AF78 -> 7503 | AJ78: 分包国道通
W79: 2886 | X79: =W79 -> 2886 | AA79: 2308.8 | AB79: =AA79 -> 2308.8
D80: 河东路 | F80: HNJH2019-039J02S | O80: 27029 | R80: =O80 -> 27029 | U80: =R80 -> 27029 | V80: =U80 -> 27029 | W80: 24326 | X80: =W80 -> 24326 | Y80: =V80-X80-X81 -> 0 | Z80: =V80*0.8 -> 21623.2 | AA80: 19460.8 | AB80: =AA80 -> 19460.8 | AC80: =Z80-AB80-AB81 -> 0 | AD80: 国道通 | AE80: 设计 | AF80: =AB80*0.75 -> 14595.6 | AI80: =Z80-AF80 -> 7027.6 | AJ80: 分包国道通
W81: 2703 | X81: 2703 | AA81: 2162.4 | AB81: =AA81 -> 2162.4
D82: 刘香路 | F82: HNJH2019-039J03S | O82: 3656 | R82: =O82 -> 3656 | U82: =R82 -> 3656 | V82: =U82 -> 3656 | W82: 3290 | X82: =W82 -> 3290 | Y82: =V82-X82-X83 -> 0 | Z82: =V82*0.8 -> 2924.8 | AA82: 2632 | AB82: =AA82 -> 2632 | AC82: =Z82-AB82-AB83 -> 0 | AD82: 国道通 | AE82: 设计 | AF82: =AB82*0.75 -> 1974 | AI82: =Z82-AF82 -> 950.8 | AJ82: 分包国道通
W83: 366 | X83: 366 | AA83: 292.8 | AB83: =AA83 -> 292.8
C84: 2020.6 | D84: 2 0 2 0 年延庆区对不合格标线重新施划工程 | E84: 河南交规院 | F84: HNJH2019-039 | L84: 21550 | O84: 21119 | R84: =O84 -> 21119 | U84: =R84 -> 21119 | V84: =U84 -> 21119 | W84: 19007 | X84: =W84 -> 19007 | Y84: =V84-X84-X85 -> 0 | Z84: =V84*0.8 -> 16895.2 | AA84: 15205.6 | AB84: =AA84 -> 15205.6 | AC84: =Z84-AB84-AB85 -> 1689.6 | AH84: =3801.4 -> 3801.4 | AI84: =Z84-AG84-AH84 -> 13093.8 | AK84: =AG84/V84 -> 0 | AL84: =AH84/R84/0.8 -> 0.22499882
W85: 2112 | X85: 2112
A86: 42 | B86: 2020年延庆区普通公路路面、桥梁、隧道中小修工程勘察设计第1标---路面、桥梁 | C86: 2019.3 | D86: 兴阳线（K212+400-220+300）中修工程 | E86: 河南交规院 | F86: HNJH2019-040L01S | G86: 延庆公路局 | H86: 张旭学 | I86: 13811589649 | J86: 杨建东 | K86: 杨建东 | L86: 203847 | M86: 118500 | O86: =INT(L86*0.98)+36 -> 199806 | P86: =M86*0.98 -> 116130 | R86: =O86 -> 199806 | S86: =P86 -> 116130 | U86: =R86+S86 -> 315936 | V86: =U86 -> 315936 | W86: 295955 | X86: =W86 -> 295955 | Y86: =V86-X86-X87 -> 0 | Z86: =V86*0.8 -> 252748.8 | AA86: 236764 | AB86: =AA86 -> 236764 | AC86: =Z86-AB86-AB87 -> 15984.8 | AD86: 任永超 | AE86: 测绘+取芯 | AF86: =7.8*2500+6*150 -> 20400 | AG86: =73988.75 -> 73988.75 | AI86: =Z86-AF86-AF87-AG86-AH86 -> 148220.05 | AK86: =AG86/V86 -> 0.23418904 | AL86: =AH86/R86/0.8 -> 0
X87: 19981 | AD87: 瑞通十九处 | AE87: 路检+弯沉 | AF87: =7.8*800+78*50 -> 10140
C88: 2020.5 | D88: 2020年延庆区道路小修工程 | F88: HNJH2019-040L02S | L88: 140114 | O88: 137312 | R88: =O88 -> 137312 | U88: =R88 -> 137312 | V88: =U88 -> 137312 | W88: =V88 -> 137312 | X88: =W88 -> 137312 | Y88: =V88-X88 -> 0 | Z88: =V88*0.8 -> 109849.6 | AA88: 109849.6 | AB88: =AA88 -> 109849.6 | AC88: =Z88-AB88 -> 0 | AG88: =30895.25+3223.24 -> 34118.49 | AH88: =19772.96+2062.87 -> 21835.83 | AI88: =Z88-AG88-AH88 -> 53895.28 | AK88: =AG88/V88 -> 0.2484742 | AL88: =AH88/R88/0.8 -> 0.19877933
C89: 2020.6 | D89: 延庆区昌赤路（K49+000-K78+700）中修工程--（70.7-78.7）2级路 | F89: HNJH2019-040L03S | L89: =143208*2/3 -> 95472 | M89: 80000 | O89: =248640-M89-O92-P92 -> 91093 | P89: =M89 -> 80000 | R89: =O89 -> 91093 | S89: =P89 -> 80000 | U89: =R89+S89 -> 171093 | V89: =U89 -> 171093 | W89: =V89 -> 171093 | X89: =W89 -> 171093 | Y89: =V89-X89 -> 0 | Z89: =V89*0.8 -> 136874.4 | AA89: 136874.4 | AB89: =AA89 -> 136874.4 | AC89: =Z89-AB89 -> 0 | AD89: 瑞通十九处+戴工 | AE89: 路检+交桩 | AF89: =11*800+8000 -> 16800 | AI89: =Z89-AF89-AG89-AH89 -> 120074.4 | AK89: =AG89/V89 -> 0 | AL89: =AH89/R89/0.8 -> 0
C90: 2020.6 | D90: 延庆区康张路（K0+000-K0+500、K9+000-K12+975）中修工程 | F90: HNJH2019-040L04S | L90: 80752 | M90: 89750 | O90: =166949-M90 -> 77199 | P90: =M90 -> 89750 | R90: =O90 -> 77199 | S90: =P90 -> 89750 | U90: =R90+S90 -> 166949 | V90: =U90 -> 166949 | W90: =V90 -> 166949 | X90: =W90 -> 166949 | Y90: =V90-X90 -> 0 | Z90: =V90*0.8 -> 133559.2 | AA90: 133559.2 | AB90: =AA90 -> 133559.2 | AC90: =Z90-AB90 -> 0 | AD90: 瑞通十九处+任永超 | AE90: 路检+交桩 | AF90: =8.975*800+1500 -> 8680 | AG90: =39189.91 -> 39189.91 | AH90: 11597.97 | AI90: =Z90-AF90-AG90-AH90 -> 74091.32 | AK90: =AG90/V90 -> 0.23474181 | AL90: =AH90/R90/0.8 -> 0.1877934
C91: 2020.6 | D91: 延庆区旧小路（K0+000-K4+200、K7+060-K11+600）中修工程 | F91: HNJH2019-040L05S | L91: 50612 | M91: 87400 | O91: =133936-M91 -> 46536 | P91: =M91 -> 87400 | R91: =O91 -> 46536 | S91: =P91 -> 87400 | U91: =R91+S91 -> 133936 | V91: =U91 -> 133936 | W91: =V91 -> 133936 | X91: =W91 -> 133936 | Y91: =V91-X91 -> 0 | Z91: =V91*0.8 -> 107148.8 | AA91: 107148.8 | AB91: =AA91 -> 107148.8 | AC91: =Z91-AB91 -> 0 | AD91: 瑞通十九处+任永超 | AE91: 路检+交桩 | AF91: =11.6*800+1500 -> 10780 | AG91: =31440.38 -> 31440.38 | AH91: =6991.32 -> 6991.32 | AI91: =Z91-AF91-AG91-AH91 -> 57937.1 | AK91: =AG91/V91 -> 0.23474182 | AL91: =AH91/R91/0.8 -> 0.18779332
C92: 2020.6含戴工做 | D92: 延庆区昌赤路（K49+000-K78+700）中修工程 | F92: HNJH2019-040L03S | L92: =143208*1/3 -> 47736 | M92: 32000 | O92: 45547 | P92: 32000 | R92: 45547 | S92: 32000 | T92: 0 | U92: =R92+S92+T92 -> 77547 | V92: =U92 -> 77547 | W92: =V92 -> 77547 | X92: =W92 -> 77547 | Y92: =V92-X92 -> 0 | Z92: =V92*0.8 -> 62037.6 | AA92: 62037.6 | AB92: =AA92 -> 62037.6 | AC92: =Z92-AB92 -> 0 | AD92: 戴工 | AE92: 设计 | AF92: =Z92 -> 62037.6 | AG92: =40162.68 -> 40162.68 | AH92: =13685.33 -> 13685.33 | AI92: =Z92-AF92 -> 0 | AJ92: 70.7-78.7自己做，49-53戴工做 | AK92: =AG92/V92 -> 0.51791404 | AL92: =AH92/R92/0.8 -> 0.37558264
A93: 总计 | L93: =SUM(L5:L92) -> 11855896 | M93: =SUM(M5:M92) -> 1829141.2 | N93: =SUM(N5:N92) -> 50000 | O93: =SUM(O5:O92) -> 6246498.9 | P93: =SUM(P5:P92) -> 1710352.9 | Q93: =SUM(Q5:Q92) -> 50000 | R93: =SUM(R5:R92) -> 7921337.7 | S93: =SUM(S5:S92) -> 1660078.2 | ... AC93: =SUM(AC5:AC92) -> 2725746.2 | AF93: =SUM(AF5:AF92) -> 526679 | AG93: =SUM(AG5:AG92) -> 859777.58 | AH93: =SUM(AH5:AH92) -> 378095.05 | AI93: =SUM(AI5:AI92) -> 4872586.3
A94: 2019年上报数值 | L94: 18855225 | M94: 1083317.2 | N94: 50000 | O94: 1165467.5 | P94: 340405.66 | Q94: 50000 | R94: 1274777.6 | S94: 356822.61 | T94: 50000 | U94: 1823928.2 | V94: 1823928.2 | W94: 1488579.2 | X94: 1488579.2 | Y94: 335349.01 | Z94: 1236531.1 | AA94: 666600.32 | AB94: 666600.32 | AC94: 583802.16 | AF94: 52085 | AG94: 388968.29 | AH94: 187779.48 | AI94: 616330.36
A95: 2020年上报数值 | L95: 19872923 | M95: 2129349.2 | N95: 50000 | O95: 4848286.5 | P95: 1546704.9 | Q95: 50000 | R95: 4617397.4 | S95: 1488494.3 | T95: 50000 | U95: 6155891.7 | V95: 6133951.1 | W95: 4423210.8 | X95: 4423210.8 | Y95: 1622977.6 | Z95: 4144757.9 | AA95: 1690627.3 | AB95: 1583881.3 | AC95: 533644.6 | AF95: 417000.2 | AG95: 1389289.6 | AH95: 673318.18 | AI95: 1703049.2
A96: 较2019年差值 | L96: =L95-L94 -> 1017698 | M96: =M95-M94 -> 1046032 | N96: =N95-N94 -> 0 | O96: =O95-O94 -> 3682819 | P96: =P95-P94 -> 1206299.3 | Q96: =Q95-Q94 -> 0 | R96: =R95-R94 -> 3342619.9 | S96: =S95-S94 -> 1131671.7 | ... AC96: =AC95-AC94 -> -50157.554 | AF96: =AF95-AF94 -> 364915.2 | AG96: =AG95-AG94 -> 1000321.3 | AH96: =AH95-AH94 -> 485538.7 | AI96: =AI95-AI94 -> 1086718.8
A97: 2021年上报数值
A98: 较2020年差值

Sheet 2020
A1: 项目经营管理台账（2020年）（电子）
A2: 序号 | B2: 项目信息 | G2: 经营信息 | L2: 概算信息（估算） | O2: 审计信息 | R2: 甲方信息 | Z2: 公司信息 | AJ2: 备注
B3: 项目名称 | C3: 承接 日期 | D3: 项目概况 | E3: 资质 | F3: 项目编号 | G3: 单位 | H3: 联系人 | I3: 联系方式 | J3: 经营 负责人 | K3: 经营 参与人 | L3: 设计费（元） | M3: 勘察费（元） | N3: 可研费（元） | O3: 设计费（元） | P3: 勘察费（元） | Q3: 可研费（元） | R3: 合同/补充协议额（元） | V3: 应支额（元） | W3: 甲方支付信息 | Z3: 应收额（元） | AA3: 公司收入信息 | AD3: 公司支付信息 | AI3: 公司结余 （元）
R4: 设计费（元） | S4: 勘察费（元） | T4: 可研费（元） | U4: 补充协议额（元） | W4: 开票金额（元） | X4: 支付金额（元） | Y4: 未收金额（元） | AA4: 开票金额（元） | AB4: 实收金额（元） | AC4: 未收金额（元） | AD4: 单位 （个人） | AE4: 内容 | AF4: 金额（元） | AG4: 经营奖金（元） | AH4: 生产奖金（元）
A5: 1 | B5: 2020年延庆区乡村公路建养工程勘察设计---2标 | C5: 2020.1.10 | D5: 安防一标段 | E5: 河南交规院 | F5: HNJH2020-001 | G5: 北京市交通委员会延庆分局 | H5: 张旭学 | I5: 13811589649 | J5: 杨建东 | K5: 杨建东 | L5: 101006 | O5: 48435 | R5: =O5 -> 48435 | U5: =R5 -> 48435 | V5: =U5+U6 -> 125220 | W5: =U5 -> 48435 | X5: =W5 -> 48435 | Y5: =V5-X5-X6 -> 0 | Z5: =V5*0.8 -> 100176 | AA5: =W5*0.8 -> 38748 | AB5: =AA5 -> 38748 | AC5: =Z5-AB5-AB6 -> 0 | AG5: 12108.75 | AH5: 7749.6 | AI5: =Z5-AF5-AG6-AH65-AF6-AG5-AH5-AH6 -> 48835.8 | AK5: =AG5/R5 -> 0.25 | AL5: =AH5/AB5 -> 0.2
D6: 安防二标段 | L6: 151472 | O6: 76785 | R6: =O6 -> 76785 | U6: =R6 -> 76785 | W6: =U6 -> 76785 | X6: =W6 -> 76785 | AA6: =W6*0.8 -> 61428 | AB6: =AA6 -> 61428 | AG6: 19196.25 | AH6: 12285.6 | AK6: =AG6/R6 -> 0.25 | AL6: =AH6/AB6 -> 0.2
A7: 2 | B7: 通州区体育局2020年健身步道工程 | C7: 2020.1.10 | D7: 6.489公里 | E7: 河南交规院 | F7: HNJH2020-002 | G7: 北京市通州体育局 | H7: 王栋 | I7: 18610277462 | J7: 王新星 | K7: 王新星 | L7: 980573 | M7: 294172 | O7: 575545.53 | P7: 91451.59 | R7: =O7 -> 575545.53 | S7: =P7 -> 91451.59 | U7: =R7+S7 -> 666997.12 | V7: =U7 -> 666997.12 | W7: =V7 -> 666997.12 | X7: =W7 -> 666997.12 | Y7: =V7-X7-X9 -> 0 | Z7: =V7*0.8 -> 533597.7 | AA7: =W7*0.8 -> 533597.7 | AB7: =AA7 -> 533597.7 | AC7: =Z7-AB7 -> 0 | AD7: 任永超 | AE7: 测绘 | AF7: =8.21*1500 -> 12315 | AG7: =156572.1 -> 156572.1 | AH7: =86467 -> 86467 | AI7: =Z7-AG7-AH7-AF7-AF8 -> 277043.6 | AK7: =AG7/V7 -> 0.23474179 | AL7: =AH7/R7/0.8 -> 0.18779357
AD8: 张华 | AE8: 效果图 | AF8: =300*4 -> 1200
A10: 3 | B10: 2020年延庆区普通公路路面、桥梁、隧道中小修工程第3标---隧道 | C10: 2020.1.10 | E10: 河南交规院 | F10: HNJH2020-003 | G10: 北京市交通委员会延庆分局 | H10: 吴颖 | I10: 13488805779 | J10: 杨建东 | K10: 杨建东 | X10: 0 | Y10: =V10-X10-X12 -> 0 | Z10: =V10*0.8 -> 0
X12: 0
A13: 4 | B13: 2020年延庆路网外场设备更新工程 | C13: 2020.3 | D13: 兴阳线、京青线、滦赤路、安四路、妫川路5条道路上更新15套设备，其中更新超声波交调设备8套，可变情报板设备6套，视频监控设备1套，在京青线拆除2套微波交调设备。 | E13: 河南交规院 | F13: HNJH2020-004 | G13: 北京市交通委员会延庆分局 | H13: 于伟 | I13: 13701025230 | J13: 杨建东 | K13: 杨建东 | L13: 82209 | O13: 53949 | R13: =O13 -> 53949 | U13: =R13+S13+T13 -> 53949 | V13: =U13 -> 53949 | W13: =V13 -> 53949 | X13: =W13 -> 53949 | Y13: =V13-X13-X15 -> 0 | Z13: =V13*0.8 -> 43159.2 | AA13: =W13*0.8 -> 43159.2 | AB13: =AA13 -> 43159.2 | AC13: =Z13-AB13 -> 0 | AI13: =Z13-AG13-AH13 -> 43159.2
A16: 5 | B16: 北京市2021年延庆区G234、沈韩路、千小路预防性养护工程2标段勘察设计工程 | C16: 2020.3 | D16: 沈韩路 | E16: 河南交规院 | F16: HNJH2020-005 | G16: 北京市交通委员会延庆分局 | H16: 刑工 | I16: 13810992745 | J16: 杨建东 | K16: 杨建东 | L16: =O16 -> 209490 | M16: =P16 -> 36969 | N16: 0 | O16: 209490 | P16: 36969 | Q16: 0 | R16: =O16-381.75 -> 209108.25 | S16: =P16 -> 36969 | T16: =Q16 -> 0 | U16: =R16+S16+T16 -> 246077.25 | V16: =U16 -> 246077.25 | W16: 225160.59 | X16: 225160.59 | Y16: =V16-X16-X17-X18 -> 3.6379788e-12 | Z16: =V16*0.8 -> 196861.8 | AA16: =W16*0.8 -> 180128.47 | AB16: =X16*0.8 -> 180128.47 | AC16: =Z16-AB16 -> 16733.328 | AD16: 韩国峰 | AE16: 测绘 | AF16: =7*2500 -> 17500
W17: 20916.66 | X17: 20916.66 | AD17: 韩国峰 | AE17: 取芯 | AF17: =8*200 -> 1600
A19: 8 | B19: 燕山地区迎风南路、迎风街路域环境提升工程---燕山政府西环路 | C19: 2020.3 | D19: 慢行系统、景观绿化、公共交通、环境卫生、照明系统提升 | E19: 河南交规院 | F19: HNJH2020-008 | G19: 燕山区办事处 | H19: 穆科长 | I19: 13910416067 | J19: 王新星 | K19: 杨建东 | L19: 1312407 | AD19: 张华 | AE19: 效果图 | AF19: =6*300 -> 1800
A21: 10 | B21: 通州区乡村公路咨询 | C21: 2020.3 | D21: 编制《乡村公路示范路方案咨询报告》 | E21: 北京逸群 | F21: YQJH2020-010 | G21: 北京市交通委员会通州分局 | H21: 张伟 | I21: 13439987630 | J21: 王新星 | K21: 王新星 | N21: 195000 | Q21: 176882 | T21: =U21 -> 176882 | U21: =Q21 -> 176882 | V21: 176882 | W21: =V21 -> 176882 | X21: =W21 -> 176882 | Y21: =V21-X21 -> 0 | Z21: =V21*0.85+0.3 -> 150350 | AA21: =Z21 -> 150350 | AB21: =AA21 -> 150350 | AC21: =Z21-AB21 -> 0 | AD21: 张华 | AE21: 效果图 | AF21: =10*300 -> 3000 | AH21: =28235 -> 28235 | AI21: =Z21-AG21-AH21-AF21 -> 119115
D23: 编制《乡村公路大修工程设计指南》 | N23: 193000 | Q23: 193000 | T23: =Q23 -> 193000 | U23: =T23 -> 193000 | V23: =U23 -> 193000 | W23: =V23 -> 193000 | X23: =W23 -> 193000 | Y23: =V23-X23 -> 0 | Z23: =V23*0.85 -> 164050 | AA23: =Z23 -> 164050 | AB23: =AA23 -> 164050 | AC23: =Z23-AB23 -> 0 | AI23: =Z23-AG23-AH23 -> 164050
A25: 12 | B25: 2020年延庆区妫川路等公路路域环境整治工程 | C25: 2020.4 | E25: 河南交规院 | F25: HNJH2020-012 | G25: 北京市交通委员会延庆分局 | H25: 刑工 | I25: 13810992745 | J25: 杨建东 | K25: 杨建东 | L25: 337094 | M25: 50865 | O25: 331489 | P25: 50865 | R25: =O25 -> 331489 | S25: =P25 -> 50865 | U25: =R25+S25+T25 -> 382354 | V25: =U25 -> 382354 | W25: 349205 | X25: =W25 -> 349205 | Y25: =V25-X25-X26 -> 0 | Z25: =V25*0.8 -> 305883.2 | AA25: 279364 | AB25: =AA25 -> 279364 | AC25: =Z25-AB25-AB26 -> 0 | AD25: 刘素良 | AE25: 测绘 | AF25: =3.2*2500 -> 8000 | AG25: =81973 -> 81973 | AH25: =44821.03 -> 44821.03 | AI25: =Z25-AF25-AF26-AG25-AH25-AG26-AH26 -> 169589.17 | AK25: =AG25/V25 -> 0.21439033 | AL25: =AH25/(R25*0.8) -> 0.16901402
W26: 33149 | X26: 33149 | AA26: =X26*0.8 -> 26519.2 | AB26: =AA26 -> 26519.2 | AD26: 张华 | AE26: 效果图 | AF26: =5*300 -> 1500
A27: 13 | B27: 宁夏回族自治区交通运输综合执法监督局2020年迎国检项目施工图设计 | C27: 2020.7 | D27: 宁夏回族自治区交通运输综合执法监督局2020年迎国检项目对宁夏回族自治区交通运输综合执法监督局所辖银川分局、石嘴山分局、吴忠分局、中卫分局、固原分局下属治超检测站根据实际情况进行部分设施维修更换，包括更换检测车道票亭、检测车道岛头维修粉刷、指示标志标牌维修更换、检测大棚线路维护等；对部分站点进行改造包括：对黄羊滩治超检测站西侧检测车道出入口进行延长拓宽改造；在水洞沟治超检测站增装计重地磅1台；在银巴治超检测站建设3000㎡固定卸载场，卸载场安装静态汽车衡称重复检设备1套；在关马湖治超检测站道口以南新修一条与G344线斜交的货车引道；国道307盐池治超检测站更换计重地磅2台；将S301线石炭井沟口超限检测站搬迁至原S301线石炭井收费站。 | E27: 河南交规院 | F27: HNJH2020-013 | O27: 336000 | U27: 336000 | V27: =U27 -> 336000 | W27: 336000 | X27: =W27 -> 336000 | Y27: =W27-X27 -> 0 | Z27: =V27*0.8 -> 268800 | AA27: =Z27 -> 268800 | AB27: =AA27 -> 268800 | AC27: =Z27-AB27 -> 0 | AD27: 李文博 | AE27: 咨询 | AF27: =V27*0.75 -> 252000 | AG27: 0 | AH27: 0 | AI27: =Z27-AF27 -> 16800
A28: 15 | B28: 2021年房山区普通公路养护工程第3标段：2021年房山区班陈路、紫码路修复养护工程勘察设计 | C28: 2020.4 | D28: 班陈路起点为京昆线，终点陈家台，全长5.583km。K0+000-K0+268、K0+514-K5+583段技术等级为三级公路；K0+268-K0+514段技术等级为二级公路。本次设计段落为班陈路全段。 | E28: 河南交规院 | F28: HNJH2020-015 | G28: 北京市交通委员会房山分局 | H28: 白秀龙 | I28: 13811745176 | J28: 王新星 | K28: 王新星 | L28: 137645 | M28: 45224 | N28: 0 | AD28: 任永超 | AE28: 测绘 | AF28: =5.58*2500 -> 13950
AD29: 任永超 | AE29: 取芯 | AF29: =11*150 -> 1650
AD30: 中交路星 | AE30: 路检 | AF30: =5.583*800 -> 4466.4
D31: 紫码路本次设计段落为K0+000+K4+000，设计长度4km。其中K2+904-K4+000技术等级为三级公路外，其余设计路段为二级公路。 | L31: 184762 | M31: 35608 | N31: 0 | AD31: 任永超 | AE31: 测绘 | AF31: =4.35*2500 -> 10875
AD32: 任永超 | AE32: 取芯 | AF32: =10*150 -> 1500
A34: 16 | B34: 房东路污水管线回填道路恢复工程 | C34: 2020.4 | D34: 路面恢复总面积为3215.4㎡ | E34: 河南交规院 | F34: HNJH2020-016 | G34: 北京市房山区河北镇人民政府 | H34: 肖建营 | I34: 13911835251 | J34: 杨建东 | K34: 杨建东 | L34: 311577.81 | O34: 107181.6 | R34: =O34 -> 107181.6 | U34: =R34+S34+T34 -> 107181.6 | V34: =U34 -> 107181.6 | W34: 107181.6 | X34: =W34 -> 107181.6 | Y34: =V34-X34-X35 -> 0
W35: 0 | X35: 0
A36: 17 | B36: 南海子北环路污水管线工程 | C36: 2020.5 | D36: 污水管线700m | E36: 北京专业院 | F36: ZYJH2020-017 | G36: 北京国苑投资有限公司 | H36: 侯光 | I36: 13910665470 | J36: 王新星 | K36: 王新星 | AJ36: 暂缓
X37: =W37 -> 0
A38: 18 | B38: 2020年通州区台湖镇乡村公路安全生命防护工程 ---台东路、铺外二路、大地路 | C38: 2020.5 | D38: 新建护栏约计890m | E38: 河南交规院 | F38: HNJH2020-018 | G38: 北京市通州区台湖公路管理站 | H38: 李立明 | I38: 13366736778 | J38: 王新星 | K38: 王新星 | X38: =W38 -> 0
O39: 4958.17 | R39: =O39 -> 4958.17 | V39: =R39 -> 4958.17 | W39: 4958.17 | X39: =W39 -> 4958.17 | Y39: =V39-X39 -> 0 | Z39: =V39*0.8 -> 3966.536 | AA39: 3966.54 | AB39: 3966.54 | AC39: =Z39-AB39 -> -0.004
A40: 19 | B40: 2021年通州区普通公路、桥梁养护工程第1标段勘察设计：2021 年通州区柏德路(K3+450-K12+561) 修复养护工程勘察设计 | C40: 2020.6 | D40: 现况道路K3+450-K9+130 段为二级公路，路基横断面为一幅路，路面宽12.5(16)米，路基宽14.5(20)米。K9+130-K12+561 道路等级为三级公路，路基横断面为一幅路，路面宽7.0 米，路基宽9.0 米，全长9.111 公里 | E40: 河南交规院 | F40: HNJH2020-019 | G40: 北京市交通委员会通州分局 | H40: 王晓强 | I40: 13501231567 | J40: 王新星 | K40: 王新星 | L40: 706667 | M40: 84308 | X40: =W40 -> 0 | AD40: 任永超 | AE40: 测绘+取芯 | AF40: =9.111*2500+8*150 -> 23977.5
X41: =W41 -> 0 | AD41: 十九处 | AE41: 弯沉 | AF41: =91*50 -> 4550
X42: =W42 -> 0
A43: 20 | B43: 国网北京房山供电公司电力管线回填 | C43: 2020.6 | D43: 国网北京房山供电公司迎风地区1#开闭站（三供一业）配套外电源改造工程-道路恢复工程 | E43: 河南交规院 | F43: HNJH2020-020 | G43: 国网北京房山供电公司 | H43: 刘睿轩 | I43: 15810458298 | J43: 曹立东 | K43: 王新星 | L43: 504878.95 | R43: 67483.355 | U43: =R43 -> 67483.355 | V43: =U43 -> 67483.355 | W43: =V43 -> 67483.355 | X43: =W43 -> 67483.355 | Y43: =V43-X43 -> 0 | Z43: =V43*0.95-0.86 -> 64108.327 | AA43: =Z43 -> 64108.327 | AB43: =AA43 -> 64108.327 | AC43: =Z43-AB43 -> 0
D44: 国网北京房山供电公司迎风地区2#开闭站（三供一业）配套外电源改造工程--道路恢复工程 | L44: 429369.06 | R44: 57390.518 | U44: =R44 -> 57390.518 | V44: =U44 -> 57390.518 | W44: =V44 -> 57390.518 | X44: =W44 -> 57390.518 | Y44: =V44-X44 -> 0 | Z44: =V44*0.95 -> 54520.992 | AA44: =Z44 -> 54520.992 | AB44: =AA44 -> 54520.992 | AC44: =Z44-AB44 -> 0
D45: 国网北京房山供电公司东风地区2#开闭站（三供一业）配套外电源改造工程--道路恢复工程 | L45: 320008.45 | R45: 42773.112 | U45: =R45 -> 42773.112 | V45: =U45 -> 42773.112 | W45: =V45 -> 42773.112 | X45: =W45 -> 42773.112 | Y45: =V45-X45 -> 0 | Z45: =V45*0.95 -> 40634.456 | AA45: =Z45 -> 40634.456 | AB45: =AA45 -> 40634.456 | AC45: =Z45-AB45 -> 0
D46: 国网北京房山供电公司东风地区1#开闭站（三供一业）配套外电源改造工程--道路恢复工程 | L46: 452979.99 | R46: 60546.413 | U46: =R46 -> 60546.413 | V46: =U46 -> 60546.413 | W46: =V46 -> 60546.413 | X46: =W46 -> 60546.413 | Y46: =V46-X46 -> 0 | Z46: =V46*0.95 -> 57519.092 | AA46: =Z46 -> 57519.092 | AB46: =AA46 -> 57519.092 | AC46: =Z46-AB46 -> 0
D47: 国网北京房山供电公司富燕新村区开闭站（三供一业）配套外电源改造工程--道路恢复工程 | L47: 88832 | R47: 11873.502 | U47: =R47 -> 11873.502 | V47: =U47 -> 11873.502 | W47: =V47 -> 11873.502 | X47: =W47 -> 11873.502 | Y47: =V47-X47 -> 0 | Z47: =V47*0.95 -> 11279.827 | AA47: =Z47 -> 11279.827 | AB47: =AA47 -> 11279.827 | AC47: =Z47-AB47 -> 0
A48: 21 | B48: 房山区G108（K34+300-K42+000）预防性养护工程勘察设计 | C48: 2020.7 | D48: 预养 | E48: 河南交规院 | F48: HNJH2020-021 | G48: 北京市交通委员会房山分局 | H48: 白秀龙 | I48: 13811745176 | J48: 杨建东 | K48: 王新星 | L48: 50292 | M48: 77000 | O48: 50198 | P48: 77000 | R48: =O48 -> 50198 | S48: =P48 -> 77000 | U48: =R48+S48 -> 127198 | V48: =U48 -> 127198 | W48: 101833.6 | X48: =W48 -> 101833.6 | Y48: =V48-X48-X49 -> 0 | Z48: =V48*0.8 -> 101758.4 | AA48: =X48*0.8 -> 81466.88 | AB48: =AA48 -> 81466.88 | AC48: =Z48-AB48-AB49 -> 0 | AG48: =23904.6 -> 23904.6 | AH48: 0 | AI48: =Z48-AG48-AH48 -> 77853.8 | AK48: =AG48/V48 -> 0.1879322 | AL48: =AH48/(R48*0.8) -> 0
W49: 25364.4 | X49: =W49 -> 25364.4 | AA49: =X49*0.8 -> 20291.52 | AB49: =AA49 -> 20291.52
A50: 22 | B50: 房东路燃气管线回填道路恢复工程 | C50: 2020.11 | D50: 440平米 | E50: 河南交规院 | F50: HNJH2020-022 | G50: 北京市房山区河北镇人民政府 | H50: 肖建营 | I50: 13911835251 | J50: 杨建东 | K50: 杨建东 | L50: 78996 | O50: 78996
A53: 总计 | L53: =SUM(L5:L52) -> 6440259.3 | M53: =SUM(M5:M52) -> 624146 | N53: =SUM(N5:N52) -> 388000 | O53: =SUM(O5:O52) -> 1873027.3 | P53: =SUM(P5:P52) -> 256285.59 | Q53: =SUM(Q5:Q52) -> 369882 | R53: =SUM(R5:R52) -> 1697716.4 | S53: =SUM(S5:S6) -> 0 | T53: =SUM(T5:T6) -> 0 | U53: =SUM(U5:U52) -> 2654925.9 | V53: =SUM(V5:V52) -> 2659884 | W53: =SUM(W5:W52) -> 2659884 | X53: =SUM(X5:X52) -> 2659884 | Y53: =SUM(Y5:Y52) -> 3.6379788e-12 | Z53: =SUM(Z5:Z52) -> 2096665.5 | AA53: =SUM(AA5:AA52) -> 2079932.2 | AB53: =SUM(AB5:AB52) -> 2079932.2 | AC53: =SUM(AC5:AC52) -> 16733.324 | AF53: =SUM(AF5:AF52) -> 359883.9 | AG53: =SUM(AG5:AG52) -> 293754.7 | AH53: =SUM(AH5:AH52) -> 179558.23 | AI53: =SUM(AI5:AI52) -> 916446.57
A54: 2020年上报数值 | L54: 6333769.3 | M54: 642545 | N54: 190000 | O54: 1141359.7 | P54: 219316.59 | Q54: 176882 | R54: 1136401.5 | S54: 0 | T54: 0 | U54: 1355718.1 | V54: 1537558.3 | W54: 1124881.7 | X54: 1124881.7 | Y54: 25364.4 | Z54: 851540.65 | AA54: 150349.7 | AB54: 150349.7 | AC54: 0 | AF54: 90917.5 | AG54: 255762.03 | AH54: 150824.26 | AI54: 495622.3
L57: =720/12 -> 60

Sheet 2021
A1: 项目经营管理台账（2021年）（电子）
A2: 序号 | B2: 项目信息 | G2: 经营信息 | L2: 概算信息（估算） | O2: 审计信息 | R2: 甲方信息 | Y2: 公司信息 | AH2: 备注
B3: 项目名称 | C3: 承接 日期 | D3: 项目概况 | E3: 资质 | F3: 项目编号 | G3: 单位 | H3: 联系人 | I3: 联系方式 | J3: 经营 负责人 | K3: 经营 参与人 | L3: 设计费（元） | M3: 勘察费（元） | N3: 咨询费（元） | O3: 设计费（元） | P3: 勘察费（元） | Q3: 咨询费（元） | R3: 合同/补充协议额（元） | V3: 甲方支付信息 | Y3: 公司收入信息 | AB3: 公司支付信息 | AG3: 公司结余 （元）
R4: 设计费（元） | S4: 勘察费（元） | T4: 咨询费（元） | U4: 合计额（元） | V4: 应支额（元） | W4: 支付金额（元） | X4: 未收金额（元） | Y4: 应收额（元） | Z4: 实收金额（元） | AA4: 未收金额（元） | AB4: 经营奖金（元） | AC4: 生产奖金（元） | AD4: 单位 （个人） | AE4: 内容 | AF4: 金额（元）
A5: 1 | B5: 2021年房山区普通公路养护工程勘察设计（查）设计第1标段---2021年房山区普通公路交通工程勘察设计 | C5: 20221.1.3 | D5: 2021年房山区公路交通安全隐患治理工程 | E5: 河南交规院 | F5: HNJH2021-001 | G5: 北京市交通委员会房山分局 | H5: 王现卫 | I5: 13552275070 | J5: 王新星 | K5: 曹立冬 | L5: 169969 | O5: =L5 -> 169969 | R5: =O5 -> 169969 | U5: =SUM(R5:T7) -> 169969 | V5: =U5 -> 169969 | W5: 144474 | X5: =V5-W5-W6-W7 -> 0 | Y5: =V5*0.8 -> 135975.2 | Z5: =W5*0.8 -> 115579.2 | AA5: =Y5-Z5-Z6-Z7 -> 0 | AD5: 刘素良 | AE5: 测绘 | AF5: =0.2*2500 -> 500 | AG5: =Y5-AB5-AC5-AF5-AF6-AF7 -> 135475.2
W6: 25495 | Z6: =W6*0.8 -> 20396
W7: 0
A8: 2 | B8: 2021年房山区普通公路路面和桥梁中小修工程勘察设计---第1标段—2021年房山区普通公路国省道路面中小修工程勘察设计 | C8: 2021.2. | D8: 2021年普通公路水毁恢复工程 | E8: 河南交规院 | F8: HNJH2021-002 | G8: 北京市交通委员会房山分局 | H8: 王现卫 | I8: 13552275070 | J8: 王新星 | K8: 王新星 | L8: 147220 | O8: 129380 | R8: =O8 -> 129380 | U8: =SUM(R8:T10) -> 129380 | V8: =U8 -> 129380 | W8: 103504 | X8: =V8-W8-W9-W10 -> 0 | Y8: =V8*0.8 -> 103504 | Z8: =W8*0.8 -> 82803.2 | AA8: =Y8-Z8-Z9-Z10 -> 20700.8 | AG8: =Y8-AB8-AC8-AF8-AF9-AF10 -> 103504
W9: 25876
W10: 0
A11: 3 | B11: 星城地区主要道路提升工程 | C11: 2020.2 | D11: 综合治理，城市次干路5.2km | E11: 河南交规院 | F11: HNJH2021-003 | G11: 北京市房山区燕山城市管理和交通委员会 | H11: 穆佳楠 | I11: 13910416067 | J11: 王新星 | K11: 王新星 | R11: 0 | U11: =SUM(R11:T13) -> 0 | V11: =U11 -> 0 | W11: 0 | X11: =V11-W11-W12-W13 -> 0 | Y11: =V11*0.8 -> 0 | AA11: =Y11-Z11-Z12-Z13 -> 0 | AG11: =Y11-AB11-AC11-AF11-AF12-AF13 -> 0
W12: 0
W13: 0
A14: 4 | B14: 2021年延庆区普通公路路面、桥梁、隧道中小修工程勘察设计第1标段：2021年延庆区普通公路路面中小修工程勘察设计 | C14: 2020.3.1 | D14: 东刘路中修工程，4.49km | E14: 河南交规院 | F14: HNJH2021-004 | G14: 北京市交通委员会延庆分局 | H14: 刑工 | I14: 13810992745 | J14: 杨建东 | K14: 杨建东 | L14: 115594 | M14: 20399 | N14: 0 | O14: =134570*0.85 -> 114384.5 | P14: =134570*0.15 -> 20185.5 | Q14: 0 | R14: =O14 -> 114384.5 | S14: =P14 -> 20185.5 | T14: =Q14 -> 0 | U14: =SUM(R14:T15) -> 134570 | V14: =U14 -> 134570 | W14: 123132 | X14: =V14-W14-W15 -> 0 | Y14: =V14*0.8 -> 107656 | Z14: =W14*0.8 -> 98505.6 | AA14: =Y14-Z14-Z15 -> 0 | AD14: 刘素良 | AE14: 测绘 | AF14: =2500*4.49 -> 11225 | AG14: =Y14-AB14-AC14-AF14-AF15 -> 94031 | AH14: 测绘沿用2016年成果
W15: 11438 | Z15: =W15*0.8 -> 9150.4 | AD15: 刘素良 | AE15: 取芯 | AF15: =16*150 -> 2400
D16: 北西路（戴工分包） | O16: 111425 | P16: 0 | Q16: 0 | R16: =O16 -> 111425 | S16: =P16 -> 0 | T16: =Q16 -> 0 | U16: =SUM(R16:T17) -> 111425 | V16: =U16 -> 111425 | W16: 101954 | X16: =V16-W16-W17 -> 0 | Y16: =V16*0.8 -> 89140 | Z16: =W16*0.8 -> 81563.2 | AA16: =Y16-Z16-Z17 -> -1.1823431e-11 | AD16: 戴时云 | AE16: 咨询 | AF16: =V16*0.75 -> 83568.75 | AG16: =Y16-AF16 -> 5571.25 | AH16: 戴工分包
W17: 9471 | Z17: =W17*0.8 -> 7576.8
A18: 5 | B18: 新华家园外电源工程—兴阳线电力管线开挖及回填道路恢复工程 | C18: 2021.3 | D18: 电力管线回填及路面恢复，长890米，面积4490m2 | E18: 河南交规院 | F18: HNJH2021-005 | G18: 新华家园健康科技（北京）有限公司 | J18: 杨建东 | K18: 杨建东 | L18: 159887 | M18: 0 | N18: 0 | O18: =L18 -> 159887 | P18: 0 | Q18: 0 | R18: =O18 -> 159887 | S18: 0 | T18: 0 | U18: =SUM(R18:T20) -> 159887 | V18: =U18 -> 159887 | W18: 143898.3 | X18: =V18-W18-W19 -> 0 | Y18: =V18*0.8 -> 127909.6 | Z18: =W18*0.8 -> 115118.64 | AA18: =Y18-Z18-Z19-Z20 -> 5.4569682e-12 | AB18: =22969.68 -> 22969.68 | AC18: 21618.52 | AG18: =Y18-AB18-AC18-AF18-AF19-AF20 -> 83321.4 | AI18: =AB18/V18 -> 0.14366196 | AJ18: =AC18/R18/0.8 -> 0.16901405
W19: 15988.7 | Z19: =W19*0.8 -> 12790.96
W20: 0 | Z20: =W20*0.8 -> 0
A21: 6 | B21: 改善办学条件-基础设施改造-校园道路及附属设施改造工程（设计） | C21: 2021.4 | E21: 河南交规院 | F21: HNJH2021-006 | G21: 北京农业职业学院 | H21: 盖振华 | J21: 王新星 | K21: 王新星 | L21: 349996.52 | O21: 320000 | R21: =O21 -> 320000 | U21: =SUM(R21:T23) -> 320000 | V21: =U21 -> 320000 | W21: 96000 | X21: =V21-W21-W22-W23 -> 0 | Y21: =V21*0.8 -> 256000 | Z21: =W21*0.8 -> 76800 | AA21: =Y21-Z21-Z22-Z23 -> 0 | AB21: =45971.83+54028.17 -> 100000 | AC21: =38460.09+48075.12*0.2 -> 48075.114 | AD21: 专家费 | AF21: 2800 | AG21: =Y21-AB21-AC21-AF21-AF22-AF23 -> 98824.886 | AI21: =AB21/V21 -> 0.3125 | AJ21: =AC21/R21/0.8 -> 0.18779341
W22: 192000 | Z22: =W22*0.8 -> 153600 | AD22: 代理服务费 | AF22: 4800
W23: 32000 | Z23: =W23*0.8 -> 25600 | AD23: 招标文件 | AF23: 1500
A24: 7 | B24: 2021年延庆区标线覆划工程 | C24: 2021.7 | E24: 河南交规院 | F24: HNJH2021-007 | G24: 北京市交通委员会延庆分局 | H24: 刘一圻 | I24: 15210239334 | J24: 杨建东 | K24: 杨建东 | L24: 70488 | O24: =R24 -> 69783 | R24: =6978+62805 -> 69783 | U24: =SUM(R24:T25) -> 69783 | V24: =U24 -> 69783 | W24: 62805 | X24: =V24-W24-W25 -> 0 | Y24: =V24*0.8 -> 55826.4 | Z24: =W24*0.8 -> 50244 | AA24: =Y24-Z24-Z25 -> 0 | AG24: =Y24-AB24-AC24-AF24-AF25 -> 55826.4
W25: 6978 | Z25: =W25*0.8 -> 5582.4
A26: 8 | B26: 京雄高速跨路交通导行工程//、京雄高速跨路恢复工程（同上合并） | C26: 2021.7 | D26: 3工区（走瑞通）（走京宏） | E26: 河南交规院 | F26: HNJH2021-008-1 | G26: 京雄高速项目经理部 | H26: 闫超 | I26: 13811311956 | J26: 曹立冬 | K26: 曹立冬 | L26: 124586.5 | O26: =L26 -> 124586.5 | R26: =O26 -> 124586.5 | U26: =SUM(R26:T28) -> 124586.5 | V26: =U26 -> 124586.5 | W26: 0 | X26: =V26-W26-W27-W28 -> 124586.5 | Y26: =V26 -> 124586.5 | AA26: =Y26-Z26-Z27-Z28 -> 124586.5 | AG26: =Y26-AB26-AC26-AF26-AF27-AF28 -> 124586.5
W27: 0
W28: 0
C29: 2021.7 | D29: 4工区（走河南交规院），长于路支线永久导改工程 | E29: 河南交规院 | F29: HNJH2021-008-2 | J29: 曹立冬 | K29: 曹立冬 | L29: 70785 | O29: =L29 -> 70785 | R29: 70785 | U29: =SUM(R29:T31) -> 70785 | V29: =U29 -> 70785 | W29: 0 | X29: =V29-W29-W30-W31 -> 70785 | Y29: =V29*0.8 -> 56628 | AA29: =Y29-Z29-Z30-Z31 -> 56628 | AG29: =Y29-AB29-AC29-AF29-AF30-AF31 -> 56628
W30: 0
W31: 0
C32: 2021.7 | D32: 4工区（走河南交规院），长阳路导改 | E32: 河南交规院 | F32: HNJH2021-008-2 | H32: 张哲 | I32: 15533018887 | J32: 曹立冬 | K32: 曹立冬 | L32: 24136.7 | O32: 24136.7 | R32: 24136.7 | U32: =SUM(R32:T34) -> 24136.7 | V32: =U32 -> 24136.7 | W32: 0 | X32: =V32-W32-W33-W34 -> 24136.7 | Y32: =V32*0.8 -> 19309.36 | AA32: =Y32-Z32-Z33-Z34 -> 19309.36 | AG32: =Y32-AB32-AC32-AF32-AF33-AF34 -> 19309.36
W33: 0
W34: 0
C35: 2021.7 | D35: 6工区（走瑞通）（走京宏） | E35: 河南交规院 | F35: HNJH2021-008-3 | J35: 曹立冬 | K35: 曹立冬 | L35: 162660.48 | R35: 0 | U35: =SUM(R35:T37) -> 0 | V35: =U35 -> 0 | W35: 0 | X35: =V35-W35-W36-W37 -> 0 | Y35: =V35*0.8 -> 0 | AA35: =Y35-Z35-Z36-Z37 -> 0 | AG35: =Y35-AB35-AC35-AF35-AF36-AF37 -> 0
W36: 0
W37: 0
C38: 2021.7 | D38: 7工区（走京宏） | E38: 河南交规院 | F38: HNJH2021-008-4 | J38: 曹立冬 | K38: 曹立冬 | L38: 54382 | O38: =L38 -> 54382 | R38: 54382 | U38: =SUM(R38:T40) -> 54382 | V38: =U38 -> 54382 | W38: 54382 | X38: =V38-W38-W39-W40 -> 0 | Y38: =U38 -> 54382 | Z38: =Y38 -> 54382 | AA38: =Y38-Z38-Z39-Z40 -> 0 | AG38: =Y38-AB38-AC38-AF38-AF39-AF40 -> 54382
W39: 0 | Z39: 0
W40: 0 | Z40: 0
C41: 2021.7 | D41: 8工区（走京宏） | E41: 河南交规院 | F41: HNJH2021-008-5 | J41: 曹立冬 | K41: 曹立冬 | L41: 42278 | O41: =L41 -> 42278 | R41: 42278 | U41: =SUM(R41:T43) -> 42278 | V41: =U41 -> 42278 | W41: 42278 | X41: =V41-W41-W42-W43 -> 0 | Y41: =V41 -> 42278 | Z41: =Y41 -> 42278 | AA41: =Y41-Z41-Z42-Z43 -> 0 | AG41: =Y41-AB41-AC41-AF41-AF42-AF43 -> 42278
W42: 0 | Z42: 0
W43: 0 | Z43: 0
A44: 9 | B44: 2021年延庆区普通公路路面、桥梁、隧道中小修工程勘察设计第1标段：2021年延庆区普通公路路面中小修工程勘察设计 | C44: 2021.7 | D44: 四宝路水毁恢复工程 | E44: 河南交规院 | F44: HNJH2021-009 | J44: 杨建东 | K44: 杨建东 | L44: 86316 | M44: 15232 | O44: =INT(L44*0.99)+1 -> 85453 | P44: =INT(M44*0.99) -> 15079 | R44: =O44 -> 85453 | S44: =P44 -> 15079 | U44: =SUM(R44:T46) -> 100532 | V44: =U44 -> 100532 | W44: 91987 | X44: =V44-W44-W45-W46 -> 0 | Y44: =V44*0.8 -> 80425.6 | Z44: =W44*0.8 -> 73589.6 | AA44: =Y44-Z44-Z45-Z46 -> 0 | AG44: =Y44-AB44-AC44-AF44-AF45-AF46 -> 80425.6
W45: 8545 | Z45: =W45*0.8 -> 6836
W46: 0 | Z46: 0
A47: 10 | B47: 2021年延庆区昌赤路利民街路口隐患治理工程 | C47: 2021.8 | D47: 本项目位于昌赤路K50+726交叉口处。由于现况路口交通组织混乱，未设置信号灯，存在安全隐患，拟对本处路口实施隐患治理工程 | E47: 河南交规院 | F47: HNJH2021-010 | J47: 杨建东 | K47: 杨建东 | L47: 66822 | M47: 11792 | O47: =INT(L47*0.99)-369 -> 65784 | P47: =INT(M47*0.99) -> 11674 | R47: =O47 -> 65784 | S47: =P47 -> 11674 | U47: =SUM(R47:T49) -> 77458 | V47: =U47 -> 77458 | W47: 70874 | X47: =V47-W47-W48-W49 -> 0 | Y47: =V47*0.8 -> 61966.4 | Z47: =W47*0.8 -> 56699.2 | AA47: =Y47-Z47-Z48-Z49 -> -3.6379788e-12 | AD47: 任永超 | AE47: 测绘 | AF47: =0.6*2500 -> 1500 | AG47: =Y47-AB47-AC47-AF47-AF48-AF49 -> 60466.4
W48: 6584 | Z48: =W48*0.8 -> 5267.2
W49: 0 | Z49: =W49*0.8 -> 0
A50: 11 | B50: 2021年延庆区普通公路路面、桥梁、隧道中小修工程勘察设计第1标段：2021年延庆区普通公路路面中小修工程勘察设计 | C50: 2021.8 | D50: 2021年水毁抢通工程勘察设计 | E50: 河南交规院 | F50: HNJH2021-011 | J50: 杨建东 | K50: 杨建东 | L50: 76680.25 | O50: 75913 | R50: =O50 -> 75913 | U50: =SUM(R50:T52) -> 75913 | V50: =U50 -> 75913 | W50: 0 | X50: =V50-W50-W51-W52 -> 75913 | Y50: =V50*0.8 -> 60730.4 | Z50: =W50*0.8 -> 0 | AA50: =Y50-Z50-Z51-Z52 -> 60730.4 | AG50: =Y50-AB50-AC50-AF50-AF51-AF52 -> 60730.4
W51: 0 | Z51: =W51*0.8 -> 0
W52: 0 | Z52: =W52*0.8 -> 0
A53: 12 | B53: 2022年房山区普通公路养护工程勘察设计-----第3标段兴良路（K14+700-K20+682）综合治理工程勘察设计 | C53: 2021.9 | D53: 二级公路，长度6k | E53: 河南交规院 | F53: HNJH2021-012 | J53: 王新星 | K53: 曹立冬 | L53: 247348 | M53: 43650 | O53: 248408.99 | P53: 43836.88 | R53: =285178.04-S53 -> 242218.04 | S53: =INT(P53*0.98) -> 42960 | U53: =SUM(R53:T55) -> 285178.04 | V53: =U53 -> 285178.04 | W53: 229120 | X53: =V53-W53-W54-W55 -> -2.1827873e-11 | Y53: =V53*0.8 -> 228142.43 | Z53: =W53*0.8 -> 183296 | AA53: =Y53-Z53-Z54-Z55 -> 0 | AG53: =Y53-AB53-AC53-AF53-AF54-AF55 -> 228142.43
W54: 56058.04 | Z54: =W54*0.8 -> 44846.432
W55: 0 | Z55: =W55*0.8 -> 0
A56: 13 | B56: 北京市建设工程材料交易中心食堂燃气工程----道路恢复工程 | C56: 2021.9 | E56: 河南交规院 | F56: HNJH2021-013 | J56: 曹立冬 | K56: 曹立冬 | L56: 19397.35 | O56: =L56 -> 19397.35 | R56: =O56 -> 19397.35 | U56: =SUM(R56:T58) -> 19397.35 | V56: =U56 -> 19397.35 | W56: 0 | X56: =V56-W56-W57-W58 -> 19397.35 | Y56: 18400 | Z56: 18400 | AA56: =Y56-Z56-Z57-Z58 -> 0 | AG56: =Y56-AB56-AC56-AF56-AF57-AF58 -> 18400 | AH56: 给现金。5个点倒帐费。
W57: 0 | Z57: =W57*0.8 -> 0
W58: 0 | Z58: =W58*0.8 -> 0
A59: 14 | B59: 航天和兴军工设备研发生产基地项目 | C59: 2021.1 | D59: 项目占地面积约13265万平米，容积率1.99。项目建筑面积31756万平米（其中地下面积5300万平米），主要建设总装、总测车间、科研楼、办公楼 | E59: 河南交规院 | F59: HNJH2021-014 | J59: 王新星 | K59: 王新星 | L59: 2730000 | M59: 238000 | N59: 12000 | O59: 2730000 | P59: 238000 | Q59: 12000 | R59: =O59 -> 2730000 | S59: =P59 -> 238000 | T59: =Q59 -> 12000 | U59: =SUM(R59:T62) -> 2980000 | V59: =U59 -> 2980000 | W59: 596000 | X59: =V59-W59-W61-W62 -> 2384000 | Y59: =V59*0.8 -> 2384000 | Z59: =W59*0.8 -> 476800 | AA59: =Y59-Z59-Z61-Z62 -> 1907200 | AD59: 城建亚泰 | AE59: 建筑设计 | AF59: 850000 | AG59: =Y59-AB59-AC59-AF59-AF61-AF62 -> 1343600
W60: 0 | Z60: =W60*0.8 -> 0 | AD60: 任永超 | AE60: 测绘 | AF60: 12000
W61: 0 | Z61: =W61*0.8 -> 0 | AD61: 刘素良 | AE61: 地勘 | AF61: =238000*0.8 -> 190400
W62: 0 | Z62: =W62*0.8 -> 0
A63: 总计 | L63: =SUM(L5:L62) -> 4718546.8 | M63: =SUM(M5:M62) -> 329073 | N63: =SUM(N5:N62) -> 12000 | O63: =SUM(O5:O62) -> 4615953 | P63: =SUM(P5:P62) -> 328775.38 | Q63: =SUM(Q5:Q62) -> 12000 | R63: =SUM(R5:R62) -> 4609762.1 | S63: =SUM(S5:S62) -> 327898.5 | ... AB63: =SUM(AB5:AB62) -> 122969.68 | AC63: =SUM(AC5:AC7) -> 0 | AF63: =SUM(AF5:AF62) -> 1160693.8 | AG63: =SUM(AG5:AG7) -> 135475.2
A64: 2020年上报数值

Sheet 2022
A1: 项目经营管理台账（2022年）（电子）
A2: 序号 | B2: 项目信息 | G2: 经营信息 | L2: 概算信息（估算） | O2: 审计信息 | R2: 甲方信息 | Y2: 公司信息 | AH2: 备注
B3: 项目名称 | C3: 承接 日期 | D3: 项目概况 | E3: 资质 | F3: 项目编号 | G3: 单位 | H3: 联系人 | I3: 联系方式 | J3: 经营 负责人 | K3: 经营 参与人 | L3: 设计费（元） | M3: 勘察费（元） | N3: 咨询费（元） | O3: 设计费（元） | P3: 勘察费（元） | Q3: 咨询费（元） | R3: 合同/补充协议额（元） | V3: 甲方支付信息 | Y3: 公司收入信息 | AB3: 公司支付信息 | AG3: 公司结余 （元）
R4: 设计费（元） | S4: 勘察费（元） | T4: 咨询费（元） | U4: 合计额（元） | V4: 应支额（元） | W4: 支付金额（元） | X4: 未收金额（元） | Y4: 应收额（元） | Z4: 实收金额（元） | AA4: 未收金额（元） | AB4: 经营奖金（元） | AC4: 生产奖金（元） | AD4: 单位 （个人） | AE4: 内容 | AF4: 金额（元）
A5: 1 | B5: 2022年重大义务植树活动南火垡植树区域内道路修复工程 | C5: 2022.3 | E5: 河南交规院 | F5: HNJH2022-001 | G5: 张湾公路站 | H5: 卢世茹 | I5: 13520175981 | J5: 王新星 | K5: 王新星 | L5: 13090.26 | O5: 13090.26 | R5: 13090.26 | U5: =SUM(R5:T7) -> 13090.26 | V5: =U5 -> 13090.26 | W5: 13090.26 | X5: =V5-W5-W6-W7 -> 0 | Y5: =V5*0.8 -> 10472.208 | AA5: =Y5-Z5-Z6-Z7 -> 10472.208 | AG5: =Y5-AB5-AC5-AF5-AF6-AF7 -> 10472.208
W6: 0
W7: 0
A8: 2 | B8: 2022年大兴区普通公路中修、桥梁中修、小修维护及应急抢险工程、绿化工程和交通工程勘察设计第4标段 | C8: 2022.4 | E8: 河南交规院 | F8: HNJH2022-002 | G8: 北京市交通委员会大兴分局 | H8: 解鹏 | I8: 13381203969 | J8: 王新星 | K8: 王新星 | R8: 0 | U8: =SUM(R8:T10) -> 0 | V8: =U8 -> 0 | W8: 0 | X8: =V8-W8-W9-W10 -> 0 | Y8: =V8*0.8 -> 0 | AA8: =Y8-Z8-Z9-Z10 -> 0 | AG8: =Y8-AB8-AC8-AF8-AF9-AF10 -> 0
W9: 0
W10: 0
A11: 3 | B11: 2022年延庆区普通公路路面、桥梁、隧道中修工程、小修维护及应急抢险工程、绿化工程、交通工程勘察设计第1标段 | C11: 2022.4 | D11: 永艾路，5.733km，6m | E11: 河南交规院 | F11: HNJH2022-003-01 | G11: 北京市交通委员会延庆分局 | H11: 刑工 | I11: 13810992745 | J11: 杨建东 | K11: 杨建东 | O11: 134649 | P11: 23761 | R11: =O11 -> 134649 | S11: =P11 -> 23761 | U11: =R11+S11 -> 158410 | V11: =U11 -> 158410 | W11: 144945 | X11: =V11-W11-W12 -> 0 | Y11: =V11*0.8 -> 126728 | AA11: =Y11-Z11-Z13-Z22 -> -1645.6 | AD11: 任永超 | AE11: 测绘 | AF11: =5.733*2500 -> 14332.5 | AG11: =Y11-AB11-AC11-AF11-AF12 -> 110595.5
W12: 13465 | AD12: 任永超 | AE12: 取芯 | AF12: =12*150 -> 1800
D13: 千小路，6km，6m | F13: HNJH2022-003-02 | O13: 149068 | P13: 26306 | R13: =O13 -> 149068 | S13: =P13 -> 26306 | U13: =R13+S13 -> 175374 | V13: =U13 -> 175374 | W13: 160467 | X13: =V13-W13-W14 -> 14907 | Y13: =U13*0.8 -> 140299.2 | Z13: =W13*0.8 -> 128373.6 | AA13: =Y13-Z13-Z14 -> 11925.6 | AD13: 任永超 | AE13: 取芯 | AF13: =7*150 -> 1050 | AG13: =Y13-AB13-AC13-AF13-AF14 -> 139249.2
D15: 付小路边沟修复工程，200米 | F15: HNJH2022-003-03 | O15: =37685+3501 -> 41186 | R15: =O15 -> 41186 | U15: =R15+S15 -> 41186 | V15: =U15 -> 41186 | W15: 37685 | X15: =V15-W15-W16 -> 0 | Y15: 0 | AA15: 0 | AG15: =Y15-AB15-AC15-AF15-AF16 -> 0
W16: 3501
D17: 2022年延庆区普通公路挡墙恢复项目-2022年延庆区普通公路日常养护-滦赤路、兴阳线挡墙恢复项目 | F17: HNJH2022-003-04 | O17: 77193 | P17: 13622 | R17: =O17 -> 77193 | S17: =P17 -> 13622 | U17: =R17+S17 -> 90815 | V17: =U17 -> 90815 | W17: 83096 | X17: =V17-W17-W18 -> 0 | Y17: 0 | AA17: 0 | AG17: =Y17-AB17-AC17-AF17-AF18 -> 0
W18: 7719
D19: 祁付路，1.969km | F19: HNJH2022-003-05 | O19: 78637 | P19: 13877 | R19: =O19 -> 78637 | S19: =P19 -> 13877 | U19: =R19+S19 -> 92514 | V19: =U19 -> 92514 | W19: 84650 | X19: =V19-W19-W20 -> 7864 | Y19: =U19*0.8 -> 74011.2 | Z19: =W19*0.8 -> 67720 | AA19: =Y19-Z19-Z20 -> 6291.2 | AD19: 任永超 | AE19: 测绘 | AF19: =1.839*2500 -> 4597.5 | AG19: =Y19-AB19-AC19-AF19-AF20 -> 68813.7
AD20: 任永超 | AE20: 取芯 | AF20: =4*150 -> 600
D21: 东岔路，3km | F21: HNJH2022-003-06 | O21: 121724 | P21: 21481 | R21: =O21 -> 121724 | S21: =P21 -> 21481 | U21: =R21+S21 -> 143205 | V21: =U21 -> 143205 | W21: 131033 | X21: =V21-W21-W22 -> 12172 | Y21: =U21*0.8 -> 114564 | Z21: =W21*0.8 -> 104826.4 | AA21: =Y21-Z21-Z22 -> 9737.6 | AD21: 任永超 | AE21: 测绘 | AF21: =2.04*2500 -> 5100 | AG21: =Y21-AB21-AC21-AF21-AF22 -> 108714
AD22: 任永超 | AE22: 取芯 | AF22: =5*150 -> 750
A23: 4 | B23: 房山区西潞街道东沿村集体土地租赁住房项目市政工程（工程设计、地形测绘） | C23: 2022.4 | E23: 河南交规院 | F23: HNJH2022-004 | H23: 王伟 | I23: 13801288357 | J23: 王新星 | K23: 王新星 | L23: 261666.77 | M23: 0 | N23: 0 | O23: 0 | P23: 0 | Q23: 0 | R23: =O23 -> 0 | S23: =P23 -> 0 | T23: =Q23 -> 0 | U23: =SUM(R23:T24) -> 0 | V23: =U23 -> 0 | W23: 0 | X23: =V23-W23-W24 -> 0 | Y23: =V23*0.8 -> 0 | Z23: =W23*0.8 -> 0 | AA23: =Y23-Z23-Z24 -> 0 | AD23: 任永超 | AE23: 测绘、物探 | AF23: 8000 | AG23: =Y23-AB23-AC23-AF23-AF24 -> -8000
W24: 0 | Z24: =W24*0.8 -> 0
W25: 0 | Z25: =W25*0.8 -> 0
A26: 5 | B26: 2021年延庆区城东一次供热管网改造工程—妫川路（庆园街-庆隆街）热力管线回填道路恢复工程 | C26: 2022.6 | D26: 城市主干路管线掘路回填338米 | E26: 河南交规院 | F26: HNJH2022-005 | G26: 北京市交通委员会延庆分局 | H26: 刑工 | I26: 13810992745 | J26: 杨建东 | K26: 杨建东 | L26: 27452.02 | M26: 0 | N26: 0 | O26: 91506.74 | P26: 0 | Q26: 0 | R26: =O26 -> 91506.74 | S26: 0 | T26: 0 | U26: =SUM(R26:T28) -> 91506.74 | V26: =U26 -> 91506.74 | W26: 27452.02 | X26: =V26-W26-W27-W28 -> 64054.72 | Y26: =V26*0.8 -> 73205.392 | Z26: =W26*0.8 -> 21961.616 | AA26: =Y26-Z26-Z27-Z28 -> 51243.776 | AG26: =Y26-AB26-AC26-AF26-AF27-AF28 -> 73205.392
W27: 0 | Z27: =W27*0.8 -> 0
W28: 0 | Z28: =W28*0.8 -> 0
A29: 6 | B29: 第2标段：大兴区国道106交通综合治理工程勘察设计 | C29: 2022.8 | D29: 长度600米 | E29: 河南交规院 | F29: HNJH2022-006 | G29: 北京市交通委员会大兴分局 | H29: 陈友来 | J29: 王新星 | K29: 王新星 | L29: =261666.77*0.85 -> 222416.75 | M29: =261666.77*0.15 -> 39250.015 | N29: 0 | O29: =L29 -> 222416.75 | P29: =M29 -> 39250.015 | Q29: 0 | R29: 222416.75 | S29: 39250.02 | T29: 0 | U29: =SUM(R29:T31) -> 261666.77 | V29: =U29 -> 261666.77 | W29: 235500 | X29: =V29-W29-W30-W31 -> -1.0913936e-11 | Y29: =V29*0.8 -> 209333.42 | Z29: =W29*0.8 -> 188400 | AA29: =Y29-Z29-Z30-Z31 -> -3.6379788e-12 | AD29: 刘素良 | AE29: 测绘 | AF29: =0.85*2500 -> 2125 | AG29: =Y29-AB29-AC29-AF29-AF30-AF31 -> 207208.42
W30: 26166.77 | Z30: =W30*0.8 -> 20933.416
W31: 0 | Z31: =W31*0.8 -> 0
A32: 7 | B32: 第2标段琉陶路（K0+000-K11+319）修复养护工程勘察设计 | C32: 2022.8 | D32: 公路三级，长度11.139公里 | E32: 华西 | F32: HXJH2022-007 | G32: 北京市交通委员会房山分局 | H32: 刘然 | J32: 王新星 | K32: 王新星 | L32: =529899-M32 -> 419899 | M32: =11*10000 -> 110000 | N32: 0 | O32: =L32 -> 419899 | P32: =M32 -> 110000 | Q32: 0 | R32: =INT(O32*0.99) -> 415700 | S32: =INT(P32*0.99) -> 108900 | T32: 1 | U32: =SUM(R32:T34) -> 524601 | V32: =U32 -> 524601 | W32: 0 | X32: =V32-W32-W33-W34 -> 524601 | Y32: =V32*0.81 -> 424926.81 | Z32: =W32*0.8 -> 0 | AA32: =Y32-Z32-Z33-Z34 -> 424926.81 | AD32: 任永超 | AE32: 测绘 | AF32: =11.319*2500 -> 28297.5 | AG32: =Y32-AB32-AC32-AF32-AF33-AF34 -> 396629.31
W33: 0 | Z33: =W33*0.8 -> 0
W34: 0 | Z34: =W34*0.8 -> 0
A35: 8 | B35: 第4标段G108（K34+300-K68+000）修复养护工程勘察设计 | C35: 2022.8 | D35: 公路二级，长度34公里 | E35: 河南交规院 | F35: HNJH2022-008 | G35: 北京市交通委员会房山分局 | H35: 刘然 | J35: 王新星 | K35: 王新星 | L35: =838410-M35 -> 498410 | M35: =10000*34 -> 340000 | N35: 0 | O35: =L35 -> 498410 | P35: =M35 -> 340000 | Q35: =N35 -> 0 | R35: =INT(O35*0.99) -> 493425 | S35: =INT(P35*0.99) -> 336600 | T35: =INT(Q35*0.99) -> 0 | U35: =SUM(R35:T37) -> 830025 | V35: =U35 -> 830025 | W35: 0 | X35: =V35-W35-W36-W37 -> 830025 | Y35: =V35*0.8 -> 664020 | AA35: =Y35-Z35-Z36-Z37 -> 664020 | AD35: 刘素良 | AE35: 测绘 | AF35: =7.8*2500 -> 19500 | AG35: =Y35-AB35-AC35-AF35-AF36-AF37 -> 644520
W36: 0
W37: 0
A38: 9 | B38: 107 国道临时开口工程设计 | C38: 2022.9 | E38: 河南交规院 | F38: HNJH2022-009 | G38: 中铁五局 | J38: 曹立东 | K38: 曹立东 | L38: 50000 | O38: 50000 | R38: 50000 | U38: =SUM(R38:T40) -> 50000 | V38: =U38 -> 50000 | W38: 10000 | X38: =V38-W38-W39-W40 -> 0 | Y38: =V38*0.8 -> 40000 | Z38: =W38*0.8 -> 8000 | AA38: =Y38-Z38-Z39-Z40 -> 0 | AG38: =Y38-AB38-AC38-AF38-AF39-AF40 -> 40000
W39: 40000 | Z39: =W39*0.8 -> 32000
W40: 0
A41: 总计 | L41: =SUM(L5:L40) -> 1492934.8 | M41: =SUM(M5:M40) -> 489250.02 | N41: =SUM(N5:N40) -> 0 | O41: =SUM(O5:O40) -> 1897779.8 | P41: =SUM(P5:P40) -> 588297.02 | Q41: =SUM(Q5:Q40) -> 0 | R41: =SUM(R5:R40) -> 1888595.8 | S41: =SUM(S5:S40) -> 583797.02 | ... AB41: =SUM(AB5:AB40) -> 0 | AC41: =SUM(AC5:AC7) -> 0 | AF41: =SUM(AF5:AF40) -> 86152.5 | AG41: =SUM(AG5:AG7) -> 10472.208
A42: 2020年上报数值

Sheet 2023  
A1: 项目经营管理台账（2023年）（电子）
A2: 序号 | B2: 项目信息 | G2: 经营信息 | I2: 概算信息（估算） | L2: 审计信息 | O2: 合同、支付信息 | V2: 收入、分包支付信息 | AI2: 备注
B3: 项目名称 | C3: 承接 日期 | D3: 项目概况 | E3: 资质 | F3: 项目编号 | G3: 单位 | H3: 联系人 | I3: 设计费（元） | J3: 勘察费（元） | K3: 咨询费（元） | L3: 设计费（元） | M3: 勘察费（元） | N3: 咨询费（元） | O3: 合同/补充协议额（元） | S3: 甲方支付信息 | V3: 公司收入信息 | Y3: 公司支付信息 | AH3: 公司结余 （元）
O4: 设计费（元） | P4: 勘察费（元） | Q4: 咨询费（元） | R4: 合计额（元） | S4: 应支额（元） | T4: 支付金额（元） | U4: 未收金额（元） | V4: 应收额（元） | W4: 实收金额（元） | X4: 未收金额（元） | Y4: 应发经营奖金（元） | Z4: 扣减经营奖金（元） | AA4: 实发经营奖金（元） | AB4: 应发生产奖金（元） | AC4: 扣减生产奖金（元） | AD4: 实发生产奖金（元） | AE4: 单位 （个人） | AF4: 内容 | AG4: 金额（元）
A5: 1 | B5: 大兴公路分局 2023 年路网信息采集与发布设施建设、更新、治超专项工程及其他路网建设项目 | C5: 2023.1.19 | D5: 2023年大兴公路分局普通公路路网设施工程 | E5: 河南交规院 | F5: HNJH2023-001J01 | G5: 甲方单位 | H5: 北京市交通委员会大兴分局 | I5: 47455 | L5: 46980.45 | O5: =L5 -> 46980.45 | P5: =M5 -> 0 | Q5: =N5 -> 0 | R5: =SUM(O5:Q7) -> 46980.45 | S5: =R5 -> 46980.45 | T5: 46980.45 | U5: =S5-T5-T6-T7 -> 0 | V5: =O5*0.8 -> 37584.36 | W5: 37584.36 | X5: =V5-W5-W6-W7 -> 0 | Y5: =S5*0.17/1.065 -> 7499.2268 | AB5: =V5*0.2/1.065 -> 7058.0958 | AH5: =V5-Y5-AB5-AG5-AG6-AG7 -> 23027.037
G6: 联系人、联系方式 | H6: 谈志宏13641349036
G7: 经营人员 | H7: 王新星
D8: 2023年大兴公路分局普通公路治超专项工程 | F8: HNJH2023-001J02 | I8: 107843 | L8: 106764.57 | O8: =L8 -> 106764.57 | P8: =M8 -> 0 | Q8: =N8 -> 0 | R8: =SUM(O8:Q10) -> 106764.57 | S8: =R8 -> 106764.57 | T8: 106764.57 | U8: =S8-T8-T9-T10 -> 0 | V8: =O8*0.8 -> 85411.656 | W8: 85411.66 | X8: =V8-W8-W9-W10 -> -0.004 | Y8: =S8*0.17/1.065 -> 17042.232 | AB8: =V8*0.2/1.065 -> 16039.748 | AE8: 任永超 | AF8: 测量 | AG8: =0.5*2500 -> 1250 | AH8: =V8-Y8-AB8-AG8-AG9-AG10 -> 50479.677
AE9: 任永超 | AF9: 取芯 | AG9: =4*150 -> 600
A11: 2 | B11: 2023 年延庆区普通公路路面、桥梁、隧道修复性养护（中修）第1标段 | C11: 2023.4 | D11: 兴阳线中修，2.665km | E11: 河南交规院 | F11: HNJH2023-002 | G11: 甲方单位 | H11: 北京市交通委员会延庆分局 | I11: 50194 | J11: 8858 | L11: =I11 -> 50194 | M11: =J11 -> 8858 | O11: =L11 -> 50194 | P11: =M11 -> 8858 | Q11: =N11 -> 0 | R11: =SUM(O11:Q13) -> 59052 | S11: =R11 -> 59052 | T11: 54033 | U11: =S11-T11-T12-T13 -> 5019 | V11: =S11*0.8 -> 47241.6 | W11: =T11*0.8 -> 43226.4 | X11: =V11-W11-W12-W13 -> 4015.2 | Y11: =S11*0.17/1.065 -> 9426.1408 | AB11: =V11*0.2/1.065 -> 8871.662 | AH11: =V11-Y11-AB11-AG11-AG12-AG13 -> 28943.797
G12: 联系人、联系方式 | H12: 穆坤15810568502 | T12: 0
G13: 经营人员 | H13: 杨建东 | T13: 0
C14: 2023.9 | D14: 兴阳线水毁 | I14: 49791 | L14: 21097 | M14: 3723 | O14: 21097 | P14: 3723 | Q14: =N14 -> 0 | R14: =SUM(O14:Q16) -> 24820 | S14: =R14 -> 24820 | T14: 24820 | U14: =S14-T14-T15-T16 -> 0 | V14: =S14*0.8 -> 19856 | W14: =T14*0.8 -> 19856 | X14: =V14-W14-W15-W16 -> 0 | Y14: =S14*0.17/1.065 -> 3961.8779 | AB14: =V14*0.2/1.065 -> 3728.8263 | AH14: =V14-Y14-AB14-AG14-AG15-AG16 -> 12165.296
T15: 0
T16: 0
C17: 2023.9 | D17: 大西路水毁 | I17: 49831 | L17: 21774 | M17: 3843 | O17: 21774 | P17: 3843 | Q17: =N17 -> 0 | R17: =SUM(O17:Q19) -> 25617 | S17: =R17 -> 25617 | T17: 25617 | U17: =S17-T17-T18-T19 -> 0 | V17: =S17*0.8 -> 20493.6 | W17: =T17*0.8 -> 20493.6 | X17: =V17-W17-W18-W19 -> 0 | Y17: =S17*0.17/1.065 -> 4089.0986 | AB17: =V17*0.2/1.065 -> 3848.5634 | AH17: =V17-Y17-AB17-AG17-AG18-AG19 -> 12555.938
T18: 0
T19: 0
C20: 2023.9 | D20: 黑艾路水毁 | I20: 63593 | L20: 30914 | M20: 5455 | O20: 30914 | P20: 5455 | Q20: =N20 -> 0 | R20: =SUM(O20:Q22) -> 36369 | S20: =R20 -> 36369 | T20: 36369 | U20: =S20-T20-T21-T22 -> 0 | V20: =S20*0.8 -> 29095.2 | W20: =T20*0.8 -> 29095.2 | X20: =V20-W20-W21-W22 -> 0 | Y20: =S20*0.17/1.065 -> 5805.3803 | AB20: =V20*0.2/1.065 -> 5463.8873 | AH20: =V20-Y20-AB20-AG20-AG21-AG22 -> 17825.932
T21: 0
T22: 0
C23: 2023.9 | D23: 铁泰路水毁 | I23: 72659 | L23: 41134 | M23: 7259 | O23: 41134 | P23: 7259 | Q23: =N23 -> 0 | R23: =SUM(O23:Q25) -> 48393 | S23: =R23 -> 48393 | T23: 48393 | U23: =S23-T23-T24-T25 -> 0 | V23: =S23*0.8 -> 38714.4 | W23: =T23*0.8 -> 38714.4 | X23: =V23-W23-W24-W25 -> 0 | Y23: =S23*0.17/1.065 -> 7724.7042 | AB23: =V23*0.2/1.065 -> 7270.3099 | AH23: =V23-Y23-AB23-AG23-AG24-AG25 -> 23719.386
T24: 0
T25: 0
C26: 2023.9 | D26: 外石路水毁 | I26: 56590 | L26: 26790 | M26: 4728 | O26: 26790 | P26: 4728 | Q26: =N26 -> 0 | R26: =SUM(O26:Q28) -> 31518 | S26: =R26 -> 31518 | T26: 31518 | U26: =S26-T26-T27-T28 -> 0 | V26: =S26*0.8 -> 25214.4 | W26: =T26*0.8 -> 25214.4 | X26: =V26-W26-W27-W28 -> 0 | Y26: =S26*0.17/1.065 -> 5031.0423 | AB26: =V26*0.2/1.065 -> 4735.0986 | AH26: =V26-Y26-AB26-AG26-AG27-AG28 -> 15448.259
T27: 0
T28: 0
C29: 2023.9 | D29: 兴阳线北侧辅路人行步道工程 | I29: =L29+M29 -> 60172 | L29: 51146 | M29: 9026 | O29: 51146 | P29: 9026 | R29: =SUM(O29:Q31) -> 60172 | S29: =R29 -> 60172 | T29: 60172 | U29: =S29-T29-T30-T31 -> 0 | V29: =S29*0.8 -> 48137.6 | W29: =T29*0.8 -> 48137.6 | X29: =V29-W29-W30-W31 -> 0 | Y29: =S29*0.17/1.065 -> 9604.9202 | AB29: =V29*0.2/1.065 -> 9039.9249 | AE29: 刘素良 | AF29: 测量 | AG29: =1*2500 -> 2500 | AH29: =V29-Y29-AB29-AG29-AG30-AG31 -> 26992.755
C32: 2023.1 | D32: G6辅路2.67km。 | I32: 68935 | L32: =I32 -> 68935 | M32: 0 | O32: =L32 -> 68935 | P32: =M32 -> 0 | Q32: =N32 -> 0 | R32: =SUM(O32:Q34) -> 68935 | S32: =R32 -> 68935 | T32: 63049 | U32: =S32-T32-T33-T34 -> 5886 | V32: =S32*0.8 -> 55148 | W32: 50439.2 | X32: =V32-W32-W33-W34 -> 4708.8 | Y32: =S32*0.17/1.065 -> 11003.709 | AB32: =V32*0.2/1.065 -> 10356.432 | AH32: =V32-Y32-AB32-AG32-AG33-AG34 -> 33787.859
T33: 0
T34: 0
A35: 3 | B35: 通州区宋庄镇2024年乡村公路大修工程勘察设计服务项目 | C35: 2023.4 | D35: 双埠头南路 | E35: 特希达 | F35: TXDJH2023-003 | G35: 甲方单位 | H35: 宋庄公路镇政府 | I35: 287424 | J35: 31060 | O35: =L35 -> 0 | P35: =M35 -> 0 | Q35: =N35 -> 0 | R35: =SUM(O35:Q37) -> 0 | S35: =R35 -> 0 | T35: 0 | U35: =S35-T35-T36-T37 -> 0 | V35: =S35*0.85 -> 0 | X35: =V35-W35-W36-W37 -> 0 | Y35: =S35*0.17/1.065 -> 0 | AB35: =V35*0.2/1.065 -> 0 | AE35: 刘素良 | AF35: 测量 | AG35: =1.6*2000 -> 3200 | AH35: =V35-Y35-AB35-AG35-AG36-AG37 -> -3200
G36: 联系人、联系方式 | H36: 杨文通13641257276 | T36: 0
G37: 经营人员 | H37: 王新星 | T37: 0
D38: 辛疃西路，长度0.48km | I38: 80555.79 | J38: 7942.93 | L38: 80555.79 | M38: 7942.93 | O38: 80555 | P38: 7943 | Q38: =N38 -> 0 | R38: =SUM(O38:Q40) -> 88498 | S38: =R38 -> 88498 | T38: 0 | U38: =S38-T38-T39-T40 -> 88498 | V38: =S38*0.85 -> 75223.3 | X38: =V38-W38-W39-W40 -> 75223.3 | Y38: =S38*0.17/1.065 -> 14126.441 | AB38: =V38*0.2/1.065 -> 14126.441 | AE38: 刘素良 | AF38: 测绘 | AG38: =0.48*2000 -> 960 | AH38: =V38-Y38-AB38-AG38-AG39-AG40 -> 45410.417
T39: 0 | AE39: 刘素良 | AF39: 取芯 | AG39: =4*150 -> 600
T40: 0
D41: 镇工业区一路，长度1.3km | I41: 112281.74 | J41: 12896.81 | L41: 112281.74 | M41: 12896.81 | O41: 112281 | P41: 12897 | Q41: =N41 -> 0 | R41: =SUM(O41:Q43) -> 125178 | S41: =R41 -> 125178 | T41: 125178 | U41: =S41-T41-T42-T43 -> 0 | V41: =S41*0.85 -> 106401.3 | W41: 106401.3 | X41: =V41-W41-W42-W43 -> 0 | Y41: =S41*0.17/1.065 -> 19981.465 | AB41: =V41*0.2/1.065 -> 19981.465 | AE41: 刘素良 | AF41: 测绘 | AG41: =1.23*2000 -> 2460 | AH41: =V41-Y41-AB41-AG41-AG42-AG43 -> 63978.37
T42: 0
T43: 0
D44: 邢各庄路，长度1km | I44: 164211.53 | J44: 12290.48 | L44: 164211.53 | M44: 12290.48 | O44: 164211 | P44: 12291 | Q44: =N44 -> 0 | R44: =SUM(O44:Q46) -> 176502 | S44: =R44 -> 176502 | T44: 87022 | U44: =S44-T44-T45-T46 -> 89480 | V44: =S44*0.85 -> 150026.7 | W44: 73968.7 | X44: =V44-W44-W45-W46 -> 76058 | Y44: =S44*0.17/1.065 -> 28174.028 | AB44: =V44*0.2/1.065 -> 28174.028 | AE44: 刘素良 | AF44: 测绘 | AG44: =1.043*2000 -> 2086 | AH44: =V44-Y44-AB44-AG44-AG45-AG46 -> 91592.644
T45: 0
T46: 0
D47: 徐双路，长度1.1km | I47: 83405.74 | J47: 13170.42 | L47: 83405.74 | M47: 13170.42 | O47: 83405 | P47: 13171 | Q47: =N47 -> 0 | R47: =SUM(O47:Q49) -> 96576 | S47: =R47 -> 96576 | T47: 0 | U47: =S47-T47-T48-T49 -> 96576 | V47: =S47*0.85 -> 82089.6 | X47: =V47-W47-W48-W49 -> 82089.6 | Y47: =S47*0.17/1.065 -> 15415.887 | AB47: =V47*0.2/1.065 -> 15415.887 | AE47: 刘素良 | AF47: 测绘 | AG47: =1.1*2000 -> 2200 | AH47: =V47-Y47-AB47-AG47-AG48-AG49 -> 49057.825
T48: 0
T49: 0
D50: 窑管路，长度5.4km | I50: 72142.47 | J50: 48013.89 | L50: 72142.47 | M50: 48013.89 | O50: 72142 | P50: 48014 | Q50: =N50 -> 0 | R50: =SUM(O50:Q52) -> 120156 | S50: =R50 -> 120156 | T50: 0 | U50: =S50-T50-T51-T52 -> 120156 | V50: =S50*0.85 -> 102132.6 | X50: =V50-W50-W51-W52 -> 102132.6 | Y50: =S50*0.17/1.065 -> 19179.831 | AB50: =V50*0.2/1.065 -> 19179.831 | AE50: 任永超 | AF50: 测绘 | AG50: =0.65*1500 -> 975 | AH50: =V50-Y50-AB50-AG50-AG51-AG52 -> 62197.938
T51: 0 | AE51: 任永超 | AF51: 取芯 | AG51: =4*150 -> 600
T52: 0
A53: 4 | B53: 2023年大兴区普通公路和桥梁修复性养护（中修）工程、维护及应急抢险工程、交通工程、绿化工程勘察设计以及独柱墩桥抗倾覆验算第4标段---绿化 | C53: 2023.4 | D53: 团桂路，三级公路，1.802km | E53: 河南交规院 | F53: HNJH2023-004 | G53: 甲方单位 | H53: 北京市交通委员会大兴分局 | I53: 56136 | L53: =I53 -> 56136 | O53: =L53 -> 56136 | P53: =M53 -> 0 | Q53: =N53 -> 0 | R53: =SUM(O53:Q55) -> 56136 | S53: =R53 -> 56136 | T53: 0 | U53: =S53-T53-T54-T55 -> 56136 | V53: =S53*0.8 -> 44908.8 | X53: =V53-W53-W54-W55 -> 44908.8 | Y53: =S53*0.17/1.065 -> 8960.6761 | AB53: =V53*0.2/1.065 -> 8433.5775 | AE53: 刘素良 | AF53: 测量 | AG53: =2.33*2500 -> 5825 | AH53: =V53-Y53-AB53-AG53-AG54-AG55 -> 21689.546
G54: 联系人、联系方式 | H54: 韩连福13121256196 | T54: 0
G55: 经营人员 | H55: 王新星 | T55: 0
A56: 5 | B56: 房山区河北镇房东路（水泥一厂中路～镇界）道路工程 | C56: 2018转入 | D56: 城市主干路，2.3km | E56: 河南交规院 | F56: HNJH2023-005 | G56: 甲方单位 | H56: 河北镇政府 | O56: =L56 -> 0 | P56: =M56 -> 0 | Q56: =N56 -> 0 | R56: =SUM(O56:Q58) -> 0 | S56: =R56 -> 0 | T56: 0 | U56: =S56-T56-T57-T58 -> 0 | V56: =S56*0.8 -> 0 | X56: =V56-W56-W57-W58 -> 0 | Y56: 0 | AB56: 0 | AH56: =V56-Y56-AB56-AG56-AG57-AG58 -> 0 | AI56: 2018年河北镇项目转入
G57: 联系人、联系方式 | H57: 肖总13911835251 | T57: 0
G58: 经营人员 | H58: 杨建东、王新星 | T58: 0
A59: 6 | B59: 房山区农村污水治理工程（官道等13村截污排污）道路恢复工程 | C59: 2023.3 | D59: 共计5个村需要进行道路恢复，分别是北尚乐村、官道村、五侯村、晓幼营村、岳各庄村，涉及恢复道路分别为房易路、南土路、良常路、岳琉路、阎吕路，长度合计2.317公里。 | E59: 河南交规院 | F59: HNJH2023-006 | G59: 甲方单位 | H59: 邯郸设计院、房山水务局 | I59: 140000 | L59: =I59 -> 140000 | O59: =L59 -> 140000 | P59: =M59 -> 0 | Q59: =N59 -> 0 | R59: =SUM(O59:Q61) -> 140000 | S59: =R59 -> 140000 | T59: 112000 | U59: =S59-T59-T60-T61 -> 28000 | V59: =O59*0.8 -> 112000 | W59: =T59*0.8 -> 89600 | X59: =V59-W59-W60-W61 -> 22400 | Y59: =S59*0.17/1.065 -> 22347.418 | AB59: =V59*0.2/1.065 -> 21032.864 | AH59: =V59-Y59-AB59-AG59-AG60-AG61 -> 68619.718
G60: 联系人、联系方式 | H60: 陈辉13436883898，李超13811171178 | T60: 0
G61: 经营人员 | H61: 曹立东 | T61: 0
A62: 7 | B62: 2023年大兴区普通公路和桥梁修复性养护（中修）工程、维护及应急抢险工程、交通工程、绿化工程勘察设计以及独柱墩桥抗倾覆验算第5标段-交通 | C62: 2023.5 | D62: G230通武线（京开东辅路-小龙河）路中护栏提升专项 | E62: 河南交规院 | F62: HNJH2023-007-01 | G62: 甲方单位 | H62: 北京市交通委员会大兴分局 | I62: 85790.81 | L62: =I62 -> 85790.81 | O62: =L62 -> 85790.81 | P62: =M62 -> 0 | Q62: =N62 -> 0 | R62: =SUM(O62:Q64) -> 85790.81 | S62: =R62 -> 85790.81 | T62: 85790.81 | U62: =S62-T62-T63-T64 -> 0 | V62: =S62*0.8 -> 68632.648 | W62: 68632.65 | X62: =V62-W62-W63-W64 -> -0.002 | Y62: =S62*0.17/1.065 -> 13694.308 | AB62: =V62*0.2/1.065 -> 12888.76 | AH62: =V62-Y62-AB62-AG62-AG63-AG64 -> 42049.58
G63: 联系人、联系方式 | H63: 韩连福13121256196
G64: 经营人员 | H64: 王新星
C65: 2023.5 | D65: 2023年大兴区公路安全设施精细化提升工程 | E65: 河南交规院 | F65: HNJH2023-007-02 | I65: 55809 | L65: =I65 -> 55809 | O65: =L65 -> 55809 | P65: =M65 -> 0 | Q65: =N65 -> 0 | R65: =SUM(O65:Q67) -> 55809 | S65: =R65 -> 55809 | T65: 50229 | U65: =S65-T65-T66-T67 -> 5580 | V65: =S65*0.8 -> 44647.2 | W65: =T65*0.8 -> 40183.2 | X65: =V65-W65-W66-W67 -> 4464 | Y65: =S65*0.17/1.065 -> 8908.4789 | AB65: =V65*0.2/1.065 -> 8384.4507 | AH65: =V65-Y65-AB65-AG65-AG66-AG67 -> 27354.27
T66: 0
T67: 0
A68: 8 | B68: 延庆新城小营、石河营棚改项目配套雨水下游工程 延琉路（龙顺路~妫川路）雨水管线回填道路恢复工程 | C68: 2023.6 | D68: 机动车道雨水明挖管线恢复，长度482米，恢复道路面积12693平米 | E68: 河南交规院 | F68: HNJH2023-008 | G68: 甲方单位 | H68: 北京市延庆区市政设施管理中心 | I68: 99300 | L68: =I68 -> 99300 | O68: =L68 -> 99300 | P68: =M68 -> 0 | Q68: =N68 -> 0 | R68: =SUM(O68:Q70) -> 99300 | S68: =R68 -> 99300 | T68: 89370 | U68: =S68-T68-T69-T70 -> 9930 | V68: =S68*0.8 -> 79440 | X68: =V68-W68-W69-W70 -> 79440 | Y68: =S68*0.17/1.065 -> 15850.704 | AB68: =V68*0.2/1.065 -> 14918.31 | AH68: =V68-Y68-AB68-AG68-AG69-AG70 -> 48670.986
G69: 联系人、联系方式 | H69: 张大延 | T69: 0
G70: 经营人员 | H70: 杨建东 | T70: 0
A71: 9 | B71: 2024年延庆区普通公路养护工程勘察设计第1标段 | C71: 2023.7 | D71: 滨河南路（K1+000-K8+000））预防性养护工程 | E71: 河南交规院 | F71: HNJH2023-009 | G71: 甲方单位 | H71: 北京市交通委员会延庆分局 | I71: =318812*0.85 -> 270990.2 | J71: =318812*0.15 -> 47821.8 | O71: =L71 -> 0 | P71: =M71 -> 0 | Q71: =N71 -> 0 | R71: =SUM(O71:Q73) -> 0 | S71: =R71 -> 0 | T71: 0 | U71: =S71-T71-T72-T73 -> 0 | V71: =S71*0.8 -> 0 | X71: =V71-W71-W72-W73 -> 0 | Y71: =S71*0.17/1.065 -> 0 | AB71: =V71*0.2/1.065 -> 0 | AE71: 刘素良 | AF71: 测量 | AG71: =0.44*2500 -> 1100 | AH71: =V71-Y71-AB71-AG71-AG72-AG73 -> -3350
G72: 联系人、联系方式 | H72: 梁工15810476282 | T72: 0 | AE72: 刘素良 | AF72: 取芯 | AG72: =15*150 -> 2250
G73: 经营人员 | H73: 杨建东 | T73: 0
C74: 2023.7 | D74: 滦赤路（K123+000-K128+000、K137+050-K139+000）预防性养护工程 | I74: =152372*0.85 -> 129516.2 | J74: =152372*0.15 -> 22855.8 | O74: =L74 -> 0 | P74: =M74 -> 0 | Q74: =N74 -> 0 | R74: =SUM(O74:Q76) -> 0 | S74: =R74 -> 0 | T74: 0 | U74: =S74-T74-T75-T76 -> 0 | V74: =S74*0.8 -> 0 | X74: =V74-W74-W75-W76 -> 0 | Y74: =S74*0.17/1.065 -> 0 | AB74: =V74*0.2/1.065 -> 0 | AH74: =V74-Y74-AB74-AG74-AG75-AG76 -> 0 | AI74: 项目调整至HNJH2024-016
T75: 0
T76: 0
A77: 10 | B77: 2024年房山区普通公路养护工程勘察设计（第1、2、3、5标段）-2标段 | C77: 2023.8 | D77: 大件路（K0+000-K10+842）预防养护，勘察设计段落为K0+000-K10+842，全长约10.8公里，一级公路 | E77: 河南交规院 | F77: HNJH2023-010 | G77: 甲方单位 | H77: 北京市交通委员会延庆分局 | I77: =719500*0.85 -> 611575 | J77: =719500*0.15 -> 107925 | O77: =L77 -> 0 | P77: =M77 -> 0 | Q77: =N77 -> 0 | R77: =SUM(O77:Q79) -> 0 | S77: =R77 -> 0 | T77: 0 | U77: =S77-T77-T78-T79 -> 0 | V77: =S77*0.8 -> 0 | X77: =V77-W77-W78-W79 -> 0 | Y77: =S77*0.17/1.065 -> 0 | AB77: =V77*0.2/1.065 -> 0 | AE77: 解飞 | AF77: 测量 | AG77: =10.842*5000 -> 54210 | AH77: =V77-Y77-AB77-AG77-AG78-AG79 -> -58110
G78: 联系人、联系方式 | H78: 杨鹤13911253681 | T78: 0 | AE78: 刘素良 | AF78: 取芯 | AG78: =26*150 -> 3900
G79: 经营人员 | H79: 王新星 | T79: 0
C80: 2023.8 | D80: 兴良路（K8+000-K10+253）预防养护，勘察设计段落为K8+000-K10+253，全长约2.3公里，一级公路 | I80: =201700*0.85 -> 171445 | J80: =201700*0.15 -> 30255 | O80: =L80 -> 0 | P80: =M80 -> 0 | Q80: =N80 -> 0 | R80: =SUM(O80:Q82) -> 0 | S80: =R80 -> 0 | T80: 0 | U80: =S80-T80-T81-T82 -> 0 | V80: =S80*0.8 -> 0 | X80: =V80-W80-W81-W82 -> 0 | Y80: =S80*0.17/1.065 -> 0 | AB80: =V80*0.2/1.065 -> 0 | AE80: 解飞 | AF80: 测量 | AG80: =2.253*5000 -> 11265 | AH80: =V80-Y80-AB80-AG80-AG81-AG82 -> -12915
T81: 0 | AE81: 刘素良 | AF81: 取芯 | AG81: =11*150 -> 1650
T82: 0
A83: 11 | B83: 2024年大兴区京广线（K26+705-K34+880）预防性养护工程 | C83: 2023.8 | D83: 京广线（K26+705-K34+880）预防性养护工程，位于北京市大兴区，本次预防性养护段落北起庞魏路北侧（K26+705），南至黄垡桥（K34+880），技术等级为一级公路 | E83: 河南交规院 | F83: HNJH2023-011 | G83: 甲方单位 | H83: 北京市交通委员会大兴分局 | I83: =534809*0.85 -> 454587.65 | J83: =534809*0.15 -> 80221.35 | O83: =L83 -> 0 | P83: =M83 -> 0 | Q83: =N83 -> 0 | R83: =SUM(O83:Q85) -> 0 | S83: =R83 -> 0 | T83: 0 | U83: =S83-T83-T84-T85 -> 0 | V83: =S83*0.8 -> 0 | X83: =V83-W83-W84-W85 -> 0 | Y83: =S83*0.17/1.065 -> 0 | AB83: =V83*0.2/1.065 -> 0 | AE83: 刘素良 | AF83: 测量 | AG83: =8.175*2500*1.6 -> 32700 | AH83: =V83-Y83-AB83-AG83-AG84-AG85 -> -33900
G84: 联系人、联系方式 | H84: 薛建成15901120119 | T84: 0 | AE84: 刘素良 | AF84: 取芯 | AG84: =8*150 -> 1200
G85: 经营人员 | H85: 王新星 | T85: 0
A86: 12 | B86: 2023年延庆区京青线等15条道路灾后恢复重建工程（分五册出图） | C86: 2023.9 | D86: 2023年延庆区黑艾路灾后恢复重建工程 | E86: 河南交规院 | F86: HNJH2023-012 | G86: 甲方单位 | H86: 北京市交通委员会延庆分局 | I86: 20004 | L86: 18764 | O86: 18764 | P86: =M86 -> 0 | Q86: =N86 -> 0 | R86: =SUM(O86:Q88) -> 18764 | S86: =R86 -> 18764 | T86: 16887 | U86: =S86-T86-T87-T88 -> 0 | V86: =S86*0.8 -> 15011.2 | W86: =T86*0.8 -> 13509.6 | X86: =V86-W86-W87-W88 -> 4.5474735e-13 | Y86: =S86*0.17/1.065 -> 2995.1925 | AB86: =V86*0.2/1.065 -> 2819.0047 | AH86: =V86-Y86-AB86-AG86-AG87-AG88 -> 9197.0028
G87: 联系人、联系方式 | H87: 穆坤15810568502 | T87: 1877 | W87: 1501.6
G88: 经营人员 | H88: 杨建东 | T88: 0
D89: 2023年延庆区大西路等7条县道灾后恢复重建工程 | I89: 55254 | L89: 5379 | O89: 53979 | P89: =M89 -> 0 | Q89: =N89 -> 0 | R89: =SUM(O89:Q91) -> 53979 | S89: =R89 -> 53979 | T89: 48581 | U89: =S89-T89-T90-T91 -> 0 | V89: =S89*0.8 -> 43183.2 | W89: =T89*0.8 -> 38864.8 | X89: =V89-W89-W90-W91 -> 1.8189894e-12 | Y89: =S89*0.17/1.065 -> 8616.3662 | AB89: =V89*0.2/1.065 -> 8109.5211 | AH89: =V89-Y89-AB89-AG89-AG90-AG91 -> 26457.313
T90: 5398 | W90: 4318.4
T91: 0
D92: 2023年延庆区京青线等2条国道灾后恢复重建工程 | I92: 109889 | L92: 109806 | O92: 109806 | P92: =M92 -> 0 | Q92: =N92 -> 0 | R92: =SUM(O92:Q94) -> 109806 | S92: =R92 -> 109806 | T92: 98825 | U92: =S92-T92-T93-T94 -> 0 | V92: =S92*0.8 -> 87844.8 | W92: =T92*0.8 -> 79060 | X92: =V92-W92-W93-W94 -> 3.6379788e-12 | Y92: =S92*0.17/1.065 -> 17527.718 | AB92: =V92*0.2/1.065 -> 16496.676 | AH92: =V92-Y92-AB92-AG92-AG93-AG94 -> 53820.406
T93: 10981 | W93: 8784.8
T94: 0
D95: 2023年延庆区滦赤路等4条市道灾后恢复重建工程 | I95: 21671 | L95: 21281 | O95: 21281 | P95: =M95 -> 0 | Q95: =N95 -> 0 | R95: =SUM(O95:Q97) -> 21281 | S95: =R95 -> 21281 | T95: 19153 | U95: =S95-T95-T96-T97 -> 0 | V95: =S95*0.8 -> 17024.8 | W95: =T95*0.8 -> 15322.4 | X95: =V95-W95-W96-W97 -> -2.2737368e-12 | Y95: =S95*0.17/1.065 -> 3396.9671 | AB95: =V95*0.2/1.065 -> 3197.1455 | AH95: =V95-Y95-AB95-AG95-AG96-AG97 -> 10430.687
T96: 2128 | W96: 1702.4
T97: 0
D98: 2023年延庆区南山环线灾后恢复重建工程 | I98: 116822 | L98: 116821 | O98: 116821 | P98: =M98 -> 0 | Q98: =N98 -> 0 | R98: =SUM(O98:Q100) -> 116821 | S98: =R98 -> 116821 | T98: 105139 | U98: =S98-T98-T99-T100 -> 0 | V98: =S98*0.8 -> 93456.8 | W98: =T98*0.8 -> 84111.2 | X98: =V98-W98-W99-W100 -> -9.094947e-12 | Y98: =S98*0.17/1.065 -> 18647.484 | AB98: =V98*0.2/1.065 -> 17550.573 | AH98: =V98-Y98-AB98-AG98-AG99-AG100 -> 57258.744
T99: 11682 | W99: 9345.6
T100: 0
A101: 13 | B101: 新科广场（原聚龙市场）升级改造项目（设计）---地下通道工程 | C101: 2023.9 | D101: 西外广场升级改造项目（一期），市政地下通道和出入口及周边市政人行道进行升级改造，包括市政地下通道和出入口的内、外部装修设计及相关机电设计，现状桥梁盖板区域铺装更新改造及周边部分市政人行道铺装更新改造设计工作 | E101: 河南交规院 | F101: HNJH2023-013 | G101: 甲方单位 | H101: 北京市建筑设计研究院有限公司 | I101: 110000 | L101: =I101 -> 110000 | O101: =L101 -> 110000 | P101: =M101 -> 0 | Q101: =N101 -> 0 | R101: =SUM(O101:Q103) -> 110000 | S101: =R101 -> 110000 | T101: 0 | U101: =S101-T101-T102-T103 -> 110000 | V101: =S101*0.8 -> 88000 | X101: =V101-W101-W102-W103 -> 88000 | Y101: =S101*0.17/1.065 -> 17558.685 | AB101: =V101*0.2/1.065 -> 16525.822 | AE101: 杨勇 | AF101: 设计 | AG101: =S101*0.6 -> 66000 | AH101: =V101-Y101-AB101-AG101-AG102-AG103 -> -12084.507
G102: 联系人、联系方式 | H102: 李翔15210325382 | T102: 0
G103: 经营人员 | H103: 王新星 | T103: 0
...

Sheet 2024
A1: 项目经营管理台账（2024年）（电子）
A2: 序号 | B2: 项目信息 | G2: 经营信息 | I2: 概算信息（估算） | L2: 审计信息 | O2: 合同、支付信息 | V2: 收入、分包支付信息 | AI2: 备注
B3: 项目名称 | C3: 承接 日期 | D3: 项目概况 | E3: 资质 | F3: 项目编号 | G3: 单位 | H3: 联系人 | I3: 设计费（元） | J3: 勘察费（元） | K3: 咨询费（元） | L3: 设计费（元） | M3: 勘察费（元） | N3: 咨询费（元） | O3: 合同/补充协议额（元） | S3: 甲方支付信息 | V3: 公司收入信息 | Y3: 公司支付信息 | AH3: 公司结余 （元）
O4: 设计费（元） | P4: 勘察费（元） | Q4: 咨询费（元） | R4: 合计额（元） | S4: 应支额（元） | T4: 支付金额（元） | U4: 未收金额（元） | V4: 应收额（元） | W4: 实收金额（元） | X4: 未收金额（元） | Y4: 应发经营奖金（元） | Z4: 扣减经营奖金（元） | AA4: 实发经营奖金（元） | AB4: 应发生产奖金（元） | AC4: 扣减生产奖金（元） | AD4: 实发生产奖金（元） | AE4: 单位 （个人） | AF4: 内容 | AG4: 金额（元）
A5: 1 | B5: 大兴公路分局2024年路网信息采集与发布设施建设、更新、 治超专项工程及其他路网建设项目设计 | C5: 2024.1 | D5: 2024年大兴公路分局普通公路路网设施工程 | E5: 河南交规院 | F5: HNJH2024-001J | G5: 甲方单位 | H5: 北京市交通委员会大兴分局 | I5: 37515 | L5: =I5 -> 37515 | O5: =L5 -> 37515 | P5: =M5 -> 0 | Q5: =N5 -> 0 | R5: =SUM(O5:Q7) -> 37515 | S5: =R5 -> 37515 | T5: 37515 | U5: =S5-T5-T6-T7 -> 0 | V5: =S5*0.8 -> 30012 | X5: =V5-W5-W6-W7 -> 30012 | Y5: =S5*0.17/1.065 -> 5988.3099 | AB5: =V5*0.2/1.065 -> 5636.0563 | AH5: =V5-Y5-AB5-AG5-AG6-AG7 -> 18387.634
G6: 联系人、联系方式 | H6: 谈志宏13641349036 | T6: 0
G7: 经营人员 | H7: 王新星 | T7: 0
D8: 2024年大兴公路分局普通公路治超专项工程 | F8: HNJH2024-002J | I8: 201152 | L8: =I8 -> 201152 | O8: 232990 | P8: =M8 -> 0 | Q8: =N8 -> 0 | R8: =SUM(O8:Q10) -> 232990 | S8: =R8 -> 232990 | T8: 232990 | U8: =S8-T8-T9-T10 -> 0 | V8: =S8*0.8 -> 186392 | X8: =V8-W8-W9-W10 -> 186392 | Y8: =S8*0.17/1.065 -> 37190.892 | AB8: =V8*0.2/1.065 -> 35003.192 | AH8: =V8-Y8-AB8-AG8-AG9-AG10 -> 114197.92
T9: 0
T10: 0
D11: 大兴榆垡检查站车辆外廓尺寸自动检测设备安装工程 | F11: HNJH2024-002J | I11: 4950 | L11: =I11 -> 4950 | O11: =L11 -> 4950 | P11: =M11 -> 0 | Q11: =N11 -> 0 | R11: =SUM(O11:Q13) -> 4950 | S11: =R11 -> 4950 | T11: 0 | U11: =S11-T11-T12-T13 -> 4950 | V11: =S11*0.8 -> 3960 | X11: =V11-W11-W12-W13 -> 3960 | Y11: =S11*0.17/1.065 -> 790.14085 | AB11: =V11*0.2/1.065 -> 743.66197 | AH11: =V11-Y11-AB11-AG11-AG12-AG13 -> 2426.1972
T12: 0
T13: 0
D14: 2024年大兴区榆垡检查站初检区静态秤改造工程 | F14: HNJH2024-002J | I14: 26888 | L14: =I14 -> 26888 | O14: =L14 -> 26888 | P14: =M14 -> 0 | Q14: =N14 -> 0 | R14: =SUM(O14:Q16) -> 26888 | S14: =R14 -> 26888 | T14: 0 | U14: =S14-T14-T15-T16 -> 26888 | V14: =S14*0.8 -> 21510.4 | X14: =V14-W14-W15-W16 -> 21510.4 | Y14: =S14*0.17/1.065 -> 4291.9812 | AB14: =V14*0.2/1.065 -> 4039.5117 | AH14: =V14-Y14-AB14-AG14-AG15-AG16 -> 13178.907
T15: 0
T16: 0
A17: 2 | B17: 石景山区政务服务中心和档案馆新建工程-一次线部分（道路红线内）工前评估 | C17: 2024.1 | F17: HNJH2024-002 | G17: 甲方单位 | K17: 125000 | N17: 0 | O17: =L17 -> 0 | P17: =M17 -> 0 | Q17: =N17 -> 0 | R17: =SUM(O17:Q19) -> 0 | S17: =R17 -> 0 | T17: 0 | U17: =S17-T17-T18-T19 -> 0 | V17: =S17*0.8 -> 0 | X17: =V17-W17-W18-W19 -> 0 | Y17: =S17*0.17/1.065 -> 0 | AB17: =V17*0.2/1.065 -> 0 | AH17: =V17-Y17-AB17-AG17-AG18-AG19 -> 0
G18: 联系人、联系方式 | T18: 0
G19: 经营人员 | H19: 王新星 | T19: 0
A20: 3 | B20: 燕山地区道路恢复、路灯电缆修复、桥梁检测修复工程 | C20: 2024.4 | E20: 河南交规院 | F20: HNJH2024-003 | G20: 甲方单位 | I20: 1302875 | L20: =I20 -> 1302875 | O20: =L20 -> 1302875 | P20: =M20 -> 0 | Q20: =N20 -> 0 | R20: =SUM(O20:Q22) -> 1302875 | S20: =R20 -> 1302875 | T20: 260579 | U20: =S20-T20-T21-T22 -> 1042296 | V20: =S20*0.85 -> 1107443.8 | W20: 221492.15 | X20: =V20-W20-W21-W22 -> 885951.6 | Y20: =S20*0.17/1.065 -> 207970.66 | AB20: =V20*0.2/1.065 -> 207970.66 | AH20: =V20-Y20-AB20-AG20-AG21-AG22 -> 691502.44
G21: 联系人、联系方式 | H21: 穆佳楠，13910416067 | T21: 0
G22: 经营人员 | H22: 王新星 | T22: 0
A23: 4 | B23: 2024年延庆区普通公路路面、桥梁、隧道养护(中修)工程、维护及应急抢险工程、交通工程、绿化工程勘察设计第1标段 | C23: 2024.4 | D23: 延庆区东刘路（东桑园入口处）改造工程 | E23: 河南交规院 | F23: HNJH2024-004L01 | G23: 甲方单位 | O23: 32759 | P23: =M23 -> 0 | Q23: =N23 -> 0 | R23: =SUM(O23:Q25) -> 32759 | S23: =R23 -> 32759 | T23: 32759 | U23: =S23-T23-T24-T25 -> 0 | V23: =S23*0.8 -> 26207.2 | X23: =V23-W23-W24-W25 -> 26207.2 | Y23: =S23*0.17/1.065 -> 5229.1362 | AB23: =V23*0.2/1.065 -> 4921.5399 | AH23: =V23-Y23-AB23-AG23-AG24-AG25 -> 16056.524
G24: 联系人、联系方式 | T24: 0
G25: 经营人员 | H25: 杨建东 | T25: 0
D26: G234兴阳线（K181+000-K186+900、K217+000-K219+000）中修工程，7.3km | F26: HNJH2024-004L02 | O26: 196138 | P26: 34613 | Q26: =N26 -> 0 | R26: =SUM(O26:Q28) -> 230751 | S26: =R26 -> 230751 | T26: 211137 | U26: =S26-T26-T27-T28 -> 19614 | V26: =S26*0.8 -> 184600.8 | W26: 168909.6 | X26: =V26-W26-W27-W28 -> 15691.2 | Y26: =S26*0.17/1.065 -> 36833.493 | AB26: =V26*0.2/1.065 -> 34666.817 | AH26: =V26-Y26-AB26-AG26-AG27-AG28 -> 113100.49
T27: 0
T28: 0
D29: G234兴阳线（K170+600-K180+400、K207+100-K216+500、K229+200-K240+597）中修工程 19.544km | F29: HNJH2024-004L03 | O29: 385706 | P29: =M29 -> 0 | Q29: =N29 -> 0 | R29: =SUM(O29:Q31) -> 385706 | S29: =R29 -> 385706 | T29: 352921 | U29: =S29-T29-T30-T31 -> 32785 | V29: =S29*0.8 -> 308564.8 | W29: 282336.8 | X29: =V29-W29-W30-W31 -> 26228 | Y29: =S29*0.17/1.065 -> 61568.094 | AB29: =V29*0.2/1.065 -> 57946.441 | AH29: =V29-Y29-AB29-AG29-AG30-AG31 -> 189050.26
T30: 0
T31: 0
D32: 松闫路（K14+300-K16+937）路基沉陷专项治理工程 | F32: HNJH2024-004L04 | O32: 35300 | P32: =M32 -> 0 | Q32: =N32 -> 0 | R32: =SUM(O32:Q34) -> 35300 | S32: =R32 -> 35300 | T32: 35300 | U32: =S32-T32-T33-T34 -> 0 | V32: =S32*0.8 -> 28240 | X32: =V32-W32-W33-W34 -> 28240 | Y32: =S32*0.17/1.065 -> 5634.7418 | AB32: =V32*0.2/1.065 -> 5303.2864 | AH32: =V32-Y32-AB32-AG32-AG33-AG34 -> 17301.972
T33: 0
T34: 0
A35: 5 | B35: 兴亦路亦庄水厂西南侧DN600联络线掘路恢复工程 | C35: 2024.4 | E35: 河南交规院 | F35: HNJH2024-005 | G35: 甲方单位 | H35: 大兴公路局 | I35: 49000 | L35: =I35 -> 49000 | O35: =L35 -> 49000 | P35: =M35 -> 0 | Q35: =N35 -> 0 | R35: =SUM(O35:Q37) -> 49000 | S35: =R35 -> 49000 | T35: 44100 | U35: =S35-T35-T36-T37 -> 0 | V35: =S35*0.82 -> 40180 | W35: 36162 | X35: =V35-W35-W36-W37 -> 4018 | Y35: =S35*0.17/1.065 -> 7821.5962 | AB35: =V35*0.2/1.065 -> 7545.5399 | AE35: 刘素良 | AF35: 测量 | AG35: =1*2500 -> 2500 | AH35: =V35-Y35-AB35-AG35-AG36-AG37 -> 22312.864
G36: 联系人、联系方式 | T36: 4900
G37: 经营人员 | H37: 王新星 | T37: 0
A38: 6 | B38: 2024 年大兴区普通公路路面和桥梁养护（中修）工程、维护及应急抢险工程、交通工程、绿化工程勘察设计第5 标段 | C38: 2024.4 | D38: 2024年大兴区公路交通安全设施精细化提升工程（5条路护栏提升） | E38: 河南交规院 | F38: HNJH2024-006 | G38: 甲方单位 | O38: 57632 | P38: =M38 -> 0 | Q38: =N38 -> 0 | R38: =SUM(O38:Q40) -> 57632 | S38: =R38 -> 57632 | T38: 51868.8 | U38: =S38-T38-T39-T40 -> 5763.2 | V38: =S38*0.8 -> 46105.6 | W38: 41495.04 | X38: =V38-W38-W39-W40 -> 4610.56 | Y38: =S38*0.17/1.065 -> 9199.4742 | AB38: =V38*0.2/1.065 -> 8658.3286 | AE38: 刘素良 | AF38: 测量 | AG38: =1.6*2000 -> 3200 | AH38: =V38-Y38-AB38-AG38-AG39-AG40 -> 25047.797
G39: 联系人、联系方式 | T39: 0
G40: 经营人员 | H40: 王新星 | T40: 0
D41: 2024年大兴区兴亦路绿化工程 | O41: 68048 | P41: =M41 -> 0 | Q41: =N41 -> 0 | R41: =SUM(O41:Q43) -> 68048 | S41: =R41 -> 68048 | T41: 68048 | U41: =S41-T41-T42-T43 -> 0 | V41: =S41*0.8 -> 54438.4 | X41: =V41-W41-W42-W43 -> 54438.4 | Y41: =S41*0.17/1.065 -> 10862.122 | AB41: =V41*0.2/1.065 -> 10223.174 | AE41: 刘素良 | AF41: 测量 | AG41: =1.6*2000 -> 3200 | AH41: =V41-Y41-AB41-AG41-AG42-AG43 -> 30153.104
D44: 2024年道路交通安全隐患治理工程（7个终点路口） | O44: =L44 -> 0 | P44: =M44 -> 0 | Q44: =N44 -> 0 | R44: =SUM(O44:Q46) -> 0 | S44: =R44 -> 0 | T44: 0 | U44: =S44-T44-T45-T46 -> 0 | V44: =S44*0.8 -> 0 | X44: =V44-W44-W45-W46 -> 0 | Y44: =S44*0.17/1.065 -> 0 | AB44: =V44*0.2/1.065 -> 0 | AE44: 刘素良 | AF44: 测量 | AG44: =1.6*2000 -> 3200 | AH44: =V44-Y44-AB44-AG44-AG45-AG46 -> -3200
T45: 0
T46: 0
A47: 7 | B47: 2024年房山区普通公路路面和桥梁养护（中修）工程、维护及应急抢险工程勘察设计 | C47: 2024.5 | D47: 房山区G108京昆线东庄子桥小修工程 | E47: 河南交规院 | F47: HNJH2024-007Q01 | G47: 甲方单位 | H47: 房山公路局 | O47: =L47 -> 0 | P47: =M47 -> 0 | Q47: =N47 -> 0 | R47: =SUM(O47:Q49) -> 0 | S47: =R47 -> 0 | T47: 0 | U47: =S47-T47-T48-T49 -> 0 | V47: =S47*0.8 -> 0 | X47: =V47-W47-W48-W49 -> 0 | Y47: =S47*0.17/1.065 -> 0 | AB47: =V47*0.2/1.065 -> 0 | AH47: =V47-Y47-AB47-AG47-AG48-AG49 -> 0
G48: 联系人、联系方式 | T48: 0
G49: 经营人员 | H49: 王新星 | T49: 0
D50: 房山区西庄村1号桥中修工程 | F50: HNJH2024-007Q02 | I50: 112384 | L50: 95526.4 | M50: 16857.6 | O50: =L50 -> 95526.4 | P50: =M50 -> 16857.6 | Q50: =N50 -> 0 | R50: =SUM(O50:Q52) -> 112384 | S50: =R50 -> 112384 | T50: 101145 | U50: =S50-T50-T51-T52 -> 11239 | V50: =S50*0.8 -> 89907.2 | W50: 80916 | X50: =V50-W50-W51-W52 -> 8991.2 | Y50: =S50*0.17/1.065 -> 17939.23 | AB50: =V50*0.2/1.065 -> 16883.981 | AE50: 刘素良 | AF50: 测量 | AG50: 2000 | AH50: =V50-Y50-AB50-AG50-AG51-AG52 -> 53083.989
T51: 0
T52: 0
D53: 房山区窦公路公议庄村排水改造工程 | F53: HNJH2024-007L03 | O53: 82750.25 | P53: =M53 -> 0 | Q53: =N53 -> 0 | R53: =SUM(O53:Q55) -> 82750.25 | S53: =R53 -> 82750.25 | T53: 82750.25 | U53: =S53-T53-T54-T55 -> 0 | V53: =S53*0.8 -> 66200.2 | X53: =V53-W53-W54-W55 -> 66200.2 | Y53: =S53*0.17/1.065 -> 13208.96 | AB53: =V53*0.2/1.065 -> 12431.962 | AH53: =V53-Y53-AB53-AG53-AG54-AG55 -> 40559.277
D56: 房山区窦公路路面修复工程 | F56: HNJH2024-007L04 | O56: 88654.67 | P56: =M56 -> 0 | Q56: =N56 -> 0 | R56: =SUM(O56:Q58) -> 88654.67 | S56: =R56 -> 88654.67 | T56: 88654.67 | U56: =S56-T56-T57-T58 -> 0 | V56: =S56*0.8 -> 70923.736 | X56: =V56-W56-W57-W58 -> 70923.736 | Y56: =S56*0.17/1.065 -> 14151.45 | AB56: =V56*0.2/1.065 -> 13319.011 | AH56: =V56-Y56-AB56-AG56-AG57-AG58 -> 43453.275
A59: 8 | B59: 2024年通州区宋庄镇乡村公路中修工程 | C59: 2024.5 | D59: 宋通路路基工程 | E59: 特希达 | F59: TXDJH2024-008 | G59: 甲方单位 | H59: 宋庄公路镇政府 | I59: 7108 | L59: =I59 -> 7108 | O59: =L59 -> 7108 | P59: =M59 -> 0 | Q59: =N59 -> 0 | R59: =SUM(O59:Q61) -> 7108 | S59: =R59 -> 7108 | T59: 7108 | U59: =S59-T59-T60-T61 -> 0 | V59: =S59*0.85 -> 6041.8 | W59: =T59*0.85 -> 6041.8 | X59: =V59-W59-W60-W61 -> 0 | Y59: =S59*0.17/1.065 -> 1134.6103 | AB59: =V59*0.2/1.065 -> 1134.6103 | AH59: =V59-Y59-AB59-AG59-AG60-AG61 -> 3772.5793
G60: 联系人、联系方式 | H60: 杨文通13641257276 | T60: 0
G61: 经营人员 | H61: 王新星 | T61: 0
D62: 宋通路中修工程 | I62: 17553 | L62: =I62 -> 17553 | O62: =L62 -> 17553 | P62: =M62 -> 0 | Q62: =N62 -> 0 | R62: =SUM(O62:Q64) -> 17553 | S62: =R62 -> 17553 | T62: 17553 | U62: =S62-T62-T63-T64 -> 0 | V62: =S62*0.85 -> 14920.05 | W62: =T62*0.85 -> 14920.05 | X62: =V62-W62-W63-W64 -> 0 | Y62: =S62*0.17/1.065 -> 2801.8873 | AB62: =V62*0.2/1.065 -> 2801.8873 | AH62: =V62-Y62-AB62-AG62-AG63-AG64 -> 9316.2754
T63: 0
T64: 0
D65: 小堡工业区环路中修工程 | I65: 16320 | L65: =I65 -> 16320 | O65: =L65 -> 16320 | P65: =M65 -> 0 | Q65: =N65 -> 0 | R65: =SUM(O65:Q67) -> 16320 | S65: =R65 -> 16320 | T65: 11234 | U65: =S65-T65-T66-T67 -> 5086 | V65: =S65*0.85 -> 13872 | W65: =T65*0.85 -> 9548.9 | X65: =V65-W65-W66-W67 -> 4323.1 | Y65: =S65*0.17/1.065 -> 2605.0704 | AB65: =V65*0.2/1.065 -> 2605.0704 | AH65: =V65-Y65-AB65-AG65-AG66-AG67 -> 8661.8592
T66: 0
T67: 0
D68: 辛疃西路中修工程 | I68: 18022 | L68: =I68 -> 18022 | O68: =L68 -> 18022 | P68: =M68 -> 0 | Q68: =N68 -> 0 | R68: =SUM(O68:Q70) -> 18022 | S68: =R68 -> 18022 | T68: 0 | U68: =S68-T68-T69-T70 -> 18022 | V68: =S68*0.85 -> 15318.7 | X68: =V68-W68-W69-W70 -> 15318.7 | Y68: =S68*0.17/1.065 -> 2876.7512 | AB68: =V68*0.2/1.065 -> 2876.7512 | AH68: =V68-Y68-AB68-AG68-AG69-AG70 -> 9565.1977
T69: 0
T70: 0
D71: 徐双路路基工程 | I71: 4569 | L71: =I71 -> 4569 | O71: =L71 -> 4569 | P71: =M71 -> 0 | Q71: =N71 -> 0 | R71: =SUM(O71:Q73) -> 4569 | S71: =R71 -> 4569 | T71: 0 | U71: =S71-T71-T72-T73 -> 4569 | V71: =S71*0.85 -> 3883.65 | X71: =V71-W71-W72-W73 -> 3883.65 | Y71: =S71*0.17/1.065 -> 729.32394 | AB71: =V71*0.2/1.065 -> 729.32394 | AH71: =V71-Y71-AB71-AG71-AG72-AG73 -> 2425.0021
T72: 0
T73: 0
D74: 中坝河路中修工程 | I74: 4678 | L74: =I74 -> 4678 | O74: =L74 -> 4678 | P74: =M74 -> 0 | Q74: =N74 -> 0 | R74: =SUM(O74:Q76) -> 4678 | S74: =R74 -> 4678 | T74: 0 | U74: =S74-T74-T75-T76 -> 4678 | V74: =S74*0.85 -> 3976.3 | X74: =V74-W74-W75-W76 -> 3976.3 | Y74: =S74*0.17/1.065 -> 746.723 | AB74: =V74*0.2/1.065 -> 746.723 | AH74: =V74-Y74-AB74-AG74-AG75-AG76 -> 2482.854
T75: 0
T76: 0
A77: 9 | B77: 延庆区G6辅路（K58+900-K62+600）、八峪路（上行K3+900-K6+000、下行K3+900-K4+800、下行K7+700-K9+400、下行K13+400-K14+300）养护工程 | C77: 2024.5 | D77: G6辅路（K58+900-K62+600）养护工程 | E77: 河南交规院 | F77: HNJH2024-009 | G77: 甲方单位 | H77: 延庆交通委 | O77: =L77 -> 0 | P77: =M77 -> 0 | Q77: =N77 -> 0 | R77: =SUM(O77:Q79) -> 0 | S77: =R77 -> 0 | T77: 0 | U77: =S77-T77-T78-T79 -> 0 | V77: =S77*0.8 -> 0 | X77: =V77-W77-W78-W79 -> 0 | Y77: =S77*0.17/1.065 -> 0 | AB77: =V77*0.2/1.065 -> 0 | AH77: =V77-Y77-AB77-AG77-AG78-AG79 -> 0
G78: 联系人、联系方式 | T78: 0
G79: 经营人员 | H79: 杨建东 | T79: 0
D80: 八峪路（上行K3+900-K6+000、下行K3+900-K4+800、下行K7+700-K9+400、下行K13+400-K14+300）养护工程 | O80: =L80 -> 0 | P80: =M80 -> 0 | Q80: =N80 -> 0 | R80: =SUM(O80:Q82) -> 0 | S80: =R80 -> 0 | T80: 0 | U80: =S80-T80-T81-T82 -> 0 | V80: =S80*0.8 -> 0 | X80: =V80-W80-W81-W82 -> 0 | Y80: =S80*0.17/1.065 -> 0 | AB80: =V80*0.2/1.065 -> 0 | AH80: =V80-Y80-AB80-AG80-AG81-AG82 -> 0
T81: 0
T82: 0
A83: 10 | B83: 环卫集团南宫厨余沼气并网配套天然气工程（工前评估） | C83: 2024.6 | D83: 环卫集团南宫厨余沼气并网配套天然气工程穿越G104公路进行工前评估报告编制工作 | E83: 中工 | F83: HNJH2024-010 | G83: 甲方单位 | H83: 大兴燃气集团 | K83: 80000 | N83: =K83 -> 80000 | O83: =L83 -> 0 | P83: =M83 -> 0 | Q83: =N83 -> 80000 | R83: =SUM(O83:Q85) -> 80000 | S83: =R83 -> 80000 | T83: 0 | U83: =S83-T83-T84-T85 -> 80000 | V83: =S83*0.8 -> 64000 | X83: =V83-W83-W84-W85 -> 64000 | Y83: =S83*0.17/1.065 -> 12769.953 | AB83: =V83*0.2/1.065 -> 12018.779 | AH83: =V83-Y83-AB83-AG83-AG84-AG85 -> 39211.268
G84: 联系人、联系方式 | H84: 吕文克 | T84: 0
G85: 经营人员 | H85: 王新星 | T85: 0
A86: 11 | B86: 2024年庞各庄镇乡村公路大修（设计） | C86: 2024.6 | D86: 张北路，四级路，1.71km | E86: 中工 | F86: HNJH2024-011 | I86: 57763 | J86: 10193 | L86: =I86 -> 57763 | M86: =J86 -> 10193 | O86: =L86 -> 57763 | P86: =M86 -> 10193 | Q86: =N86 -> 0 | R86: =SUM(O86:Q88) -> 67956 | S86: =R86 -> 67956 | T86: 0 | U86: =S86-T86-T87-T88 -> 67956 | V86: =S86*0.8 -> 54364.8 | X86: =V86-W86-W87-W88 -> 54364.8 | Y86: =S86*0.17/1.065 -> 10847.437 | AB86: =V86*0.2/1.065 -> 10209.352 | AE86: 刘素良 | AF86: 测量 | AG86: =1.71*2000 -> 3420 | AH86: =V86-Y86-AB86-AG86-AG87-AG88 -> 29288.011
T87: 0 | AE87: 刘素良 | AF87: 取芯 | AG87: =4*150 -> 600
T88: 0
D89: 双南路，四级路，0.49km | I89: 44592 | J89: 7869 | L89: =I89 -> 44592 | M89: =J89 -> 7869 | O89: =L89 -> 44592 | P89: =M89 -> 7869 | Q89: =N89 -> 0 | R89: =SUM(O89:Q91) -> 52461 | S89: =R89 -> 52461 | T89: 0 | U89: =S89-T89-T90-T91 -> 52461 | V89: =S89*0.8 -> 41968.8 | X89: =V89-W89-W90-W91 -> 41968.8 | Y89: 0 | AB89: 0 | AE89: 刘素良 | AF89: 测量 | AG89: =0.49*2000 -> 980 | AH89: =V89-Y89-AB89-AG89-AG90-AG91 -> 40688.8
T90: 0 | AE90: 刘素良 | AF90: 取芯 | AG90: =2*150 -> 300
T91: 0
D92: 王加路，四级路，1.693km | I92: 71043 | J92: 12537 | L92: =I92 -> 71043 | M92: =J92 -> 12537 | O92: =L92 -> 71043 | P92: =M92 -> 12537 | Q92: =N92 -> 0 | R92: =SUM(O92:Q94) -> 83580 | S92: =R92 -> 83580 | T92: 0 | U92: =S92-T92-T93-T94 -> 83580 | V92: =S92*0.8 -> 66864 | X92: =V92-W92-W93-W94 -> 66864 | Y92: =S92*0.17/1.065 -> 13341.408 | AB92: =V92*0.2/1.065 -> 12556.62 | AE92: 刘素良 | AF92: 测量 | AG92: =1.693*2000 -> 3386 | AH92: =V92-Y92-AB92-AG92-AG93-AG94 -> 36529.972
T93: 0 | AE93: 刘素良 | AF93: 取芯 | AG93: =7*150 -> 1050
T94: 0
D95: 庞北路，四级路，0.715kn | I95: 42520 | J95: 7504 | L95: =I95 -> 42520 | M95: =J95 -> 7504 | O95: =L95 -> 42520 | P95: =M95 -> 7504 | Q95: =N95 -> 0 | R95: =SUM(O95:Q97) -> 50024 | S95: =R95 -> 50024 | T95: 0 | U95: =S95-T95-T96-T97 -> 50024 | V95: =S95*0.8 -> 40019.2 | X95: =V95-W95-W96-W97 -> 40019.2 | Y95: =S95*0.17/1.065 -> 7985.0516 | AB95: =V95*0.2/1.065 -> 7515.3427 | AE95: 刘素良 | AF95: 测量 | AG95: =0.715*2000 -> 1430 | AH95: =V95-Y95-AB95-AG95-AG96-AG97 -> 22638.806
T96: 0 | AE96: 刘素良 | AF96: 取芯 | AG96: =3*150 -> 450
T97: 0
D98: 鲍北路，四级路，1.521km | I98: 63004 | J98: 11118 | L98: =I98 -> 63004 | M98: =J98 -> 11118 | O98: =L98 -> 63004 | P98: =M98 -> 11118 | Q98: =N98 -> 0 | R98: =SUM(O98:Q100) -> 74122 | S98: =R98 -> 74122 | T98: 0 | U98: =S98-T98-T99-T100 -> 74122 | V98: =S98*0.8 -> 59297.6 | X98: =V98-W98-W99-W100 -> 59297.6 | Y98: =S98*0.17/1.065 -> 11831.681 | AB98: =V98*0.2/1.065 -> 11135.7 | AE98: 刘素良 | AF98: 测量 | AG98: =1.521*2000 -> 3042 | AH98: =V98-Y98-AB98-AG98-AG99-AG100 -> 32688.22
T99: 0 | AE99: 刘素良 | AF99: 取芯 | AG99: =4*150 -> 600
T100: 0
D101: 西韩路，四级路，1.31km | I101: 58399 | J101: 10303 | L101: =I101 -> 58399 | M101: =J101 -> 10303 | O101: =L101 -> 58399 | P101: =M101 -> 10303 | Q101: =N101 -> 0 | R101: =SUM(O101:Q103) -> 68702 | S101: =R101 -> 68702 | T101: 0 | U101: =S101-T101-T102-T103 -> 68702 | V101: =S101*0.8 -> 54961.6 | X101: =V101-W101-W102-W103 -> 54961.6 | Y101: =S101*0.17/1.065 -> 10966.516 | AB101: =V101*0.2/1.065 -> 10321.427 | AE101: 刘素良 | AF101: 测量 | AG101: =1.31*2000 -> 2620 | AH101: =V101-Y101-AB101-AG101-AG102-AG103 -> 30453.656
T102: 0 | AE102: 刘素良 | AF102: 取芯 | AG102: =4*150 -> 600
T103: 0
D104: 荣北路，四级路，6.95km | I104: 246800 | J104: 43553 | L104: =I104 -> 246800 | M104: =J104 -> 43553 | O104: =L104 -> 246800 | P104: =M104 -> 43553 | Q104: =N104 -> 0 | R104: =SUM(O104:Q106) -> 290353 | S104: =R104 -> 290353 | T104: 0 | U104: =S104-T104-T105-T106 -> 290353 | V104: =S104*0.8 -> 232282.4 | X104: =V104-W104-W105-W106 -> 232282.4 | Y104: =S104*0.17/1.065 -> 46347.427 | AB104: =V104*0.2/1.065 -> 43621.108 | AE104: 刘素良 | AF104: 测量 | AG104: =6.95*2000 -> 13900 | AH104: =V104-Y104-AB104-AG104-AG105-AG106 -> 127213.86
T105: 0 | AE105: 刘素良 | AF105: 取芯 | AG105: =8*150 -> 1200
T106: 0
...

Sheet 2025
A1: 项目经营管理台账（2025年）（电子）
A2: 序号 | B2: 项目信息 | G2: 经营信息 | I2: 概算信息（估算） | L2: 审计信息 | O2: 合同、支付信息 | V2: 收入、分包支付信息 | AI2: 备注
B3: 项目名称 | C3: 承接 日期 | D3: 项目概况 | E3: 资质 | F3: 项目编号 | G3: 单位 | H3: 联系人 | I3: 设计费（元） | J3: 勘察费（元） | K3: 咨询费（元） | L3: 设计费（元） | M3: 勘察费（元） | N3: 咨询费（元） | O3: 合同/补充协议额（元） | S3: 甲方支付信息 | V3: 公司收入信息 | Y3: 公司支付信息 | AH3: 公司结余 （元）
O4: 设计费（元） | P4: 勘察费（元） | Q4: 咨询费（元） | R4: 合计额（元） | S4: 应支额（元） | T4: 支付金额（元） | U4: 未收金额（元） | V4: 应收额（元） | W4: 实收金额（元） | X4: 未收金额（元） | Y4: 应发经营奖金（元） | Z4: 扣减经营奖金（元） | AA4: 实发经营奖金（元） | AB4: 应发生产奖金（元） | AC4: 扣减生产奖金（元） | AD4: 实发生产奖金（元） | AE4: 单位 （个人） | AF4: 内容 | AG4: 金额（元）
A5: 1 | B5: 朝阳区三间房D区棚户区改造土地开发项目0007、0020地块市政 | D5: 黄渠东路、三间房南一街、三间房南二街 | F5: ZYYJH2025-002 | I5: 876300 | O5: =L5 -> 0 | P5: =M5 -> 0 | Q5: =N5 -> 0 | R5: =SUM(O5:Q7) -> 0 | S5: =R5 -> 0 | T5: 0 | U5: =S5-T5-T6-T7 -> 0 | V5: =S5*0.8 -> 0 | X5: =V5-W5-W6-W7 -> 0 | Y5: =S5*0.17/1.065 -> 0 | AB5: =V5*0.2/1.065 -> 0 | AH5: =V5-Y5-AB5-AG5-AG6-AG7 -> 0
T6: 0
T7: 0
A8: 2 | B8: 2025年通州区宋庄镇乡村公路中修工程 | D8: 平疃路北段K1+570 涵洞养护工程，D=1500mm 过路管涵，长6米 | F8: TXDJH2025-002 | O8: =L8 -> 0 | P8: =M8 -> 0 | Q8: =N8 -> 0 | R8: =SUM(O8:Q10) -> 0 | S8: =R8 -> 0 | T8: 0 | U8: =S8-T8-T9-T10 -> 0 | V8: =S8*0.8 -> 0 | X8: =V8-W8-W9-W10 -> 0 | Y8: =S8*0.17/1.065 -> 0 | AB8: =V8*0.2/1.065 -> 0 | AH8: =V8-Y8-AB8-AG8-AG9-AG10 -> 0
T9: 0
T10: 0
A11: 3 | B11: 大兴区庞各庄镇薛营东路综合治理工程 | C11: 2025.02 | D11: 四级路，0.6km | F11: HNJH2025-003 | O11: =L11 -> 0 | P11: =M11 -> 0 | Q11: =N11 -> 0 | R11: =SUM(O11:Q13) -> 0 | S11: =R11 -> 0 | T11: 0 | U11: =S11-T11-T12-T13 -> 0 | V11: =S11*0.8 -> 0 | X11: =V11-W11-W12-W13 -> 0 | Y11: =S11*0.17/1.065 -> 0 | AB11: =V11*0.2/1.065 -> 0 | AH11: =V11-Y11-AB11-AG11-AG12-AG13 -> 0
T12: 0
T13: 0
A14: 4 | B14: 106国道（兴良路-天河西路、天宫院桥匝道-G230）提级改造工程 | C14: 2025.01 | D14: 一级路，2.47km | F14: HNJH2025-004 | O14: =L14 -> 0 | P14: =M14 -> 0 | Q14: =N14 -> 0 | R14: =SUM(O14:Q16) -> 0 | S14: =R14 -> 0 | T14: 0 | U14: =S14-T14-T15-T16 -> 0 | V14: =S14*0.8 -> 0 | X14: =V14-W14-W15-W16 -> 0 | Y14: =S14*0.17/1.065 -> 0 | AB14: =V14*0.2/1.065 -> 0 | AH14: =V14-Y14-AB14-AG14-AG15-AG16 -> 0
T15: 0
T16: 0
A17: 5 | B17: 大兴公路分局2025年路网信息采集与发布设施建设、更新、治超专项工程及其他路网建设项目 | C17: 2025.3 | F17: HNJH2025-005 | O17: =L17 -> 0 | P17: =M17 -> 0 | Q17: =N17 -> 0 | R17: =SUM(O17:Q19) -> 0 | S17: =R17 -> 0 | T17: 0 | U17: =S17-T17-T18-T19 -> 0 | V17: =S17*0.8 -> 0 | X17: =V17-W17-W18-W19 -> 0 | Y17: =S17*0.17/1.065 -> 0 | AB17: =V17*0.2/1.065 -> 0 | AH17: =V17-Y17-AB17-AG17-AG18-AG19 -> 0
T18: 0
T19: 0
A20: 6 | B20: 人民渠（首钢东南区）蓄涝区建设工程--工前评估 | C20: 2025.4 | D20: 4个 | F20: HNJH2025-006 | N20: 468000 | O20: =L20 -> 0 | P20: =M20 -> 0 | Q20: =N20 -> 468000 | R20: =SUM(O20:Q22) -> 468000 | S20: =R20 -> 468000 | T20: 140400 | U20: =S20-T20-T21-T22 -> 327600 | V20: =S20*0.82 -> 383760 | X20: =V20-W20-W21-W22 -> 383760 | Y20: =S20*0.17/1.065 -> 74704.225 | AB20: =V20*0.2/1.065 -> 72067.606 | AH20: =V20-Y20-AB20-AG20-AG21-AG22 -> 236988.17
T21: 0
T22: 0
A23: 7 | B23: 通州区宋庄镇徐双路道路工程 | F23: TXDJH2025-007 | O23: =L23 -> 0 | P23: =M23 -> 0 | Q23: =N23 -> 0 | R23: =SUM(O23:Q25) -> 0 | S23: =R23 -> 0 | T23: 0 | U23: =S23-T23-T24-T25 -> 0 | V23: =S23*0.8 -> 0 | X23: =V23-W23-W24-W25 -> 0 | Y23: =S23*0.17/1.065 -> 0 | AB23: =V23*0.2/1.065 -> 0 | AH23: =V23-Y23-AB23-AG23-AG24-AG25 -> 0
T24: 0
T25: 0
A26: 8 | B26: 京青线米家堡路口专项设计工程 | C26: 2025.4 | D26: 道路开口 | F26: HNJH2025-008 | O26: =L26 -> 0 | P26: =M26 -> 0 | Q26: =N26 -> 0 | R26: =SUM(O26:Q28) -> 0 | S26: =R26 -> 0 | T26: 0 | U26: =S26-T26-T27-T28 -> 0 | V26: =S26*0.8 -> 0 | X26: =V26-W26-W27-W28 -> 0 | Y26: =S26*0.17/1.065 -> 0 | AB26: =V26*0.2/1.065 -> 0 | AH26: =V26-Y26-AB26-AG26-AG27-AG28 -> 0
T27: 0
T28: 0
O29: =L29 -> 0 | P29: =M29 -> 0 | Q29: =N29 -> 0 | R29: =SUM(O29:Q31) -> 0 | S29: =R29 -> 0 | T29: 0 | U29: =S29-T29-T30-T31 -> 0 | V29: =S29*0.8 -> 0 | X29: =V29-W29-W30-W31 -> 0 | Y29: =S29*0.17/1.065 -> 0 | AB29: =V29*0.2/1.065 -> 0 | AH29: =V29-Y29-AB29-AG29-AG30-AG31 -> 0
T30: 0
T31: 0
A32: 总计 | I32: =SUM(I5:I31) -> 876300 | J32: =SUM(J5:J31) -> 0 | K32: =SUM(K5:K31) -> 0 | L32: =SUM(L5:L31) -> 0 | M32: =SUM(M5:M31) -> 0 | N32: =SUM(N5:N31) -> 468000 | O32: =SUM(#REF!) -> #REF! | P32: =SUM(#REF!) -> #REF! | Q32: =SUM(#REF!) -> #REF! | R32: =SUM(#REF!) -> #REF! | S32: =SUM(#REF!) -> #REF! | T32: =SUM(#REF!) -> #REF! | U32: =SUM(#REF!) -> #REF! | V32: =SUM(#REF!) -> #REF! | ... Y32: =SUM(#REF!) -> #REF! | AB32: =SUM(#REF!) -> #REF! | AG32: =SUM(#REF!) -> #REF! | AH32: =SUM(#REF!) -> #REF!

Sheet 年度汇总表
A1: 年度汇总表
A2: 序号 | B2: 年度 | C2: 甲方信息 | F2: 公司信息
C3: 支付信息 | F3: 收入信息 | I3: 支出信息
C4: 应支额 | D4: 已支额 | E4: 未支额 | F4: 应收额 | G4: 已收额 | H4: 未收额 | I4: 应支额 | J4: 支付额 | K4: 未支额
A5: 1 | B5: 2017 | C5: ='2017 '!T94 -> 10379510 | D5: ='2017 '!U94 -> 9964678.6 | E5: ='2017 '!V94 -> 414831.06 | F5: ='2017 '!W94 -> 8193929.2 | G5: ='2017 '!X94 -> 7910342.8 | H5: ='2017 '!Y94 -> 283586.45 | I5: ='2017 '!AB94 -> 604647.5
A6: =A5+1 -> 2 | B6: =B5+1 -> 2018 | C6: ='2018'!U53 -> 9794836.2 | D6: ='2018'!V53 -> 6041016.5 | E6: ='2018'!W53 -> 3753819.7 | F6: ='2018'!X53 -> 7601716.2 | G6: ='2018'!Y53 -> 4622090.4 | H6: ='2018'!Z53 -> 2979625.8 | I6: ='2018'!AC53 -> 181984.66
A7: =A6+1 -> 3 | B7: =B6+1 -> 2019 | C7: ='2019'!V93 -> 9631415.9 | D7: ='2019'!X93 -> 7202868.5 | E7: ='2019'!Y93 -> 2428547.5 | F7: ='2019'!Z93 -> 7683562.6 | G7: ='2019'!AB93 -> 4714887.7 | H7: ='2019'!AC93 -> 2725746.2 | I7: ='2019'!AF93 -> 526679
A8: =A7+1 -> 4 | B8: =B7+1 -> 2020 | C8: ='2020'!V53 -> 2659884 | D8: ='2020'!X53 -> 2659884 | E8: ='2020'!Y53 -> 3.6379788e-12 | F8: ='2020'!Z53 -> 2096665.5 | G8: ='2020'!AB53 -> 2079932.2 | H8: ='2020'!AC53 -> 16733.324 | I8: ='2020'!AF53 -> 359883.9
A9: =A8+1 -> 5 | B9: =B8+1 -> 2021 | C9: ='2021'!V63 -> 4949660.6 | D9: ='2021'!W63 -> 2250842 | E9: ='2021'!X63 -> 2698818.5 | F9: ='2021'!Y63 -> 4006859.9 | G9: ='2021'!Z63 -> 1817704.8 | H9: ='2021'!AA63 -> 2189155.1 | I9: ='2021'!AF63 -> 1160693.8
A10: =A9+1 -> 6 | B10: =B9+1 -> 2022 | C10: ='2022'!V41 -> 2472393.8 | D10: ='2022'!W41 -> 1018770.1 | E10: ='2022'!X41 -> 1453623.7 | F10: ='2022'!Y41 -> 1877560.2 | G10: ='2022'!Z41 -> 572215.03 | H10: ='2022'!AA41 -> 1176971.6 | I10: ='2022'!AF41 -> 86152.5
A11: =A10+1 -> 7 | B11: =B10+1 -> 2023 | C11: ='2023 '!S122 -> 2777717.8 | D11: ='2023 '!T122 -> 1819232.8 | E11: ='2023 '!U122 -> 958485 | F11: ='2023 '!V122 -> 2239244.8 | G11: ='2023 '!W122 -> 1435886.5 | H11: ='2023 '!X122 -> 803358.29 | I11: ='2023 '!Y122 -> 443391.58
A12: =A11+1 -> 8 | B12: =B11+1 -> 2024 | C12: ='2024'!S191 -> 3980370.9 | D12: ='2024'!T191 -> 1780562.7 | E12: ='2024'!U191 -> 2199808.2 | F12: ='2024'!V191 -> 3253833 | G12: ='2024'!W191 -> 861822.34 | H12: ='2024'!X191 -> 2392010.6 | I12: ='2024'!Y191 -> 626990.32
A13: =A12+1 -> 9 | B13: =B12+1 -> 2025
A14: 合计 | C14: =SUM(C5:C13) -> 46645789 | D14: =SUM(D5:D13) -> 32737855 | E14: =SUM(E5:E13) -> 13907934 | F14: =SUM(F5:F13) -> 36953371 | G14: =SUM(G5:G13) -> 24014882 | H14: =SUM(H5:H13) -> 12567187 | I14: =SUM(I5:I13) -> 3990423.2 | J14: =SUM(J5:J13) -> 0 | K14: =SUM(K5:K13) -> 0
